Workbook

Sheet SQL
A1: select cr.includename, cr.isinactive, cr.name, LOWER(cr.scriptid) as record_id, cf.fieldtype, cf.fieldvaluetype, cf.fieldvaluetyperecord, cf.name, LOWER(cf.scriptid) as field_id from customrecordtype cr join customfield cf on cf.recordtype = cr.internalid where cr.scriptid like '%TWC%' order by cr.scriptid, cf.scriptid

Sheet LIVE
A1: includename | B1: isinactive | C1: name | D1: record_id | E1: TABLE IN SB | F1: fieldtype | G1: fieldvaluetype | H1: fieldvaluetyperecord | I1: name_0 | J1: field_id | K1: IN SB
A2: T | B2: F | C2: OSSMTWC - AWL Type | D2: customrecord_ossm_twc_awl_type | E2: =VLOOKUP(D2,'TABLES SB'!D:D,1,FALSE) -> customrecord_ossm_twc_awl_type | K2: =IF(J2="","",VLOOKUP(J2,SB!I:I,1,FALSE))
A3: T | B3: F | C3: OSSMTWC - FE Last Test Result | D3: customrecord_ossm_twc_fe_last_test_res | E3: =VLOOKUP(D3,'TABLES SB'!D:D,1,FALSE) -> customrecord_ossm_twc_fe_last_test_res | K3: =IF(J3="","",VLOOKUP(J3,SB!I:I,1,FALSE))
A4: T | B4: F | C4: OSSMTWC - FE Type | D4: customrecord_ossm_twc_fe_type | E4: =VLOOKUP(D4,'TABLES SB'!D:D,1,FALSE) -> customrecord_ossm_twc_fe_type | K4: =IF(J4="","",VLOOKUP(J4,SB!I:I,1,FALSE))
A5: T | B5: F | C5: OSSMTWC - FIRE EXTINGUISHER | D5: customrecord_ossm_twc_fire_extinguisher | E5: =VLOOKUP(D5,'TABLES SB'!D:D,1,FALSE) -> customrecord_ossm_twc_fire_extinguisher | F5: RECORD | G5: List/Record | H5: 1071 | I5: Accommodation | J5: custrecord_twc_fe_acc | K5: =IF(J5="","",VLOOKUP(J5,SB!I:I,1,FALSE)) -> custrecord_twc_fe_acc
A6: T | B6: F | C6: OSSMTWC - FIRE EXTINGUISHER | D6: customrecord_ossm_twc_fire_extinguisher | E6: =VLOOKUP(D6,'TABLES SB'!D:D,1,FALSE) -> customrecord_ossm_twc_fire_extinguisher | F6: RECORD | G6: Text Area | I6: Comments | J6: custrecord_twc_fe_comments | K6: =IF(J6="","",VLOOKUP(J6,SB!I:I,1,FALSE)) -> custrecord_twc_fe_comments
A7: T | B7: F | C7: OSSMTWC - FIRE EXTINGUISHER | D7: customrecord_ossm_twc_fire_extinguisher | E7: =VLOOKUP(D7,'TABLES SB'!D:D,1,FALSE) -> customrecord_ossm_twc_fire_extinguisher | F7: RECORD | G7: Free-Form Text | I7: Fire Extinguisher ID | J7: custrecord_twc_fe_id | K7: =IF(J7="","",VLOOKUP(J7,SB!I:I,1,FALSE)) -> custrecord_twc_fe_id
A8: T | B8: F | C8: OSSMTWC - FIRE EXTINGUISHER | D8: customrecord_ossm_twc_fire_extinguisher | E8: =VLOOKUP(D8,'TABLES SB'!D:D,1,FALSE) -> customrecord_ossm_twc_fire_extinguisher | F8: RECORD | G8: Date | I8: Installed Date | J8: custrecord_twc_fe_inst_date | K8: =IF(J8="","",VLOOKUP(J8,SB!I:I,1,FALSE)) -> custrecord_twc_fe_inst_date
A9: T | B9: F | C9: OSSMTWC - FIRE EXTINGUISHER | D9: customrecord_ossm_twc_fire_extinguisher | E9: =VLOOKUP(D9,'TABLES SB'!D:D,1,FALSE) -> customrecord_ossm_twc_fire_extinguisher | F9: RECORD | G9: Date | I9: Refill Date | J9: custrecord_twc_fe_refill_date | K9: =IF(J9="","",VLOOKUP(J9,SB!I:I,1,FALSE)) -> custrecord_twc_fe_refill_date
A10: T | B10: F | C10: OSSMTWC - FIRE EXTINGUISHER | D10: customrecord_ossm_twc_fire_extinguisher | E10: =VLOOKUP(D10,'TABLES SB'!D:D,1,FALSE) -> customrecord_ossm_twc_fire_extinguisher | F10: RECORD | G10: List/Record | H10: 1148 | I10: Site | J10: custrecord_twc_fe_site | K10: =IF(J10="","",VLOOKUP(J10,SB!I:I,1,FALSE)) -> custrecord_twc_fe_site
A11: T | B11: F | C11: OSSMTWC - FIRE EXTINGUISHER | D11: customrecord_ossm_twc_fire_extinguisher | E11: =VLOOKUP(D11,'TABLES SB'!D:D,1,FALSE) -> customrecord_ossm_twc_fire_extinguisher | F11: RECORD | G11: List/Record | H11: 1803 | I11: FE Status | J11: custrecord_twc_fe_status | K11: =IF(J11="","",VLOOKUP(J11,SB!I:I,1,FALSE)) -> custrecord_twc_fe_status
A12: T | B12: F | C12: OSSMTWC - FIRE EXTINGUISHER | D12: customrecord_ossm_twc_fire_extinguisher | E12: =VLOOKUP(D12,'TABLES SB'!D:D,1,FALSE) -> customrecord_ossm_twc_fire_extinguisher | F12: RECORD | G12: List/Record | H12: 1801 | I12: FE Type | J12: custrecord_twc_fe_ty | K12: =IF(J12="","",VLOOKUP(J12,SB!I:I,1,FALSE)) -> custrecord_twc_fe_ty
A13: T | B13: F | C13: OSSMTWC - FIRE EXTINGUISHER | D13: customrecord_ossm_twc_fire_extinguisher | E13: =VLOOKUP(D13,'TABLES SB'!D:D,1,FALSE) -> customrecord_ossm_twc_fire_extinguisher | F13: RECORD | G13: Integer Number | I13: Year of Manufacture | J13: custrecord_twc_fe_yom | K13: =IF(J13="","",VLOOKUP(J13,SB!I:I,1,FALSE)) -> custrecord_twc_fe_yom
A14: T | B14: F | C14: OSSMTWC - FIRE EXTINGUISHER | D14: customrecord_ossm_twc_fire_extinguisher | E14: =VLOOKUP(D14,'TABLES SB'!D:D,1,FALSE) -> customrecord_ossm_twc_fire_extinguisher | F14: RECORD | G14: List/Record | H14: 1800 | I14: Last Test Result | J14: custrecord_twc_last_test_res | K14: =IF(J14="","",VLOOKUP(J14,SB!I:I,1,FALSE)) -> custrecord_twc_last_test_res
A15: T | B15: F | C15: OSSMTWC - FIRE EXTINGUISHER | D15: customrecord_ossm_twc_fire_extinguisher | E15: =VLOOKUP(D15,'TABLES SB'!D:D,1,FALSE) -> customrecord_ossm_twc_fire_extinguisher | F15: RECORD | G15: Free-Form Text | I15: Location | J15: custrecord_twc_location | K15: =IF(J15="","",VLOOKUP(J15,SB!I:I,1,FALSE)) -> custrecord_twc_location
A16: F | B16: T | C16: OSSMTWC - Accommodation | D16: customrecord_twc_ac | E16: =VLOOKUP(D16,'TABLES SB'!D:D,1,FALSE) -> customrecord_twc_ac | F16: RECORD | G16: List/Record | H16: 1024 | I16: AC Feed Phase | J16: custrecord_twc_ac_ac_feed_phase | K16: =IF(J16="","",VLOOKUP(J16,SB!I:I,1,FALSE)) -> custrecord_twc_ac_ac_feed_phase
A17: F | B17: T | C17: OSSMTWC - Accommodation | D17: customrecord_twc_ac | E17: =VLOOKUP(D17,'TABLES SB'!D:D,1,FALSE) -> customrecord_twc_ac | F17: RECORD | G17: Free-Form Text | I17: Comments | J17: custrecord_twc_ac_comments | K17: =IF(J17="","",VLOOKUP(J17,SB!I:I,1,FALSE)) -> custrecord_twc_ac_comments
A18: F | B18: T | C18: OSSMTWC - Accommodation | D18: customrecord_twc_ac | E18: =VLOOKUP(D18,'TABLES SB'!D:D,1,FALSE) -> customrecord_twc_ac | F18: RECORD | G18: List/Record | H18: 1060 | I18: Facilities Services | J18: custrecord_twc_ac_fac_svc | K18: =IF(J18="","",VLOOKUP(J18,SB!I:I,1,FALSE)) -> custrecord_twc_ac_fac_svc
A19: F | B19: T | C19: OSSMTWC - Accommodation | D19: customrecord_twc_ac | E19: =VLOOKUP(D19,'TABLES SB'!D:D,1,FALSE) -> customrecord_twc_ac | F19: RECORD | G19: Check Box | I19: Fire Alarm Present | J19: custrecord_twc_ac_fire_alarm_pres | K19: =IF(J19="","",VLOOKUP(J19,SB!I:I,1,FALSE)) -> custrecord_twc_ac_fire_alarm_pres
A20: F | B20: T | C20: OSSMTWC - Accommodation | D20: customrecord_twc_ac | E20: =VLOOKUP(D20,'TABLES SB'!D:D,1,FALSE) -> customrecord_twc_ac | F20: RECORD | G20: Free-Form Text | I20: Height (m) | J20: custrecord_twc_ac_height | K20: =IF(J20="","",VLOOKUP(J20,SB!I:I,1,FALSE)) -> custrecord_twc_ac_height
A21: F | B21: T | C21: OSSMTWC - Accommodation | D21: customrecord_twc_ac | E21: =VLOOKUP(D21,'TABLES SB'!D:D,1,FALSE) -> customrecord_twc_ac | F21: RECORD | G21: Free-Form Text | I21: Infrastructure ID | J21: custrecord_twc_ac_infra_id | K21: =IF(J21="","",VLOOKUP(J21,SB!I:I,1,FALSE)) -> custrecord_twc_ac_infra_id
A22: F | B22: T | C22: OSSMTWC - Accommodation | D22: customrecord_twc_ac | E22: =VLOOKUP(D22,'TABLES SB'!D:D,1,FALSE) -> customrecord_twc_ac | F22: RECORD | G22: Date | I22: Installed | J22: custrecord_twc_ac_installed | K22: =IF(J22="","",VLOOKUP(J22,SB!I:I,1,FALSE)) -> custrecord_twc_ac_installed
A23: F | B23: T | C23: OSSMTWC - Accommodation | D23: customrecord_twc_ac | E23: =VLOOKUP(D23,'TABLES SB'!D:D,1,FALSE) -> customrecord_twc_ac | F23: RECORD | G23: Check Box | I23: Intruder Alarm Present | J23: custrecord_twc_ac_intruder_alarm_pres | K23: =IF(J23="","",VLOOKUP(J23,SB!I:I,1,FALSE)) -> custrecord_twc_ac_intruder_alarm_pres
A24: F | B24: T | C24: OSSMTWC - Accommodation | D24: customrecord_twc_ac | E24: =VLOOKUP(D24,'TABLES SB'!D:D,1,FALSE) -> customrecord_twc_ac | F24: RECORD | G24: Free-Form Text | I24: Intruder Code | J24: custrecord_twc_ac_intruder_code | K24: =IF(J24="","",VLOOKUP(J24,SB!I:I,1,FALSE)) -> custrecord_twc_ac_intruder_code
A25: F | B25: T | C25: OSSMTWC - Accommodation | D25: customrecord_twc_ac | E25: =VLOOKUP(D25,'TABLES SB'!D:D,1,FALSE) -> customrecord_twc_ac | F25: RECORD | G25: Free-Form Text | I25: Length (m) | J25: custrecord_twc_ac_length | K25: =IF(J25="","",VLOOKUP(J25,SB!I:I,1,FALSE)) -> custrecord_twc_ac_length
A26: F | B26: T | C26: OSSMTWC - Accommodation | D26: customrecord_twc_ac | E26: =VLOOKUP(D26,'TABLES SB'!D:D,1,FALSE) -> customrecord_twc_ac | F26: RECORD | G26: Integer Number | I26: Loadings | J26: custrecord_twc_ac_loadings | K26: =IF(J26="","",VLOOKUP(J26,SB!I:I,1,FALSE)) -> custrecord_twc_ac_loadings
A27: F | B27: T | C27: OSSMTWC - Accommodation | D27: customrecord_twc_ac | E27: =VLOOKUP(D27,'TABLES SB'!D:D,1,FALSE) -> customrecord_twc_ac | F27: RECORD | G27: List/Record | H27: 1106 | I27: Lock | J27: custrecord_twc_ac_lock | K27: =IF(J27="","",VLOOKUP(J27,SB!I:I,1,FALSE)) -> custrecord_twc_ac_lock
A28: F | B28: T | C28: OSSMTWC - Accommodation | D28: customrecord_twc_ac | E28: =VLOOKUP(D28,'TABLES SB'!D:D,1,FALSE) -> customrecord_twc_ac | F28: RECORD | G28: Free-Form Text | I28: Model | J28: custrecord_twc_ac_model | K28: =IF(J28="","",VLOOKUP(J28,SB!I:I,1,FALSE)) -> custrecord_twc_ac_model
A29: F | B29: T | C29: OSSMTWC - Accommodation | D29: customrecord_twc_ac | E29: =VLOOKUP(D29,'TABLES SB'!D:D,1,FALSE) -> customrecord_twc_ac | F29: RECORD | G29: Integer Number | I29: Noise Level | J29: custrecord_twc_ac_noice_level | K29: =IF(J29="","",VLOOKUP(J29,SB!I:I,1,FALSE)) -> custrecord_twc_ac_noice_level
A30: F | B30: T | C30: OSSMTWC - Accommodation | D30: customrecord_twc_ac | E30: =VLOOKUP(D30,'TABLES SB'!D:D,1,FALSE) -> customrecord_twc_ac | F30: RECORD | G30: Date | I30: Next Aircon Service | J30: custrecord_twc_ac_nxt_aircon_svc | K30: =IF(J30="","",VLOOKUP(J30,SB!I:I,1,FALSE)) -> custrecord_twc_ac_nxt_aircon_svc
A31: F | B31: T | C31: OSSMTWC - Accommodation | D31: customrecord_twc_ac | E31: =VLOOKUP(D31,'TABLES SB'!D:D,1,FALSE) -> customrecord_twc_ac | F31: RECORD | G31: Date | I31: Next Alarm Service | J31: custrecord_twc_ac_nxt_alarm_svc | K31: =IF(J31="","",VLOOKUP(J31,SB!I:I,1,FALSE)) -> custrecord_twc_ac_nxt_alarm_svc
A32: F | B32: T | C32: OSSMTWC - Accommodation | D32: customrecord_twc_ac | E32: =VLOOKUP(D32,'TABLES SB'!D:D,1,FALSE) -> customrecord_twc_ac | F32: RECORD | G32: Date | I32: Next Fire Service | J32: custrecord_twc_ac_nxt_fire_svc | K32: =IF(J32="","",VLOOKUP(J32,SB!I:I,1,FALSE)) -> custrecord_twc_ac_nxt_fire_svc
A33: F | B33: T | C33: OSSMTWC - Accommodation | D33: customrecord_twc_ac | E33: =VLOOKUP(D33,'TABLES SB'!D:D,1,FALSE) -> customrecord_twc_ac | F33: RECORD | G33: List/Record | H33: 1153 | I33: Public | J33: custrecord_twc_ac_public | K33: =IF(J33="","",VLOOKUP(J33,SB!I:I,1,FALSE)) -> custrecord_twc_ac_public
A34: F | B34: T | C34: OSSMTWC - Accommodation | D34: customrecord_twc_ac | E34: =VLOOKUP(D34,'TABLES SB'!D:D,1,FALSE) -> customrecord_twc_ac | F34: RECORD | G34: Integer Number | I34: Rack Spaces Available | J34: custrecord_twc_ac_rack_spaces_available | K34: =IF(J34="","",VLOOKUP(J34,SB!I:I,1,FALSE)) -> custrecord_twc_ac_rack_spaces_available
A35: F | B35: T | C35: OSSMTWC - Accommodation | D35: customrecord_twc_ac | E35: =VLOOKUP(D35,'TABLES SB'!D:D,1,FALSE) -> customrecord_twc_ac | F35: RECORD | G35: Check Box | I35: SAF Auto-Approve | J35: custrecord_twc_ac_saf_auto_approve | K35: =IF(J35="","",VLOOKUP(J35,SB!I:I,1,FALSE)) -> custrecord_twc_ac_saf_auto_approve
A36: F | B36: T | C36: OSSMTWC - Accommodation | D36: customrecord_twc_ac | E36: =VLOOKUP(D36,'TABLES SB'!D:D,1,FALSE) -> customrecord_twc_ac | F36: RECORD | G36: List/Record | H36: 1025 | I36: SAF Status | J36: custrecord_twc_ac_saf_sts | K36: =IF(J36="","",VLOOKUP(J36,SB!I:I,1,FALSE)) -> custrecord_twc_ac_saf_sts
A37: F | B37: T | C37: OSSMTWC - Accommodation | D37: customrecord_twc_ac | E37: =VLOOKUP(D37,'TABLES SB'!D:D,1,FALSE) -> customrecord_twc_ac | F37: RECORD | G37: List/Record | H37: 1148 | I37: Site | J37: custrecord_twc_ac_site | K37: =IF(J37="","",VLOOKUP(J37,SB!I:I,1,FALSE)) -> custrecord_twc_ac_site
A38: F | B38: T | C38: OSSMTWC - Accommodation | D38: customrecord_twc_ac | E38: =VLOOKUP(D38,'TABLES SB'!D:D,1,FALSE) -> customrecord_twc_ac | F38: RECORD | G38: List/Record | H38: 1026 | I38: SRF Status | J38: custrecord_twc_ac_srf_sts | K38: =IF(J38="","",VLOOKUP(J38,SB!I:I,1,FALSE)) -> custrecord_twc_ac_srf_sts
A39: F | B39: T | C39: OSSMTWC - Accommodation | D39: customrecord_twc_ac | E39: =VLOOKUP(D39,'TABLES SB'!D:D,1,FALSE) -> customrecord_twc_ac | F39: RECORD | G39: List/Record | H39: 1027 | I39: Accommodation Status | J39: custrecord_twc_ac_sts | K39: =IF(J39="","",VLOOKUP(J39,SB!I:I,1,FALSE)) -> custrecord_twc_ac_sts
A40: F | B40: T | C40: OSSMTWC - Accommodation | D40: customrecord_twc_ac | E40: =VLOOKUP(D40,'TABLES SB'!D:D,1,FALSE) -> customrecord_twc_ac | F40: RECORD | G40: List/Record | H40: 1028 | I40: Accommodation Type | J40: custrecord_twc_ac_type | K40: =IF(J40="","",VLOOKUP(J40,SB!I:I,1,FALSE)) -> custrecord_twc_ac_type
A41: F | B41: T | C41: OSSMTWC - Accommodation | D41: customrecord_twc_ac | E41: =VLOOKUP(D41,'TABLES SB'!D:D,1,FALSE) -> customrecord_twc_ac | F41: RECORD | G41: Integer Number | I41: Units | J41: custrecord_twc_ac_units | K41: =IF(J41="","",VLOOKUP(J41,SB!I:I,1,FALSE)) -> custrecord_twc_ac_units
A42: F | B42: T | C42: OSSMTWC - Accommodation | D42: customrecord_twc_ac | E42: =VLOOKUP(D42,'TABLES SB'!D:D,1,FALSE) -> customrecord_twc_ac | F42: RECORD | G42: Free-Form Text | I42: Width (m) | J42: custrecord_twc_ac_width | K42: =IF(J42="","",VLOOKUP(J42,SB!I:I,1,FALSE)) -> custrecord_twc_ac_width
A43: T | B43: T | C43: OSSMTWC - Accommodation SAF Status | D43: customrecord_twc_accom_saf_sts | E43: =VLOOKUP(D43,'TABLES SB'!D:D,1,FALSE) -> customrecord_twc_accom_saf_sts | K43: =IF(J43="","",VLOOKUP(J43,SB!I:I,1,FALSE))
A44: T | B44: T | C44: OSSMTWC - Accommodation SRF Status | D44: customrecord_twc_accom_srf_sts | E44: =VLOOKUP(D44,'TABLES SB'!D:D,1,FALSE) -> customrecord_twc_accom_srf_sts | K44: =IF(J44="","",VLOOKUP(J44,SB!I:I,1,FALSE))
A45: T | B45: T | C45: OSSMTWC - Accommodation Status | D45: customrecord_twc_accom_sts | E45: =VLOOKUP(D45,'TABLES SB'!D:D,1,FALSE) -> customrecord_twc_accom_sts | K45: =IF(J45="","",VLOOKUP(J45,SB!I:I,1,FALSE))
A46: T | B46: F | C46: OSSMTWC - Accommodation Type | D46: customrecord_twc_accom_type | E46: =VLOOKUP(D46,'TABLES SB'!D:D,1,FALSE) -> customrecord_twc_accom_type | K46: =IF(J46="","",VLOOKUP(J46,SB!I:I,1,FALSE))
A47: F | B47: F | C47: OSSMTWC - ACL | D47: customrecord_twc_acl | E47: =VLOOKUP(D47,'TABLES SB'!D:D,1,FALSE) -> customrecord_twc_acl | F47: RECORD | G47: List/Record | H47: 1042 | I47: Contractor | J47: custrecord_twc_acl_cont | K47: =IF(J47="","",VLOOKUP(J47,SB!I:I,1,FALSE)) -> custrecord_twc_acl_cont
A48: F | B48: F | C48: OSSMTWC - ACL | D48: customrecord_twc_acl | E48: =VLOOKUP(D48,'TABLES SB'!D:D,1,FALSE) -> customrecord_twc_acl | F48: RECORD | G48: List/Record | H48: 1042 | I48: Customer | J48: custrecord_twc_acl_cust | K48: =IF(J48="","",VLOOKUP(J48,SB!I:I,1,FALSE)) -> custrecord_twc_acl_cust
A49: T | B49: F | C49: OSSMTWC - Active/Passive | D49: customrecord_twc_active_passive | E49: =VLOOKUP(D49,'TABLES SB'!D:D,1,FALSE) -> customrecord_twc_active_passive | K49: =IF(J49="","",VLOOKUP(J49,SB!I:I,1,FALSE))
A50: T | B50: F | C50: OSSMTWC - AC Feed Phase | D50: customrecord_twc_ac_feed_phase | E50: =VLOOKUP(D50,'TABLES SB'!D:D,1,FALSE) -> customrecord_twc_ac_feed_phase | K50: =IF(J50="","",VLOOKUP(J50,SB!I:I,1,FALSE))
A51: T | B51: F | C51: OSSMTWC - A/C Model | D51: customrecord_twc_ac_model | E51: =VLOOKUP(D51,'TABLES SB'!D:D,1,FALSE) -> customrecord_twc_ac_model | K51: =IF(J51="","",VLOOKUP(J51,SB!I:I,1,FALSE))
A52: T | B52: F | C52: OSSMTWC - A/C Units | D52: customrecord_twc_ac_unit | E52: =VLOOKUP(D52,'TABLES SB'!D:D,1,FALSE) -> customrecord_twc_ac_unit | F52: RECORD | G52: List/Record | H52: 1148 | I52: Site | J52: custrecord_twc_actable_site | K52: =IF(J52="","",VLOOKUP(J52,SB!I:I,1,FALSE)) -> custrecord_twc_actable_site
A53: T | B53: F | C53: OSSMTWC - A/C Units | D53: customrecord_twc_ac_unit | E53: =VLOOKUP(D53,'TABLES SB'!D:D,1,FALSE) -> customrecord_twc_ac_unit | F53: RECORD | G53: List/Record | H53: 1071 | I53: Accommodation | J53: custrecord_twc_ac_accom | K53: =IF(J53="","",VLOOKUP(J53,SB!I:I,1,FALSE)) -> custrecord_twc_ac_accom
A54: T | B54: F | C54: OSSMTWC - A/C Units | D54: customrecord_twc_ac_unit | E54: =VLOOKUP(D54,'TABLES SB'!D:D,1,FALSE) -> customrecord_twc_ac_unit | F54: RECORD | G54: List/Record | H54: 1397 | I54: Model | J54: custrecord_twc_ac_mod | K54: =IF(J54="","",VLOOKUP(J54,SB!I:I,1,FALSE)) -> custrecord_twc_ac_mod
A55: T | B55: F | C55: OSSMTWC - A/C Units | D55: customrecord_twc_ac_unit | E55: =VLOOKUP(D55,'TABLES SB'!D:D,1,FALSE) -> customrecord_twc_ac_unit | F55: RECORD | G55: List/Record | H55: 1398 | I55: A/C Unit Status | J55: custrecord_twc_ac_unit_status | K55: =IF(J55="","",VLOOKUP(J55,SB!I:I,1,FALSE)) -> custrecord_twc_ac_unit_status
A56: T | B56: F | C56: OSSMTWC - A/C Units | D56: customrecord_twc_ac_unit | E56: =VLOOKUP(D56,'TABLES SB'!D:D,1,FALSE) -> customrecord_twc_ac_unit | F56: RECORD | G56: Text Area | I56: Comments | J56: custrecord_twc_comments | K56: =IF(J56="","",VLOOKUP(J56,SB!I:I,1,FALSE)) -> #N/A | L56: Field in SB ha different ID
A57: T | B57: F | C57: OSSMTWC - A/C Units | D57: customrecord_twc_ac_unit | E57: =VLOOKUP(D57,'TABLES SB'!D:D,1,FALSE) -> customrecord_twc_ac_unit | F57: RECORD | G57: List/Record | H57: 1024 | I57: Feed Phase | J57: custrecord_twc_feed_pha | K57: =IF(J57="","",VLOOKUP(J57,SB!I:I,1,FALSE)) -> custrecord_twc_feed_pha
A58: T | B58: F | C58: OSSMTWC - A/C Units | D58: customrecord_twc_ac_unit | E58: =VLOOKUP(D58,'TABLES SB'!D:D,1,FALSE) -> customrecord_twc_ac_unit | F58: RECORD | G58: Date | I58: Installed Date | J58: custrecord_twc_inst_date | K58: =IF(J58="","",VLOOKUP(J58,SB!I:I,1,FALSE)) -> custrecord_twc_inst_date
A59: T | B59: F | C59: OSSMTWC - A/C Units | D59: customrecord_twc_ac_unit | E59: =VLOOKUP(D59,'TABLES SB'!D:D,1,FALSE) -> customrecord_twc_ac_unit | F59: RECORD | G59: Decimal Number | I59: Refrigerant amount (kg) | J59: custrecord_twc_refrig_amt | K59: =IF(J59="","",VLOOKUP(J59,SB!I:I,1,FALSE)) -> custrecord_twc_refrig_amt
A60: T | B60: F | C60: OSSMTWC - A/C Units | D60: customrecord_twc_ac_unit | E60: =VLOOKUP(D60,'TABLES SB'!D:D,1,FALSE) -> customrecord_twc_ac_unit | F60: RECORD | G60: List/Record | H60: 1399 | I60: System Refrigerant | J60: custrecord_twc_sys_refr | K60: =IF(J60="","",VLOOKUP(J60,SB!I:I,1,FALSE)) -> custrecord_twc_sys_refr
A61: T | B61: F | C61: OSSM TWC - A/C Unit Status | D61: customrecord_twc_ac_unit_status | E61: =VLOOKUP(D61,'TABLES SB'!D:D,1,FALSE) -> customrecord_twc_ac_unit_status | K61: =IF(J61="","",VLOOKUP(J61,SB!I:I,1,FALSE))
A62: F | B62: F | C62: OSSMTWC - Agreement | D62: customrecord_twc_agreement | E62: =VLOOKUP(D62,'TABLES SB'!D:D,1,FALSE) -> customrecord_twc_agreement | F62: RECORD | G62: Free-Form Text | I62: Agreement Code | J62: custrecord_twc_agreement_code | K62: =IF(J62="","",VLOOKUP(J62,SB!I:I,1,FALSE)) -> custrecord_twc_agreement_code
A63: F | B63: F | C63: OSSMTWC - Agreement | D63: customrecord_twc_agreement | E63: =VLOOKUP(D63,'TABLES SB'!D:D,1,FALSE) -> customrecord_twc_agreement | F63: RECORD | G63: List/Record | H63: 1042 | I63: Customer | J63: custrecord_twc_agreement_customer | K63: =IF(J63="","",VLOOKUP(J63,SB!I:I,1,FALSE)) -> custrecord_twc_agreement_customer
A64: F | B64: F | C64: OSSMTWC - Agreement | D64: customrecord_twc_agreement | E64: =VLOOKUP(D64,'TABLES SB'!D:D,1,FALSE) -> customrecord_twc_agreement | F64: RECORD | G64: Date | I64: Agreement Date | J64: custrecord_twc_agreement_date | K64: =IF(J64="","",VLOOKUP(J64,SB!I:I,1,FALSE)) -> custrecord_twc_agreement_date
A65: F | B65: F | C65: OSSMTWC - Agreement | D65: customrecord_twc_agreement | E65: =VLOOKUP(D65,'TABLES SB'!D:D,1,FALSE) -> customrecord_twc_agreement | F65: RECORD | G65: Date | I65: Agreement Expiry | J65: custrecord_twc_agreement_expiry | K65: =IF(J65="","",VLOOKUP(J65,SB!I:I,1,FALSE)) -> custrecord_twc_agreement_expiry
A66: F | B66: F | C66: OSSMTWC - Agreement | D66: customrecord_twc_agreement | E66: =VLOOKUP(D66,'TABLES SB'!D:D,1,FALSE) -> customrecord_twc_agreement | F66: RECORD | G66: Free-Form Text | I66: Agreement Name | J66: custrecord_twc_agreement_name | K66: =IF(J66="","",VLOOKUP(J66,SB!I:I,1,FALSE)) -> custrecord_twc_agreement_name
A67: F | B67: F | C67: OSSMTWC - Agreement | D67: customrecord_twc_agreement | E67: =VLOOKUP(D67,'TABLES SB'!D:D,1,FALSE) -> customrecord_twc_agreement | F67: RECORD | G67: Free-Form Text | I67: Party | J67: custrecord_twc_agreement_party | K67: =IF(J67="","",VLOOKUP(J67,SB!I:I,1,FALSE)) -> custrecord_twc_agreement_party
A68: F | B68: F | C68: OSSMTWC - Agreement | D68: customrecord_twc_agreement | E68: =VLOOKUP(D68,'TABLES SB'!D:D,1,FALSE) -> customrecord_twc_agreement | F68: RECORD | G68: Free-Form Text | I68: Rate Card | J68: custrecord_twc_agreement_rate_card | K68: =IF(J68="","",VLOOKUP(J68,SB!I:I,1,FALSE)) -> custrecord_twc_agreement_rate_card
A69: F | B69: F | C69: OSSMTWC - Agreement | D69: customrecord_twc_agreement | E69: =VLOOKUP(D69,'TABLES SB'!D:D,1,FALSE) -> customrecord_twc_agreement | F69: RECORD | G69: Free-Form Text | I69: Agreement Template | J69: custrecord_twc_agreement_template | K69: =IF(J69="","",VLOOKUP(J69,SB!I:I,1,FALSE)) -> custrecord_twc_agreement_template
A70: F | B70: F | C70: OSSMTWC - ASCL | D70: customrecord_twc_ascl | E70: =VLOOKUP(D70,'TABLES SB'!D:D,1,FALSE) -> customrecord_twc_ascl | F70: RECORD | G70: List/Record | H70: 1042 | I70: Contractor | J70: custrecord_twc_acl_contractor | K70: =IF(J70="","",VLOOKUP(J70,SB!I:I,1,FALSE)) -> custrecord_twc_acl_contractor
A71: F | B71: F | C71: OSSMTWC - ASCL | D71: customrecord_twc_ascl | E71: =VLOOKUP(D71,'TABLES SB'!D:D,1,FALSE) -> customrecord_twc_ascl | F71: RECORD | G71: List/Record | H71: 1042 | I71: Sub Contractor | J71: custrecord_twc_acl_sub_contractor | K71: =IF(J71="","",VLOOKUP(J71,SB!I:I,1,FALSE)) -> custrecord_twc_acl_sub_contractor
A72: F | B72: F | C72: OSSMTWC - AWL | D72: customrecord_twc_awl | E72: =VLOOKUP(D72,'TABLES SB'!D:D,1,FALSE) -> customrecord_twc_awl | F72: RECORD | G72: Integer Number | I72: Height | J72: custrecord_twc_awl_height | K72: =IF(J72="","",VLOOKUP(J72,SB!I:I,1,FALSE)) -> custrecord_twc_awl_height
A73: F | B73: F | C73: OSSMTWC - AWL | D73: customrecord_twc_awl | E73: =VLOOKUP(D73,'TABLES SB'!D:D,1,FALSE) -> customrecord_twc_awl | F73: RECORD | G73: List/Record | H73: 1071 | I73: Infrastructure | J73: custrecord_twc_awl_infra | K73: =IF(J73="","",VLOOKUP(J73,SB!I:I,1,FALSE)) -> custrecord_twc_awl_infra
A74: F | B74: F | C74: OSSMTWC - AWL | D74: customrecord_twc_awl | E74: =VLOOKUP(D74,'TABLES SB'!D:D,1,FALSE) -> customrecord_twc_awl | F74: RECORD | G74: List/Record | H74: 1034 | I74: Intensity | J74: custrecord_twc_awl_intensity | K74: =IF(J74="","",VLOOKUP(J74,SB!I:I,1,FALSE)) -> custrecord_twc_awl_intensity
A75: F | B75: F | C75: OSSMTWC - AWL | D75: customrecord_twc_awl | E75: =VLOOKUP(D75,'TABLES SB'!D:D,1,FALSE) -> customrecord_twc_awl | F75: RECORD | G75: List/Record | H75: 1148 | I75: Site | J75: custrecord_twc_awl_site | K75: =IF(J75="","",VLOOKUP(J75,SB!I:I,1,FALSE)) -> custrecord_twc_awl_site
A76: F | B76: F | C76: OSSMTWC - AWL | D76: customrecord_twc_awl | E76: =VLOOKUP(D76,'TABLES SB'!D:D,1,FALSE) -> customrecord_twc_awl | F76: RECORD | G76: List/Record | H76: 1700 | I76: AWL Type | J76: custrecord_twc_awl_type | K76: =IF(J76="","",VLOOKUP(J76,SB!I:I,1,FALSE)) -> custrecord_twc_awl_type
A77: F | B77: F | C77: OSSMTWC - AWL | D77: customrecord_twc_awl | E77: =VLOOKUP(D77,'TABLES SB'!D:D,1,FALSE) -> customrecord_twc_awl | F77: RECORD | G77: List/Record | H77: 1699 | I77: Voltage | J77: custrecord_twc_awl_volt | K77: =IF(J77="","",VLOOKUP(J77,SB!I:I,1,FALSE)) -> custrecord_twc_awl_volt
A78: F | B78: F | C78: OSSMTWC - AWL | D78: customrecord_twc_awl | E78: =VLOOKUP(D78,'TABLES SB'!D:D,1,FALSE) -> customrecord_twc_awl | F78: RECORD | G78: Date | I78: Installation Date | J78: custrecord_twc_install_date | K78: =IF(J78="","",VLOOKUP(J78,SB!I:I,1,FALSE)) -> custrecord_twc_install_date
A79: T | B79: F | C79: OSSMTWC - AWL Intensity | D79: customrecord_twc_awl_intensity | E79: =VLOOKUP(D79,'TABLES SB'!D:D,1,FALSE) -> customrecord_twc_awl_intensity | K79: =IF(J79="","",VLOOKUP(J79,SB!I:I,1,FALSE))
A80: F | B80: F | C80: OSSMTWC - Capacity Review | D80: customrecord_twc_capacity_review | E80: =VLOOKUP(D80,'TABLES SB'!D:D,1,FALSE) -> customrecord_twc_capacity_review | F80: RECORD | G80: Text Area | I80: Comments | J80: custrecord_twc_cap_rev_comments | K80: =IF(J80="","",VLOOKUP(J80,SB!I:I,1,FALSE)) -> custrecord_twc_cap_rev_comments
A81: F | B81: F | C81: OSSMTWC - Capacity Review | D81: customrecord_twc_capacity_review | E81: =VLOOKUP(D81,'TABLES SB'!D:D,1,FALSE) -> customrecord_twc_capacity_review | F81: RECORD | G81: List/Record | H81: 1042 | I81: Company Reviewed By | J81: custrecord_twc_cap_rev_co_rev_by | K81: =IF(J81="","",VLOOKUP(J81,SB!I:I,1,FALSE)) -> custrecord_twc_cap_rev_co_rev_by
A82: F | B82: F | C82: OSSMTWC - Capacity Review | D82: customrecord_twc_capacity_review | E82: =VLOOKUP(D82,'TABLES SB'!D:D,1,FALSE) -> customrecord_twc_capacity_review | F82: RECORD | G82: Integer Number | I82: Existing Foundation Capacity (%) | J82: custrecord_twc_cap_rev_exg_fndn_capacity | K82: =IF(J82="","",VLOOKUP(J82,SB!I:I,1,FALSE)) -> custrecord_twc_cap_rev_exg_fndn_capacity
A83: F | B83: F | C83: OSSMTWC - Capacity Review | D83: customrecord_twc_capacity_review | E83: =VLOOKUP(D83,'TABLES SB'!D:D,1,FALSE) -> customrecord_twc_capacity_review | F83: RECORD | G83: Decimal Number | I83: Existing Foundation Overturning (kNm) | J83: custrecord_twc_cap_rev_exg_found_ot | K83: =IF(J83="","",VLOOKUP(J83,SB!I:I,1,FALSE)) -> custrecord_twc_cap_rev_exg_found_ot
A84: F | B84: F | C84: OSSMTWC - Capacity Review | D84: customrecord_twc_capacity_review | E84: =VLOOKUP(D84,'TABLES SB'!D:D,1,FALSE) -> customrecord_twc_capacity_review | F84: RECORD | G84: Integer Number | I84: Existing Structure Capacity (%) | J84: custrecord_twc_cap_rev_exg_stru_capacity | K84: =IF(J84="","",VLOOKUP(J84,SB!I:I,1,FALSE)) -> custrecord_twc_cap_rev_exg_stru_capacity
A85: F | B85: F | C85: OSSMTWC - Capacity Review | D85: customrecord_twc_capacity_review | E85: =VLOOKUP(D85,'TABLES SB'!D:D,1,FALSE) -> customrecord_twc_capacity_review | F85: RECORD | G85: Decimal Number | I85: Existing Structure Equipment Loading (危 E-BM_(m虏.m)) | J85: custrecord_twc_cap_rev_exg_stru_equip | K85: =IF(J85="","",VLOOKUP(J85,SB!I:I,1,FALSE)) -> custrecord_twc_cap_rev_exg_stru_equip
A86: F | B86: F | C86: OSSMTWC - Capacity Review | D86: customrecord_twc_capacity_review | E86: =VLOOKUP(D86,'TABLES SB'!D:D,1,FALSE) -> customrecord_twc_capacity_review | F86: RECORD | G86: Integer Number | I86: Future Foundation Capacity (%) | J86: custrecord_twc_cap_rev_futu_fndn_cap | K86: =IF(J86="","",VLOOKUP(J86,SB!I:I,1,FALSE)) -> custrecord_twc_cap_rev_futu_fndn_cap
A87: F | B87: F | C87: OSSMTWC - Capacity Review | D87: customrecord_twc_capacity_review | E87: =VLOOKUP(D87,'TABLES SB'!D:D,1,FALSE) -> customrecord_twc_capacity_review | F87: RECORD | G87: Decimal Number | I87: Future Foundation Overturning (kNm) | J87: custrecord_twc_cap_rev_futu_fndn_ot | K87: =IF(J87="","",VLOOKUP(J87,SB!I:I,1,FALSE)) -> custrecord_twc_cap_rev_futu_fndn_ot
A88: F | B88: F | C88: OSSMTWC - Capacity Review | D88: customrecord_twc_capacity_review | E88: =VLOOKUP(D88,'TABLES SB'!D:D,1,FALSE) -> customrecord_twc_capacity_review | F88: RECORD | G88: Integer Number | I88: Future Structure Capacity (%) | J88: custrecord_twc_cap_rev_futu_stru_cap | K88: =IF(J88="","",VLOOKUP(J88,SB!I:I,1,FALSE)) -> custrecord_twc_cap_rev_futu_stru_cap
A89: F | B89: F | C89: OSSMTWC - Capacity Review | D89: customrecord_twc_capacity_review | E89: =VLOOKUP(D89,'TABLES SB'!D:D,1,FALSE) -> customrecord_twc_capacity_review | F89: RECORD | G89: Decimal Number | I89: Future Structure Equipment Loading (危 E-BM_(m虏.m)) | J89: custrecord_twc_cap_rev_fut_stru_equip | K89: =IF(J89="","",VLOOKUP(J89,SB!I:I,1,FALSE)) -> custrecord_twc_cap_rev_fut_stru_equip
A90: F | B90: F | C90: OSSMTWC - Capacity Review | D90: customrecord_twc_capacity_review | E90: =VLOOKUP(D90,'TABLES SB'!D:D,1,FALSE) -> customrecord_twc_capacity_review | F90: RECORD | G90: List/Record | H90: 1071 | I90: Infrastructure | J90: custrecord_twc_cap_rev_infra | K90: =IF(J90="","",VLOOKUP(J90,SB!I:I,1,FALSE)) -> custrecord_twc_cap_rev_infra
A91: F | B91: F | C91: OSSMTWC - Capacity Review | D91: customrecord_twc_capacity_review | E91: =VLOOKUP(D91,'TABLES SB'!D:D,1,FALSE) -> customrecord_twc_capacity_review | F91: RECORD | G91: List/Record | H91: 1118 | I91: Person Reviewed by | J91: custrecord_twc_cap_rev_person_rev_by | K91: =IF(J91="","",VLOOKUP(J91,SB!I:I,1,FALSE)) -> custrecord_twc_cap_rev_person_rev_by
A92: F | B92: F | C92: OSSMTWC - Capacity Review | D92: customrecord_twc_capacity_review | E92: =VLOOKUP(D92,'TABLES SB'!D:D,1,FALSE) -> customrecord_twc_capacity_review | F92: RECORD | G92: Date | I92: Review Date | J92: custrecord_twc_cap_rev_review_date | K92: =IF(J92="","",VLOOKUP(J92,SB!I:I,1,FALSE)) -> custrecord_twc_cap_rev_review_date
A93: F | B93: F | C93: OSSMTWC - Capacity Review | D93: customrecord_twc_capacity_review | E93: =VLOOKUP(D93,'TABLES SB'!D:D,1,FALSE) -> customrecord_twc_capacity_review | F93: RECORD | G93: List/Record | H93: 1148 | I93: Site | J93: custrecord_twc_cap_rev_site | K93: =IF(J93="","",VLOOKUP(J93,SB!I:I,1,FALSE)) -> custrecord_twc_cap_rev_site
A94: T | B94: F | C94: OSSMTWC - Company | D94: customrecord_twc_company | E94: =VLOOKUP(D94,'TABLES SB'!D:D,1,FALSE) -> customrecord_twc_company | F94: RECORD | G94: List/Record | H94: -9 | I94: Entity | J94: custrecordtwc_entity | K94: =IF(J94="","",VLOOKUP(J94,SB!I:I,1,FALSE)) -> custrecordtwc_entity
A95: T | B95: F | C95: OSSMTWC - Company | D95: customrecord_twc_company | E95: =VLOOKUP(D95,'TABLES SB'!D:D,1,FALSE) -> customrecord_twc_company | F95: RECORD | G95: List/Record | H95: 1043 | I95: Contractor Flag | J95: custrecord_twc_con_flag | K95: =IF(J95="","",VLOOKUP(J95,SB!I:I,1,FALSE)) -> custrecord_twc_con_flag
A96: T | B96: F | C96: OSSMTWC - Company | D96: customrecord_twc_company | E96: =VLOOKUP(D96,'TABLES SB'!D:D,1,FALSE) -> customrecord_twc_company | F96: RECORD | G96: Date | I96: Accreditation Approved | J96: custrecord_twc_co_accred_appr | K96: =IF(J96="","",VLOOKUP(J96,SB!I:I,1,FALSE)) -> custrecord_twc_co_accred_appr
A97: T | B97: F | C97: OSSMTWC - Company | D97: customrecord_twc_company | E97: =VLOOKUP(D97,'TABLES SB'!D:D,1,FALSE) -> customrecord_twc_company | F97: RECORD | G97: Date | I97: Accredited Contractor Commencement | J97: custrecord_twc_co_accred_cont_comm | K97: =IF(J97="","",VLOOKUP(J97,SB!I:I,1,FALSE)) -> custrecord_twc_co_accred_cont_comm
A98: T | B98: F | C98: OSSMTWC - Company | D98: customrecord_twc_company | E98: =VLOOKUP(D98,'TABLES SB'!D:D,1,FALSE) -> customrecord_twc_company | F98: RECORD | G98: Date | I98: Accredited Contractor Expiry | J98: custrecord_twc_co_accred_cont_exp | K98: =IF(J98="","",VLOOKUP(J98,SB!I:I,1,FALSE)) -> custrecord_twc_co_accred_cont_exp
A99: T | B99: F | C99: OSSMTWC - Company | D99: customrecord_twc_company | E99: =VLOOKUP(D99,'TABLES SB'!D:D,1,FALSE) -> customrecord_twc_company | F99: RECORD | G99: Currency | I99: Accredited Contractor Fee | J99: custrecord_twc_co_accred_cont_fee | K99: =IF(J99="","",VLOOKUP(J99,SB!I:I,1,FALSE)) -> custrecord_twc_co_accred_cont_fee
A100: T | B100: F | C100: OSSMTWC - Company | D100: customrecord_twc_company | E100: =VLOOKUP(D100,'TABLES SB'!D:D,1,FALSE) -> customrecord_twc_company | F100: RECORD | G100: List/Record | H100: 1036 | I100: Accreditation Status | J100: custrecord_twc_co_accred_status | K100: =IF(J100="","",VLOOKUP(J100,SB!I:I,1,FALSE)) -> custrecord_twc_co_accred_status
...

Sheet SB
A1: includename | B1: isinactive | C1: name | D1: record_id | E1: fieldtype | F1: fieldvaluetype | G1: fieldvaluetyperecord | H1: name_0 | I1: field_id
A2: T | B2: F | C2: OSSMTWC - Power Meter | D2: customrecordcustomrecord_twc_pwr_mtr | E2: RECORD | F2: Text Area | G2: null | H2: Meter Comment | I2: custrecord_twc_pwr_mtr_comm
A3: T | B3: F | C3: OSSMTWC - Power Meter | D3: customrecordcustomrecord_twc_pwr_mtr | E3: RECORD | F3: Free-Form Text | G3: null | H3: Power Meter ID | I3: custrecord_twc_pwr_mtr_id
A4: T | B4: F | C4: OSSMTWC - Power Meter | D4: customrecordcustomrecord_twc_pwr_mtr | E4: RECORD | F4: Integer Number | G4: null | H4: Latest Day Reading | I4: custrecord_twc_pwr_mtr_last_day_read
A5: T | B5: F | C5: OSSMTWC - Power Meter | D5: customrecordcustomrecord_twc_pwr_mtr | E5: RECORD | F5: Integer Number | G5: null | H5: Latest Night Reading | I5: custrecord_twc_pwr_mtr_last_night_read
A6: T | B6: F | C6: OSSMTWC - Power Meter | D6: customrecordcustomrecord_twc_pwr_mtr | E6: RECORD | F6: Integer Number | G6: null | H6: Latest Peak Reading | I6: custrecord_twc_pwr_mtr_last_peak_read
A7: T | B7: F | C7: OSSMTWC - Power Meter | D7: customrecordcustomrecord_twc_pwr_mtr | E7: RECORD | F7: Date | G7: null | H7: Latest Meter Reading Date | I7: custrecord_twc_pwr_mtr_last_read_date
A8: T | B8: F | C8: OSSMTWC - Power Meter | D8: customrecordcustomrecord_twc_pwr_mtr | E8: RECORD | F8: Decimal Number | G8: null | H8: Latest kWh Usage - Reading | I8: custrecord_twc_pwr_mtr_last_usage
A9: T | B9: F | C9: OSSMTWC - Power Meter | D9: customrecordcustomrecord_twc_pwr_mtr | E9: RECORD | F9: Decimal Number | G9: null | H9: Latest kWh Usage - Amp Check | I9: custrecord_twc_pwr_mtr_last_usage_amp
A10: T | B10: F | C10: OSSMTWC - Power Meter | D10: customrecordcustomrecord_twc_pwr_mtr | E10: RECORD | F10: Free-Form Text | G10: null | H10: Meter Location | I10: custrecord_twc_pwr_mtr_loc
A11: T | B11: F | C11: OSSMTWC - Power Meter | D11: customrecordcustomrecord_twc_pwr_mtr | E11: RECORD | F11: List/Record | G11: 1069 | H11: Meter Unit Multiplier | I11: custrecord_twc_pwr_mtr_mult
A12: T | B12: F | C12: OSSMTWC - Power Meter | D12: customrecordcustomrecord_twc_pwr_mtr | E12: RECORD | F12: Check Box | G12: null | H12: Power Supplier must read Meter | I12: custrecord_twc_pwr_mtr_mustread
A13: T | B13: F | C13: OSSMTWC - Power Meter | D13: customrecordcustomrecord_twc_pwr_mtr | E13: RECORD | F13: Free-Form Text | G13: null | H13: Meter Name | I13: custrecord_twc_pwr_mtr_name
A14: T | B14: F | C14: OSSMTWC - Power Meter | D14: customrecordcustomrecord_twc_pwr_mtr | E14: RECORD | F14: Free-Form Text | G14: null | H14: Meter Number | I14: custrecord_twc_pwr_mtr_num
A15: T | B15: F | C15: OSSMTWC - Power Meter | D15: customrecordcustomrecord_twc_pwr_mtr | E15: RECORD | F15: Date | G15: null | H15: Next Meter Reading Date | I15: custrecord_twc_pwr_mtr_nxt_read
A16: T | B16: F | C16: OSSMTWC - Power Meter | D16: customrecordcustomrecord_twc_pwr_mtr | E16: RECORD | F16: List/Record | G16: 830 | H16: Meter Power Phase | I16: custrecord_twc_pwr_mtr_phase
A17: T | B17: F | C17: OSSMTWC - Power Meter | D17: customrecordcustomrecord_twc_pwr_mtr | E17: RECORD | F17: Integer Number | G17: null | H17: Meter Reading Freq | I17: custrecord_twc_pwr_mtr_read_freq
A18: T | B18: F | C18: OSSMTWC - Power Meter | D18: customrecordcustomrecord_twc_pwr_mtr | E18: RECORD | F18: List/Record | G18: 718 | H18: Site | I18: custrecord_twc_pwr_mtr_site
A19: T | B19: F | C19: OSSMTWC - Power Meter | D19: customrecordcustomrecord_twc_pwr_mtr | E19: RECORD | F19: List/Record | G19: 676 | H19: Power Supply | I19: custrecord_twc_pwr_mtr_sply
A20: T | B20: F | C20: OSSMTWC - Power Meter | D20: customrecordcustomrecord_twc_pwr_mtr | E20: RECORD | F20: List/Record | G20: 1061 | H20: Meter Status | I20: custrecord_twc_pwr_mtr_sts
A21: T | B21: F | C21: OSSMTWC - Power Meter | D21: customrecordcustomrecord_twc_pwr_mtr | E21: RECORD | F21: Check Box | G21: null | H21: Supplier Informed | I21: custrecord_twc_pwr_mtr_supplier_informed
A22: T | B22: F | C22: OSSMTWC - Power Meter | D22: customrecordcustomrecord_twc_pwr_mtr | E22: RECORD | F22: List/Record | G22: 1065 | H22: Meter Type | I22: custrecord_twc_pwr_mtr_type
A23: T | B23: F | C23: OSSMTWC - AWL Type | D23: customrecord_ossm_twc_awl_type | E23: null | F23: null | G23: null | H23: null | I23: null
A24: T | B24: F | C24: OSSMTWC - FE Last Test Result | D24: customrecord_ossm_twc_fe_last_test_res | E24: null | F24: null | G24: null | H24: null | I24: null
A25: T | B25: F | C25: OSSMTWC - FE Type | D25: customrecord_ossm_twc_fe_type | E25: null | F25: null | G25: null | H25: null | I25: null
A26: T | B26: F | C26: OSSMTWC - FIRE EXTINGUISHER | D26: customrecord_ossm_twc_fire_extinguisher | E26: RECORD | F26: List/Record | G26: 815 | H26: Accommodation | I26: custrecord_twc_fe_acc
A27: T | B27: F | C27: OSSMTWC - FIRE EXTINGUISHER | D27: customrecord_ossm_twc_fire_extinguisher | E27: RECORD | F27: Text Area | G27: null | H27: Comments | I27: custrecord_twc_fe_comments
A28: T | B28: F | C28: OSSMTWC - FIRE EXTINGUISHER | D28: customrecord_ossm_twc_fire_extinguisher | E28: RECORD | F28: Free-Form Text | G28: null | H28: Fire Extinguisher ID | I28: custrecord_twc_fe_id
A29: T | B29: F | C29: OSSMTWC - FIRE EXTINGUISHER | D29: customrecord_ossm_twc_fire_extinguisher | E29: RECORD | F29: Date | G29: null | H29: Installed Date | I29: custrecord_twc_fe_inst_date
A30: T | B30: F | C30: OSSMTWC - FIRE EXTINGUISHER | D30: customrecord_ossm_twc_fire_extinguisher | E30: RECORD | F30: Date | G30: null | H30: Refill Date | I30: custrecord_twc_fe_refill_date
A31: T | B31: F | C31: OSSMTWC - FIRE EXTINGUISHER | D31: customrecord_ossm_twc_fire_extinguisher | E31: RECORD | F31: List/Record | G31: 718 | H31: Site | I31: custrecord_twc_fe_site
A32: T | B32: F | C32: OSSMTWC - FIRE EXTINGUISHER | D32: customrecord_ossm_twc_fire_extinguisher | E32: RECORD | F32: List/Record | G32: 1057 | H32: FE Status | I32: custrecord_twc_fe_status
A33: T | B33: F | C33: OSSMTWC - FIRE EXTINGUISHER | D33: customrecord_ossm_twc_fire_extinguisher | E33: RECORD | F33: List/Record | G33: 1058 | H33: FE Type | I33: custrecord_twc_fe_ty
A34: T | B34: F | C34: OSSMTWC - FIRE EXTINGUISHER | D34: customrecord_ossm_twc_fire_extinguisher | E34: RECORD | F34: Integer Number | G34: null | H34: Year of Manufacture | I34: custrecord_twc_fe_yom
A35: T | B35: F | C35: OSSMTWC - FIRE EXTINGUISHER | D35: customrecord_ossm_twc_fire_extinguisher | E35: RECORD | F35: List/Record | G35: 1059 | H35: Last Test Result | I35: custrecord_twc_last_test_res
A36: T | B36: F | C36: OSSMTWC - FIRE EXTINGUISHER | D36: customrecord_ossm_twc_fire_extinguisher | E36: RECORD | F36: Free-Form Text | G36: null | H36: Location | I36: custrecord_twc_location
A37: F | B37: T | C37: OSSMTWC - Accommodation | D37: customrecord_twc_ac | E37: RECORD | F37: List/Record | G37: 699 | H37: AC Feed Phase | I37: custrecord_twc_ac_ac_feed_phase
A38: F | B38: T | C38: OSSMTWC - Accommodation | D38: customrecord_twc_ac | E38: RECORD | F38: Free-Form Text | G38: null | H38: Comments | I38: custrecord_twc_ac_comments
A39: F | B39: T | C39: OSSMTWC - Accommodation | D39: customrecord_twc_ac | E39: RECORD | F39: List/Record | G39: 688 | H39: Facilities Services | I39: custrecord_twc_ac_fac_svc
A40: F | B40: T | C40: OSSMTWC - Accommodation | D40: customrecord_twc_ac | E40: RECORD | F40: Check Box | G40: null | H40: Fire Alarm Present | I40: custrecord_twc_ac_fire_alarm_pres
A41: F | B41: T | C41: OSSMTWC - Accommodation | D41: customrecord_twc_ac | E41: RECORD | F41: Free-Form Text | G41: null | H41: Height (m) | I41: custrecord_twc_ac_height
A42: F | B42: T | C42: OSSMTWC - Accommodation | D42: customrecord_twc_ac | E42: RECORD | F42: Free-Form Text | G42: null | H42: Infrastructure ID | I42: custrecord_twc_ac_infra_id
A43: F | B43: T | C43: OSSMTWC - Accommodation | D43: customrecord_twc_ac | E43: RECORD | F43: Date | G43: null | H43: Installed | I43: custrecord_twc_ac_installed
A44: F | B44: T | C44: OSSMTWC - Accommodation | D44: customrecord_twc_ac | E44: RECORD | F44: Check Box | G44: null | H44: Intruder Alarm Present | I44: custrecord_twc_ac_intruder_alarm_pres
A45: F | B45: T | C45: OSSMTWC - Accommodation | D45: customrecord_twc_ac | E45: RECORD | F45: Free-Form Text | G45: null | H45: Intruder Code | I45: custrecord_twc_ac_intruder_code
A46: F | B46: T | C46: OSSMTWC - Accommodation | D46: customrecord_twc_ac | E46: RECORD | F46: Free-Form Text | G46: null | H46: Length (m) | I46: custrecord_twc_ac_length
A47: F | B47: T | C47: OSSMTWC - Accommodation | D47: customrecord_twc_ac | E47: RECORD | F47: Integer Number | G47: null | H47: Loadings | I47: custrecord_twc_ac_loadings
A48: F | B48: T | C48: OSSMTWC - Accommodation | D48: customrecord_twc_ac | E48: RECORD | F48: List/Record | G48: 693 | H48: Lock | I48: custrecord_twc_ac_lock
A49: F | B49: T | C49: OSSMTWC - Accommodation | D49: customrecord_twc_ac | E49: RECORD | F49: Free-Form Text | G49: null | H49: Model | I49: custrecord_twc_ac_model
A50: F | B50: T | C50: OSSMTWC - Accommodation | D50: customrecord_twc_ac | E50: RECORD | F50: Integer Number | G50: null | H50: Noise Level | I50: custrecord_twc_ac_noice_level
A51: F | B51: T | C51: OSSMTWC - Accommodation | D51: customrecord_twc_ac | E51: RECORD | F51: Date | G51: null | H51: Next Aircon Service | I51: custrecord_twc_ac_nxt_aircon_svc
A52: F | B52: T | C52: OSSMTWC - Accommodation | D52: customrecord_twc_ac | E52: RECORD | F52: Date | G52: null | H52: Next Alarm Service | I52: custrecord_twc_ac_nxt_alarm_svc
A53: F | B53: T | C53: OSSMTWC - Accommodation | D53: customrecord_twc_ac | E53: RECORD | F53: Date | G53: null | H53: Next Fire Service | I53: custrecord_twc_ac_nxt_fire_svc
A54: F | B54: T | C54: OSSMTWC - Accommodation | D54: customrecord_twc_ac | E54: RECORD | F54: List/Record | G54: 684 | H54: Public | I54: custrecord_twc_ac_public
A55: F | B55: T | C55: OSSMTWC - Accommodation | D55: customrecord_twc_ac | E55: RECORD | F55: Integer Number | G55: null | H55: Rack Spaces Available | I55: custrecord_twc_ac_rack_spaces_available
A56: F | B56: T | C56: OSSMTWC - Accommodation | D56: customrecord_twc_ac | E56: RECORD | F56: Check Box | G56: null | H56: SAF Auto-Approve | I56: custrecord_twc_ac_saf_auto_approve
A57: F | B57: T | C57: OSSMTWC - Accommodation | D57: customrecord_twc_ac | E57: RECORD | F57: List/Record | G57: 698 | H57: SAF Status | I57: custrecord_twc_ac_saf_sts
A58: F | B58: T | C58: OSSMTWC - Accommodation | D58: customrecord_twc_ac | E58: RECORD | F58: List/Record | G58: 718 | H58: Site | I58: custrecord_twc_ac_site
A59: F | B59: T | C59: OSSMTWC - Accommodation | D59: customrecord_twc_ac | E59: RECORD | F59: List/Record | G59: 697 | H59: SRF Status | I59: custrecord_twc_ac_srf_sts
A60: F | B60: T | C60: OSSMTWC - Accommodation | D60: customrecord_twc_ac | E60: RECORD | F60: List/Record | G60: 695 | H60: Accommodation Status | I60: custrecord_twc_ac_sts
A61: F | B61: T | C61: OSSMTWC - Accommodation | D61: customrecord_twc_ac | E61: RECORD | F61: List/Record | G61: 694 | H61: Accommodation Type | I61: custrecord_twc_ac_type
A62: F | B62: T | C62: OSSMTWC - Accommodation | D62: customrecord_twc_ac | E62: RECORD | F62: Integer Number | G62: null | H62: Units | I62: custrecord_twc_ac_units
A63: F | B63: T | C63: OSSMTWC - Accommodation | D63: customrecord_twc_ac | E63: RECORD | F63: Free-Form Text | G63: null | H63: Width (m) | I63: custrecord_twc_ac_width
A64: T | B64: T | C64: OSSMTWC - Accommodation SAF Status | D64: customrecord_twc_accom_saf_sts | E64: null | F64: null | G64: null | H64: null | I64: null
A65: T | B65: T | C65: OSSMTWC - Accommodation SRF Status | D65: customrecord_twc_accom_srf_sts | E65: null | F65: null | G65: null | H65: null | I65: null
A66: T | B66: T | C66: OSSMTWC - Accommodation Status | D66: customrecord_twc_accom_sts | E66: null | F66: null | G66: null | H66: null | I66: null
A67: T | B67: F | C67: OSSMTWC - Accommodation Type | D67: customrecord_twc_accom_type | E67: null | F67: null | G67: null | H67: null | I67: null
A68: F | B68: F | C68: OSSMTWC - ACL | D68: customrecord_twc_acl | E68: RECORD | F68: List/Record | G68: 634 | H68: Contractor | I68: custrecord_twc_acl_cont
A69: F | B69: F | C69: OSSMTWC - ACL | D69: customrecord_twc_acl | E69: RECORD | F69: List/Record | G69: 634 | H69: Customer | I69: custrecord_twc_acl_cust
A70: T | B70: F | C70: OSSMTWC - Active/Passive | D70: customrecord_twc_active_passive | E70: null | F70: null | G70: null | H70: null | I70: null
A71: T | B71: F | C71: OSSMTWC - AC Feed Phase | D71: customrecord_twc_ac_feed_phase | E71: null | F71: null | G71: null | H71: null | I71: null
A72: T | B72: F | C72: OSSMTWC - A/C Model | D72: customrecord_twc_ac_model | E72: null | F72: null | G72: null | H72: null | I72: null
A73: T | B73: F | C73: OSSMTWC - A/C Units | D73: customrecord_twc_ac_unit | E73: RECORD | F73: Text Area | G73: null | H73: Comments | I73: custrecord2
A74: T | B74: F | C74: OSSMTWC - A/C Units | D74: customrecord_twc_ac_unit | E74: RECORD | F74: List/Record | G74: 718 | H74: Site | I74: custrecord_twc_actable_site
A75: T | B75: F | C75: OSSMTWC - A/C Units | D75: customrecord_twc_ac_unit | E75: RECORD | F75: List/Record | G75: 815 | H75: Accommodation | I75: custrecord_twc_ac_accom
A76: T | B76: F | C76: OSSMTWC - A/C Units | D76: customrecord_twc_ac_unit | E76: RECORD | F76: List/Record | G76: 1049 | H76: Model | I76: custrecord_twc_ac_mod
A77: T | B77: F | C77: OSSMTWC - A/C Units | D77: customrecord_twc_ac_unit | E77: RECORD | F77: List/Record | G77: 1048 | H77: A/C Unit Status | I77: custrecord_twc_ac_unit_status
A78: T | B78: F | C78: OSSMTWC - A/C Units | D78: customrecord_twc_ac_unit | E78: RECORD | F78: List/Record | G78: 699 | H78: Feed Phase | I78: custrecord_twc_feed_pha
A79: T | B79: F | C79: OSSMTWC - A/C Units | D79: customrecord_twc_ac_unit | E79: RECORD | F79: Date | G79: null | H79: Installed Date | I79: custrecord_twc_inst_date
A80: T | B80: F | C80: OSSMTWC - A/C Units | D80: customrecord_twc_ac_unit | E80: RECORD | F80: Decimal Number | G80: null | H80: Refrigerant amount (kg) | I80: custrecord_twc_refrig_amt
A81: T | B81: F | C81: OSSMTWC - A/C Units | D81: customrecord_twc_ac_unit | E81: RECORD | F81: List/Record | G81: 1050 | H81: System Refrigerant | I81: custrecord_twc_sys_refr
A82: T | B82: F | C82: OSSM TWC - A/C Unit Status | D82: customrecord_twc_ac_unit_status | E82: null | F82: null | G82: null | H82: null | I82: null
A83: T | B83: F | C83: OSSMTWC - SDS Agreement | D83: customrecord_twc_agreement | E83: RECORD | F83: Free-Form Text | G83: null | H83: Agreement Code | I83: custrecord_twc_agreement_code
A84: T | B84: F | C84: OSSMTWC - SDS Agreement | D84: customrecord_twc_agreement | E84: RECORD | F84: List/Record | G84: 634 | H84: Customer | I84: custrecord_twc_agreement_customer
A85: T | B85: F | C85: OSSMTWC - SDS Agreement | D85: customrecord_twc_agreement | E85: RECORD | F85: Date | G85: null | H85: Agreement Date | I85: custrecord_twc_agreement_date
A86: T | B86: F | C86: OSSMTWC - SDS Agreement | D86: customrecord_twc_agreement | E86: RECORD | F86: Date | G86: null | H86: Agreement Expiry | I86: custrecord_twc_agreement_expiry
A87: T | B87: F | C87: OSSMTWC - SDS Agreement | D87: customrecord_twc_agreement | E87: RECORD | F87: Free-Form Text | G87: null | H87: Agreement Name | I87: custrecord_twc_agreement_name
A88: T | B88: F | C88: OSSMTWC - SDS Agreement | D88: customrecord_twc_agreement | E88: RECORD | F88: Free-Form Text | G88: null | H88: Party | I88: custrecord_twc_agreement_party
A89: T | B89: F | C89: OSSMTWC - SDS Agreement | D89: customrecord_twc_agreement | E89: RECORD | F89: Free-Form Text | G89: null | H89: Rate Card | I89: custrecord_twc_agreement_rate_card
A90: T | B90: F | C90: OSSMTWC - SDS Agreement | D90: customrecord_twc_agreement | E90: RECORD | F90: Free-Form Text | G90: null | H90: Agreement Template | I90: custrecord_twc_agreement_template
A91: F | B91: F | C91: OSSMTWC - SDS Agreement Condition | D91: customrecord_twc_agreement_cond | E91: RECORD | F91: Multiple Select | G91: 634 | H91: Applicable to Customers | I91: custrecord_twc_agreement_cond_cust
A92: F | B92: F | C92: OSSMTWC - SDS Agreement Condition | D92: customrecord_twc_agreement_cond | E92: RECORD | F92: Check Box | G92: null | H92: Applicable to all customers | I92: custrecord_twc_agreement_cond_cust_all
A93: F | B93: F | C93: OSSMTWC - SDS Agreement Condition | D93: customrecord_twc_agreement_cond | E93: RECORD | F93: Free-Form Text | G93: null | H93: Description | I93: custrecord_twc_agreement_cond_descr
A94: F | B94: F | C94: OSSMTWC - SDS Agreement Condition | D94: customrecord_twc_agreement_cond | E94: RECORD | F94: Free-Form Text | G94: null | H94: Field 1 Name | I94: custrecord_twc_agreement_cond_field_1
A95: F | B95: F | C95: OSSMTWC - SDS Agreement Condition | D95: customrecord_twc_agreement_cond | E95: RECORD | F95: Free-Form Text | G95: null | H95: Field 10 Name | I95: custrecord_twc_agreement_cond_field_10
A96: F | B96: F | C96: OSSMTWC - SDS Agreement Condition | D96: customrecord_twc_agreement_cond | E96: RECORD | F96: Free-Form Text | G96: null | H96: Field 2 Name | I96: custrecord_twc_agreement_cond_field_2
A97: F | B97: F | C97: OSSMTWC - SDS Agreement Condition | D97: customrecord_twc_agreement_cond | E97: RECORD | F97: Free-Form Text | G97: null | H97: Field 3 Name | I97: custrecord_twc_agreement_cond_field_3
A98: F | B98: F | C98: OSSMTWC - SDS Agreement Condition | D98: customrecord_twc_agreement_cond | E98: RECORD | F98: Free-Form Text | G98: null | H98: Field 4 Name | I98: custrecord_twc_agreement_cond_field_4
A99: F | B99: F | C99: OSSMTWC - SDS Agreement Condition | D99: customrecord_twc_agreement_cond | E99: RECORD | F99: Free-Form Text | G99: null | H99: Field 5 Name | I99: custrecord_twc_agreement_cond_field_5
A100: F | B100: F | C100: OSSMTWC - SDS Agreement Condition | D100: customrecord_twc_agreement_cond | E100: RECORD | F100: Free-Form Text | G100: null | H100: Field 6 Name | I100: custrecord_twc_agreement_cond_field_6
...

Sheet TABLES LIVE
A1: includename | B1: isinactive | C1: name | D1: record_id | E1: IN SB
A2: T | B2: F | C2: OSSM TWC - A/C Unit Status | D2: customrecord_twc_ac_unit_status | E2: =VLOOKUP(D2,'TABLES SB'!D:D,1,FALSE) -> customrecord_twc_ac_unit_status
A3: T | B3: F | C3: OSSMTWC - A/C Model | D3: customrecord_twc_ac_model | E3: =VLOOKUP(D3,'TABLES SB'!D:D,1,FALSE) -> customrecord_twc_ac_model
A4: T | B4: F | C4: OSSMTWC - A/C System Refrigerant | D4: customrecord_twc_sys_refrig | E4: =VLOOKUP(D4,'TABLES SB'!D:D,1,FALSE) -> customrecord_twc_sys_refrig
A5: T | B5: F | C5: OSSMTWC - A/C Units | D5: customrecord_twc_ac_unit | E5: =VLOOKUP(D5,'TABLES SB'!D:D,1,FALSE) -> customrecord_twc_ac_unit
A6: T | B6: F | C6: OSSMTWC - AC Feed Phase | D6: customrecord_twc_ac_feed_phase | E6: =VLOOKUP(D6,'TABLES SB'!D:D,1,FALSE) -> customrecord_twc_ac_feed_phase
A7: F | B7: F | C7: OSSMTWC - ACL | D7: customrecord_twc_acl | E7: =VLOOKUP(D7,'TABLES SB'!D:D,1,FALSE) -> customrecord_twc_acl
A8: F | B8: F | C8: OSSMTWC - ASCL | D8: customrecord_twc_ascl | E8: =VLOOKUP(D8,'TABLES SB'!D:D,1,FALSE) -> customrecord_twc_ascl
A9: F | B9: F | C9: OSSMTWC - AWL | D9: customrecord_twc_awl | E9: =VLOOKUP(D9,'TABLES SB'!D:D,1,FALSE) -> customrecord_twc_awl
A10: T | B10: F | C10: OSSMTWC - AWL Intensity | D10: customrecord_twc_awl_intensity | E10: =VLOOKUP(D10,'TABLES SB'!D:D,1,FALSE) -> customrecord_twc_awl_intensity
A11: T | B11: F | C11: OSSMTWC - AWL Type | D11: customrecord_ossm_twc_awl_type | E11: =VLOOKUP(D11,'TABLES SB'!D:D,1,FALSE) -> customrecord_ossm_twc_awl_type
A12: F | B12: T | C12: OSSMTWC - Accommodation | D12: customrecord_twc_ac | E12: =VLOOKUP(D12,'TABLES SB'!D:D,1,FALSE) -> customrecord_twc_ac
A13: T | B13: T | C13: OSSMTWC - Accommodation SAF Status | D13: customrecord_twc_accom_saf_sts | E13: =VLOOKUP(D13,'TABLES SB'!D:D,1,FALSE) -> customrecord_twc_accom_saf_sts
... A191: F | B191: F | C191: TWC - Issue List | D191: customrecord_twc_issue | E191: =VLOOKUP(D191,'TABLES SB'!D:D,1,FALSE) -> customrecord_twc_issue

Sheet TABLES SB
A1: includename | B1: isinactive | C1: name | D1: record_id | E1: IN LIVE
A2: T | B2: F | C2: OSSM TWC - A/C Unit Status | D2: customrecord_twc_ac_unit_status | E2: =VLOOKUP(D2,'TABLES LIVE'!D:D,1,FALSE) -> customrecord_twc_ac_unit_status
A3: T | B3: F | C3: OSSMTWC - A/C Model | D3: customrecord_twc_ac_model | E3: =VLOOKUP(D3,'TABLES LIVE'!D:D,1,FALSE) -> customrecord_twc_ac_model
A4: T | B4: F | C4: OSSMTWC - A/C System Refrigerant | D4: customrecord_twc_sys_refrig | E4: =VLOOKUP(D4,'TABLES LIVE'!D:D,1,FALSE) -> customrecord_twc_sys_refrig
A5: T | B5: F | C5: OSSMTWC - A/C Units | D5: customrecord_twc_ac_unit | E5: =VLOOKUP(D5,'TABLES LIVE'!D:D,1,FALSE) -> customrecord_twc_ac_unit
A6: T | B6: F | C6: OSSMTWC - AC Feed Phase | D6: customrecord_twc_ac_feed_phase | E6: =VLOOKUP(D6,'TABLES LIVE'!D:D,1,FALSE) -> customrecord_twc_ac_feed_phase
A7: F | B7: F | C7: OSSMTWC - ACL | D7: customrecord_twc_acl | E7: =VLOOKUP(D7,'TABLES LIVE'!D:D,1,FALSE) -> customrecord_twc_acl
A8: F | B8: F | C8: OSSMTWC - ASCL | D8: customrecord_twc_ascl | E8: =VLOOKUP(D8,'TABLES LIVE'!D:D,1,FALSE) -> customrecord_twc_ascl
A9: F | B9: F | C9: OSSMTWC - AWL | D9: customrecord_twc_awl | E9: =VLOOKUP(D9,'TABLES LIVE'!D:D,1,FALSE) -> customrecord_twc_awl
A10: T | B10: F | C10: OSSMTWC - AWL Intensity | D10: customrecord_twc_awl_intensity | E10: =VLOOKUP(D10,'TABLES LIVE'!D:D,1,FALSE) -> customrecord_twc_awl_intensity
A11: T | B11: F | C11: OSSMTWC - AWL Type | D11: customrecord_ossm_twc_awl_type | E11: =VLOOKUP(D11,'TABLES LIVE'!D:D,1,FALSE) -> customrecord_ossm_twc_awl_type
A12: F | B12: T | C12: OSSMTWC - Accommodation | D12: customrecord_twc_ac | E12: =VLOOKUP(D12,'TABLES LIVE'!D:D,1,FALSE) -> customrecord_twc_ac
A13: T | B13: T | C13: OSSMTWC - Accommodation SAF Status | D13: customrecord_twc_accom_saf_sts | E13: =VLOOKUP(D13,'TABLES LIVE'!D:D,1,FALSE) -> customrecord_twc_accom_saf_sts
... A58: F | B58: F | C58: OSSMTWC - Feeder | D58: customrecord_twc_fd | E58: =VLOOKUP(D58,'TABLES LIVE'!D:D,1,FALSE) -> customrecord_twc_fd
A59: F | B59: F | C59: OSSMTWC - Field Access Configs | D59: customrecord_twc_fieldaccess | E59: =VLOOKUP(D59,'TABLES LIVE'!D:D,1,FALSE) -> #N/A | F59: FIXED
A60: T | B60: F | C60: OSSMTWC - File | D60: customrecord_twc_file | E60: =VLOOKUP(D60,'TABLES LIVE'!D:D,1,FALSE) -> customrecord_twc_file
A61: T | B61: F | C61: OSSMTWC - File Status | D61: customrecord_twc_file_status | E61: =VLOOKUP(D61,'TABLES LIVE'!D:D,1,FALSE) -> customrecord_twc_file_status
A62: T | B62: F | C62: OSSMTWC - File Type | D62: customrecord_twc_file_type | E62: =VLOOKUP(D62,'TABLES LIVE'!D:D,1,FALSE) -> customrecord_twc_file_type
A63: T | B63: F | C63: OSSMTWC - Financial Condition Status | D63: customrecord_twc_financial_condition_sts | E63: =VLOOKUP(D63,'TABLES LIVE'!D:D,1,FALSE) -> customrecord_twc_financial_condition_sts
A64: F | B64: T | C64: OSSMTWC - Generator | D64: customrecord_twc_gen | E64: =VLOOKUP(D64,'TABLES LIVE'!D:D,1,FALSE) -> customrecord_twc_gen
A65: F | B65: F | C65: OSSMTWC - Generator Service | D65: customrecord_twc_gen_svc | E65: =VLOOKUP(D65,'TABLES LIVE'!D:D,1,FALSE) -> customrecord_twc_gen_svc
A66: T | B66: F | C66: OSSMTWC - Generator Service Type | D66: customrecord_twc_gen_svc_type | E66: =VLOOKUP(D66,'TABLES LIVE'!D:D,1,FALSE) -> customrecord_twc_gen_svc_type
A67: T | B67: T | C67: OSSMTWC - Generator Status | D67: customrecord_twc_gen_sts | E67: =VLOOKUP(D67,'TABLES LIVE'!D:D,1,FALSE) -> customrecord_twc_gen_sts
A68: T | B68: F | C68: OSSMTWC - Infra AC Feed Phase | D68: customrecord_twc_infra_ac_feed_phase | E68: =VLOOKUP(D68,'TABLES LIVE'!D:D,1,FALSE) -> customrecord_twc_infra_ac_feed_phase
A69: T | B69: F | C69: OSSMTWC - Infra Accommodation Type | D69: customrecord_twc_infra_accom | E69: =VLOOKUP(D69,'TABLES LIVE'!D:D,1,FALSE) -> customrecord_twc_infra_accom
A70: T | B70: F | C70: OSSMTWC - Infra Fall Arrest Status | D70: customrecord_twc_infra_fall_arr_sts | E70: =VLOOKUP(D70,'TABLES LIVE'!D:D,1,FALSE) -> customrecord_twc_infra_fall_arr_sts
A71: T | B71: F | C71: OSSMTWC - Infra Fall Arrest Types | D71: customrecord_twc_infra_fall_arr_types | E71: =VLOOKUP(D71,'TABLES LIVE'!D:D,1,FALSE) -> customrecord_twc_infra_fall_arr_types
... A167: T | B167: F | C167: OSSMTWC - SRF Item Voltage Type | D167: customrecord_twc_srf_itm_v_type | E167: =VLOOKUP(D167,'TABLES LIVE'!D:D,1,FALSE) -> customrecord_twc_srf_itm_v_type
A168: T | B168: F | C168: OSSMTWC - SRF Revenue Impact | D168: customrecord_twc_srf_revenue_impact | E168: =VLOOKUP(D168,'TABLES LIVE'!D:D,1,FALSE) -> #N/A | F168: FIXED
A169: T | B169: F | C169: OSSMTWC - SRF Review | D169: customrecord_twc_srf_rev | E169: =VLOOKUP(D169,'TABLES LIVE'!D:D,1,FALSE) -> customrecord_twc_srf_rev
A170: T | B170: F | C170: OSSMTWC - SRF Status | D170: customrecord_twc_srf_status | E170: =VLOOKUP(D170,'TABLES LIVE'!D:D,1,FALSE) -> customrecord_twc_srf_status
A171: T | B171: F | C171: OSSMTWC - SRF Type | D171: customrecord_twc_srf_type | E171: =VLOOKUP(D171,'TABLES LIVE'!D:D,1,FALSE) -> customrecord_twc_srf_type
A172: T | B172: F | C172: OSSMTWC - SRF Workflow | D172: customrecord_twc_srf_wkf | E172: =VLOOKUP(D172,'TABLES LIVE'!D:D,1,FALSE) -> customrecord_twc_srf_wkf
A173: F | B173: F | C173: OSSMTWC - SRF Workflow Item | D173: customrecord_twc_srf_wkfi | E173: =VLOOKUP(D173,'TABLES LIVE'!D:D,1,FALSE) -> customrecord_twc_srf_wkfi
A174: T | B174: F | C174: OSSMTWC - SRF Workflow Stage | D174: customrecord_twc_srf_wks | E174: =VLOOKUP(D174,'TABLES LIVE'!D:D,1,FALSE) -> customrecord_twc_srf_wks
A175: T | B175: F | C175: OSSMTWC - SRF Workflow Status | D175: customrecord_twc_srf_wkf_status | E175: =VLOOKUP(D175,'TABLES LIVE'!D:D,1,FALSE) -> customrecord_twc_srf_wkf_status
A176: T | B176: F | C176: OSSMTWC - Section 5 Decision | D176: customrecord_twc_section_5_decision | E176: =VLOOKUP(D176,'TABLES LIVE'!D:D,1,FALSE) -> customrecord_twc_section_5_decision
A177: T | B177: F | C177: OSSMTWC - Site | D177: customrecord_twc_site | E177: =VLOOKUP(D177,'TABLES LIVE'!D:D,1,FALSE) -> customrecord_twc_site
A178: T | B178: F | C178: OSSMTWC - Site BTS Status | D178: customrecord_twc_site_bts_sts | E178: =VLOOKUP(D178,'TABLES LIVE'!D:D,1,FALSE) -> customrecord_twc_site_bts_sts
A179: T | B179: F | C179: OSSMTWC - Site Level | D179: customrecord_twc_site_level | E179: =VLOOKUP(D179,'TABLES LIVE'!D:D,1,FALSE) -> customrecord_twc_site_level
A180: T | B180: F | C180: OSSMTWC - Site Perimeter Type | D180: customrecord_twc_site_perimeter_type | E180: =VLOOKUP(D180,'TABLES LIVE'!D:D,1,FALSE) -> customrecord_twc_site_perimeter_type
... A212: F | B212: F | C212: TWC - Issue List | D212: customrecord_twc_issue | E212: =VLOOKUP(D212,'TABLES LIVE'!D:D,1,FALSE) -> customrecord_twc_issue
