Workbook

Sheet TimeEntries
A1: Internal ID | B1: Date | C1: Employee | D1: Item | E1: Duration | F1: Approval Status | G1: Case/Task/Event | H1: Billable | I1: Date Created | J1: Formula (Text) | K1: Charge Billing Run ID
A2: 1542360 | B2: 46269 | C2: Dave O'Hanlon | D2: SRConNS | E2: 2 | F2: Approved | G2: Consultancy : Advance Reporting and KPI (Project Task) | H2: Yes | I2: 46272 | J2: Updates to Saved Searches and Reports?Custom centre tab and category for SS and Reports
A3: 1542357 | B3: 46268 | C3: Dave O'Hanlon | D3: SRConNS | E3: 2 | F3: Approved | G3: Consultancy : Stationery (Project Task) | H3: Yes | I3: 46272 | J3: Updates to Sales Invoice PDF
A4: 1542362 | B4: 46268 | C4: Dave O'Hanlon | D4: SRConNS | E4: 2 | F4: Approved | G4: Consultancy : E-Payments (Project Task) | H4: Yes | I4: 46272 | J4: EFT file testing with AIB and code changes to format?Finance Checklist tasks
A5: 1542359 | B5: 46267 | C5: Dave O'Hanlon | D5: SRConNS | E5: 2 | F5: Approved | G5: Consultancy : Advance Reporting and KPI (Project Task) | H5: Yes | I5: 46272 | J5: Updates to Saved Searches and Reports?Custom centre tab and category for SS and Reports
A6: 1542358 | B6: 46266 | C6: Dave O'Hanlon | D6: SRConNS | E6: 2 | F6: Approved | G6: Consultancy : Roles and Permissions (Project Task) | H6: Yes | I6: 46272 | J6: Updates to roles for Finance
A7: 1542361 | B7: 46266 | C7: Dave O'Hanlon | D7: SRConNS | E7: 2 | F7: Approved | G7: Consultancy : E-Payments (Project Task) | H7: Yes | I7: 46272 | J7: EFT file testing with AIB and code changes to format?Finance Checklist tasks
A8: 1541950 | B8: 46265 | C8: Giuseppe Dev | D8: SRConNS | E8: 4 | F8: Approved | G8: Development : Radix System Replacement - Phase 1 (Project Task) | H8: No | I8: 46266 | J8: issue list fixing SRF saving issue session with Laco
A9: 1541868 | B9: 46265 | C9: Ladislav Zimanyi | D9: SRDevNSFOC | E9: 3 | F9: Approved | G9: Development Project Mgt - Ladislav (Project Task) | H9: No | I9: 46265 | J9: Towercom - dev session with Giuseppe
A10: 1542028 | B10: 46265 | C10: Dave O'Hanlon | D10: SRConPMNS | E10: 1 | F10: Approved | G10: Project Management (Project Task) | H10: No | I10: 46266 | J10: Updates to actions checklist
A11: 1541949 | B11: 46262 | C11: Giuseppe Dev | D11: SRConNS | E11: 5.25 | F11: Approved | G11: Development : Radix System Replacement - Phase 1 (Project Task) | H11: No | I11: 46266 | J11: issue list
A12: 1541595 | B12: 46262 | C12: Ladislav Zimanyi | D12: SRDevNSFOC | E12: 2 | F12: Approved | G12: Development Project Mgt - Ladislav (Project Task) | H12: No | I12: 46262 | J12: Towercom - session with Jesna - overview and session with Amy on Nexus process
A13: 1541722 | B13: 46262 | C13: Dave O'Hanlon | D13: SRConNS | E13: 2 | F13: Approved | G13: Consultancy : System Training (Project Task) | H13: Yes | I13: 46262 | J13: Working with Towercom Finance to train ahead of Go-Live?Finance actions
... A441: 1516618 | B441: 45929 | C441: Dave O'Hanlon | D441: SRConNS | E441: 4 | F441: Approved | G441: Consultancy : ERP Consultancy and Configuration (Project Task) | H441: Yes | I441: 45931 | J441: Account Bundle Deployment
B442: Overall Total | E442: 1,392.0 | K442: 0

Sheet Sheet1
A1: Employee | C1: Time
A2: Dave O'Hanlon | B2: Implementation | C2: =SUMIF(TimeEntries!C:C,A2,TimeEntries!E:E) -> 250 | D2: =C2/$C$12 -> 0.1795977
A3: Giuseppe Dev | B3: Development | C3: =SUMIF(TimeEntries!C:C,A3,TimeEntries!E:E) -> 400 | D3: =C3/$C$12 -> 0.28735632
A4: Ladislav Zimanyi | B4: Management | C4: =SUMIF(TimeEntries!C:C,A4,TimeEntries!E:E) -> 24.5 | D4: =C4/$C$12 -> 0.017600575
A5: Sean Munroe | B5: Implementation | C5: =SUMIF(TimeEntries!C:C,A5,TimeEntries!E:E) -> 284 | D5: =C5/$C$12 -> 0.20402299
A6: Javeed Shabeer | B6: Development | C6: =SUMIF(TimeEntries!C:C,A6,TimeEntries!E:E) -> 168 | D6: =C6/$C$12 -> 0.12068966
A7: Jesna John | B7: Development | C7: =SUMIF(TimeEntries!C:C,A7,TimeEntries!E:E) -> 170.5 | D7: =C7/$C$12 -> 0.12248563
A8: Anna Carolan | B8: Management | C8: =SUMIF(TimeEntries!C:C,A8,TimeEntries!E:E) -> 43 | D8: =C8/$C$12 -> 0.030890805
A9: Abin Pious | B9: Development | C9: =SUMIF(TimeEntries!C:C,A9,TimeEntries!E:E) -> 16 | D9: =C9/$C$12 -> 0.011494253
A10: Carlos Gamiz | B10: Management | C10: =SUMIF(TimeEntries!C:C,A10,TimeEntries!E:E) -> 36 | D10: =C10/$C$12 -> 0.025862069
C12: =SUM(C2:C10) -> 1392
A15: Area | C15: Time
A16: Implementation | C16: =SUMIF(B2:B10,A16,C2:C10) -> 534 | D16: =C16/$C$20 -> 0.38362069
A17: Development | C17: =SUMIF(B3:B11,A17,C3:C11) -> 754.5 | D17: =C17/$C$20 -> 0.54202586
A18: Management | C18: =SUMIF(B4:B12,A18,C4:C12) -> 103.5 | D18: =C18/$C$20 -> 0.074353448
C20: =SUM(C16:C18) -> 1392
