Workbook

Sheet SITES TEST DATA
A1: Site ID | B1: RADIX Site Table entry number | C1: Site ID | D1: Site Name | E1: Alias | F1: Site Status | G1: Site Type | H1: Multi Mast Sites | I1: Old ID | J1: Height ASL (m) | K1: Site Level | L1: Portfolio | M1: SRF Status | N1: SAF Status | O1: BTS Status | P1: SAF Auto Approve | Q1: Public | R1: Address | S1: Eircode | T1: What3Words | U1: County | V1: Easting | W1: Northing | X1: Longitude | Y1: Latitude | Z1: Track Type | AA1: Easting (Access) | AB1: Northing (Access) | AC1: Latitude (Access) | AD1: Longitude (Access) | AE1: Directions | AF1: Instructions | AG1: Tenant Card Required | AH1: 4x4 Required | AI1: Parking Restrictions | AJ1: Crane/Mewp Access | AK1: Independent Power Supplies | AL1: Safety / Special Notes | AM1: Full Demised Area Fenced | AN1: Adjacent Groud Space | AO1: Adjacent Ground Owner | AP1: Perimeter Type | AQ1: Fence Height (m)
A2: TCK5002 | B2: 2 | C2: TCK5002 | D2: Aherla | F2: Retired | H2: NO | J2: 79 | K2: Level 1 | L2: EED | M2: Full SRF | N2: Full SAF | P2: 1 | Q2: 1 | R2: Aherla | S2: A96AP20 | T2: lsjncpsdjnc | U2: Cork | V2: 150500 | W2: 67057 | X2: 51.85409 | Y2: -8.71912 | Z2: Tarmac | AA2: 150479 | AB2: 67072 | AC2: 51.85422 | AD2: -8.71943 | AE2: From Cork City take N22 towards Macroom. After 14.5km take left turn towards Aherla. Stay on road for 2.3km, after road bears to the right and entering Aherla, take sharp 160 degree left turn. Follow road for 250m and site will be on right hand side. | AF2: 1 x eircom padlock on pedestrian gate and ISEO LOCKEN lock on anticlimb | AG2: 0 | AH2: 0 | AJ2: 1 | AM2: 0 | AN2: 1 | AO2: House on either side of site and field located behind site | AP2: Stone/Chain Link Combination | AQ2: 1.2
A3: TKY6028 | B3: 3 | C3: TKY6028 | D3: Anablaha | E3: Toormore | F3: Active | H3: NO | J3: 181 | K3: Level 2 | L3: TC68 | M3: Full SRF | N3: Full SAF | P3: 1 | Q3: 1 | R3: Toormore, Anablaha | T3: lsjncpsdjnc | U3: Kerry | V3: 102505 | W3: 96387 | X3: 52.11128 | Y3: -9.42384 | Z3: Tarmac | AA3: 102498 | AB3: 96404 | AC3: 52.11143 | AD3: -9.42395 | AE3: From Killarney take N22 towards Castleisland / Ferranfore. After 5.3km on N22, approach crossroads, take right turn heading for Finnegan's Cross. Stay on road for 6.5km, site will be on the right hand side. | AF3: Electronic LOCKEN key required for access | AG3: 0 | AH3: 0 | AJ3: 1 | AM3: 0 | AN3: 1 | AO3: Farmer | AP3: Pallisade | AQ3: 2.4
A4: TGY5003 | B4: 4 | C4: TGY5003 | D4: Ardrahan | E4: Ardrahan exchange ADNL | F4: Active | H4: NO | J4: 39 | K4: Level 2 | L4: EED | M4: Full SRF | N4: Full SAF | P4: 1 | Q4: 1 | R4: Behind Post Office, N18, Ardrahan | T4: lsjncpsdjnc | U4: Galway | V4: 146050 | W4: 212030 | X4: 53.15632 | Y4: -8.80721 | Z4: Tarmac | AA4: 146121 | AB4: 212093 | AC4: 53.15689 | AD4: -8.80616 | AE4: From Galway take N18 towards Gort. After 16.5km arrive in town of Ardrahan. Take right turn immediately after Joyces Pub" followed by immediate left turn towards Garda station and Post office. Take road located between Garda and Post office and follow for 100m, site will be on the left hand side. | AF4: elocks installed | AG4: 0 | AH4: 0 | AJ4: 1 | AM4: 0 | AN4: 1 | AO4: Eircom compound | AP4: Stone/Chain Link Combination | AQ4: 1.2
A5: TWW3001 | B5: 5 | C5: TWW3001 | D5: Arklow | F5: Active | H5: NO | J5: 3 | K5: Level 2 | L5: 108 | M5: Full SRF | N5: Full SAF | P5: 1 | Q5: 1 | R5: Main Street, Arklow Town | T5: lsjncpsdjnc | U5: Wicklow | V5: 324473 | W5: 173563 | X5: 52.799062 | Y5: -6.155261 | AA5: 324445 | AB5: 173524 | AC5: 52.79872 | AD5: -6.15569 | AE5: From N11 take turn for Arklow. Continue into town centre crossing over bridge. Arrive at T-junction, take right turn. Continue straight for approx 300m. Take immediate right after Post Office. Compound gate is located 30m down on the right hand side. Once in compound, take immediate left and continue straight for 40m. Mast is located straight ahead. | AF5: ISEO Locken key required for anticlimb | AG5: 1 | AH5: 0 | AJ5: 1 | AM5: 0 | AN5: 1 | AO5: Eircom | AP5: None
A6: TWW5005 | B6: 6 | C6: TWW5005 | D6: Arklow Town Centre | E6: Arklow Exchange | F6: Active | H6: NO | J6: 24 | K6: Level 2 | L6: EED | M6: Full SRF | N6: Full SAF | P6: 1 | Q6: 1 | R6: Main St, Arklow Town | T6: lsjncpsdjnc | U6: Wicklow | V6: 324456 | W6: 173522 | X6: 52.7987 | Y6: -6.15554 | Z6: Tarmac | AA6: 324445 | AB6: 173524 | AC6: 52.79872 | AD6: -6.15569 | AE6: From N11 take turn off for Arklow Town. In town cross over bridge and continue on road until a T-junction is reached. Take right turn at junction and folow for 300m and take another right turn after Post Office. | AF6: Ensup | AG6: 1 | AH6: 0 | AJ6: 1 | AM6: 0 | AN6: 1 | AO6: eircom / public carpark | AQ6: 1.2
A7: TWW5004 | B7: 7 | C7: TWW5004 | D7: Arklow Town South | E7: Arklow AEH | F7: Active | H7: NO | J7: 55 | K7: Level 4 | L7: EED | M7: Full SRF | N7: Full SAF | P7: 0 | Q7: 1 | R7: Emoclew Rd, Arklow Town | T7: lsjncpsdjnc | U7: Wicklow | V7: 323288 | W7: 172548 | X7: 52.79022 | Y7: -6.17321 | Z7: Tarmac | AA7: 323317 | AB7: 172635 | AC7: 52.79099 | AD7: -6.17274 | AE7: From Dublin take N11 to Arklow Town. After crossing bridge into town follow Main Street around to the right. Continue on Main Street and take left at roundabout onto Wexford Road (R772). Follow for 800m, go straight through roundabout and take right turn immediately after Emoclew Road. Follow for 500m. Site is located on left hand side. | AF7: Eircom main gate and locken iseo compound and locken iseo anticlimb. Go through main compound gate and take 1st left followed by a right turn. Site is located 50m down on L.H.S. ISEO electronic key required for access. | AG7: 0 | AH7: 0 | AJ7: 1 | AM7: 0 | AN7: 1 | AO7: Eircom compound | AP7: Pallisade | AQ7: 2.4
A8: TDL2001 | B8: 8 | C8: TDL2001 | D8: Arranmore | F8: Active | H8: NO | J8: 11 | K8: Level 1 | L8: 108 | M8: Full SRF | N8: Full SAF | P8: 0 | Q8: 1 | R8: Arranmore Island | T8: lsjncpsdjnc | U8: Donegal | V8: 168195 | W8: 415600 | X8: 54.986888 | Y8: -8.49757 | AA8: 168220 | AB8: 415610 | AC8: 54.98698 | AD8: -8.497181 | AE8: Take local ferry from Donegal to Arranmore Island. From the pier follow the road keeping the coast on your left hand side. Access site through gate from the main road. | AF8: Ferry required to Aran Island. | AG8: 0 | AH8: 0 | AJ8: 1 | AM8: 1 | AN8: 1 | AO8: Eircom | AP8: Post & Rail Fence | AQ8: 1.2
A9: TCN5006 | B9: 9 | C9: TCN5006 | D9: Arvanagh | E9: Arvagh TE Exchange(ARVA) | F9: Retired | H9: NO | J9: 75 | K9: Level 1 | L9: EED | M9: Full SRF | N9: Full SAF | P9: 0 | Q9: 1 | R9: Arvangh | T9: lsjncpsdjnc | U9: Cavan | V9: 227855 | W9: 296831 | X9: 53.92021 | Y9: -7.57679 | Z9: Tarmac | AA9: 227836 | AB9: 296796 | AC9: 53.9199 | AD9: -7.57709 | AE9: Travelling from Granard take N55 for 3.5km. Turn left and continue 4.5km, then turn right toward Swan Lake Drive and in 6.4km continue straight for 6.7km. Take sharp right at Main Street (R198) and after 130m site is located on right hand side. | AG9: 0 | AH9: 0 | AJ9: 0 | AM9: 0 | AN9: 1 | AO9: Health board | AP9: Pallisade | AQ9: 2.4
A10: TMH6457 | B10: 10 | C10: TMH6457 | D10: Athboy | F10: UTS | H10: NO | I10: TMH6057 | J10: 65 | K10: Level 3 | L10: TC68 | M10: Full SRF | N10: Full SAF | P10: 0 | Q10: 1 | R10: Athboy | T10: lsjncpsdjnc | U10: Meath | V10: 271766 | W10: 264326 | X10: 53.62401 | Y10: -6.91612 | Z10: Tarmac | AA10: 271796 | AB10: 264289 | AC10: 53.62368 | AD10: -6.91567 | AE10: Travelling on the Navan Road N51, arrive into Athboy and site is located on Lower Bridge Street. Site entrance is located beside garda station. | AF10: Garda gate entrance,Code required for keypad. soon to be automatic gates. | AG10: 0 | AH10: 0 | AJ10: 1 | AM10: 0 | AN10: 1 | AO10: Car wash place
A11: TGY5008 | B11: 12 | C11: TGY5008 | D11: Athenry | F11: Retired | H11: NO | J11: 16 | K11: Level 4 | L11: EED | M11: Full SRF | N11: Full SAF | P11: 0 | Q11: 1 | R11: Cross Street, Athenry | T11: lsjncpsdjnc | U11: Galway | V11: 150227 | W11: 227784 | X11: 53.29826 | Y11: -8.74724 | Z11: Tarmac | AA11: 150242 | AB11: 227767 | AC11: 53.29811 | AD11: -8.74701 | AE11: Travelling to Athenry on the Dublin Road (R347), take second left onto Bridge Street. Site is located on right hand side. | AF11: automatic gate with key code required for main small gate. elocks also installed | AG11: 1 | AH11: 0 | AJ11: 1 | AM11: 0 | AN11: 0 | AO11: Business area | AP11: Pallisade | AQ11: 2.4
A12: TWH4001 | B12: 13 | C12: TWH4001 | D12: Athlone HPO | F12: Active | H12: NO | J12: 42 | K12: Level 3 | L12: 108 | M12: Full SRF | N12: Full SAF | P12: 0 | Q12: 1 | R12: Custume Barracks, Grace Road, Athlone Town | T12: lsjncpsdjnc | U12: Westmeath | V12: 203705 | W12: 241477 | X12: 53.423629 | Y12: -7.945005 | AA12: 203728 | AB12: 241633 | AC12: 53.425025 | AD12: -7.944653 | AE12: Arrive in Athlone town, and take bridge across the Shannon into the west side of Athlone town. As you cross the bridge you will arrive at a roundabout, take last exit onto Grace Road. Follow for 200m and site entrance will be on the left hand side. To access ground equipment same as before cross over bridge but this time take 1st exit at roundabout onto Castle St. Follow one way system for 350m keeping to the right at all times, then take right turn onto Pearse St. Continue on road for 210m and site entrance will be on the left hand side directly after Garda Station. | AF12: 5-7 days notice required for Army Barracks approval prior to access. LOCKEN key required for access to anticlimb. | AG12: 0 | AH12: 0 | AJ12: 1 | AM12: 0 | AN12: 1 | AO12: Eircom | AP12: None
A13: TLK5009 | B13: 14 | C13: TLK5009 | D13: Athlunkard | F13: Active | H13: NO | J13: 16 | K13: Level 3 | L13: EED | M13: Full SRF | N13: Full SAF | P13: 1 | Q13: 1 | R13: Athlunkard | T13: lsjncpsdjnc | U13: Limerick | V13: 159171 | W13: 159411 | X13: 52.6847 | Y13: -8.60446 | Z13: Tarmac | AA13: 159197 | AB13: 159359 | AC13: 52.68423 | AD13: -8.60408 | AE13: Travelling into Limerick on N18 at Coonagh roundabout take 2nd exit onto Ennis Road. After 1km turn left at Dr McCann's Road (N7). At next roundabout take 4th exit to the Island/N7 heading for N24, turn left at Athlinkard Street. At Corbally roundabout take 1st exit, and turn right at Thornbrook. Site is located on right hand side. | AF13: Ensup main gate and elock on internal compound and anticlimb | AG13: 0 | AH13: 0 | AJ13: 1 | AM13: 0 | AN13: 0 | AP13: Pallisade | AQ13: 2.8
A14: TGY6318 | B14: 15 | C14: TGY6318 | D14: Aughrim | E14: Aughrim Exchange | F14: Active | H14: NO | I14: TGY6018 | J14: 63 | K14: Level 2 | L14: TC68 | M14: Full SRF | N14: Full SAF | P14: 0 | Q14: 1 | R14: Aughrim | T14: lsjncpsdjnc | U14: Galway | V14: 178899 | W14: 228106 | X14: 53.30307 | Y14: -8.31724 | Z14: Tarmac | AA14: 178899 | AB14: 228111 | AC14: 53.30312 | AD14: -8.31724 | AE14: Travelling on N6 take first exit and continue onto R338. After 5.3km take right turn in Aughrim. Site is located 260m on right hand side. | AG14: 0 | AH14: 0 | AJ14: 0 | AM14: 0 | AN14: 1 | AO14: western health board
A15: TGY5010 | B15: 16 | C15: TGY5010 | D15: Aughrim | E15: Aughrim Exchange | F15: UTS | H15: NO | J15: 62 | K15: Level 2 | L15: EED | M15: Full SRF | N15: Full SAF | P15: 0 | Q15: 1 | R15: Aughrim | T15: lsjncpsdjnc | U15: Galway | V15: 178899 | W15: 228099 | X15: 53.30301 | Y15: -8.31725 | Z15: Tarmac | AA15: 178899 | AB15: 228111 | AC15: 53.30312 | AD15: -8.31724 | AE15: Travelling on N6 take first exit and continue onto R338. After 5.3km take right turn in Aughrim. Site is located 260m on right hand side. | AG15: 0 | AH15: 0 | AJ15: 0 | AM15: 0 | AN15: 1 | AO15: western health board
A16: TMO6047 | B16: 17 | C16: TMO6047 | D16: Ayle | F16: Active | H16: NO | J16: 51 | K16: Level 2 | L16: TC68 | M16: Full SRF | N16: Full SAF | P16: 1 | Q16: 1 | R16: Ayle | T16: lsjncpsdjnc | U16: Mayo | V16: 107088 | W16: 281651 | X16: 53.77629 | Y16: -9.41005 | Z16: Tarmac | AA16: 107089 | AB16: 281632 | AC16: 53.77612 | AD16: -9.41003 | AE16: Travelling from Westport take R330 for Ballinrobe for 7.4km. Site is located on the left hand side, opposite the pub. | AF16: electronic key required to access site | AG16: 0 | AH16: 0 | AJ16: 0 | AM16: 0 | AN16: 1 | AO16: eircom | AP16: Pallisade | AQ16: 2.8
A17: TDU7001 | B17: 18 | C17: TDU7001 | D17: Balbriggan | F17: UTS | H17: NO | I17: TDU5011 | J17: 19 | K17: Level 4 | L17: EED | M17: Full SRF | N17: Full SAF | P17: 1 | Q17: 1 | R17: Oakleigh St, Balbriggan | T17: lsjncpsdjnc | U17: Dublin | V17: 319949 | W17: 263990 | X17: 53.61219 | Y17: -6.18836 | Z17: Tarmac | AA17: 319942 | AB17: 264003 | AC17: 53.612308 | AD17: -6.188452 | AE17: From Dublin take M1 to Balbriggan, take exit onto R132 into Balbriggan town. In town take left onto Main St, follow for 250m (passing school on left hand side) and take left turn onto Oakleigh Street. Site is located a further 25m on the left hand side. | AF17: Eircom gates and padlock | AG17: 0 | AH17: 0 | AJ17: 1 | AM17: 0 | AN17: 1 | AO17: Housing estate and eircom compound | AP17: Pallisade | AQ17: 2.4
A18: TMO5012 | B18: 20 | C18: TMO5012 | D18: Balla | F18: Retired | H18: NO | J18: 46 | K18: Level 1 | L18: EED | M18: Full SRF | N18: Full SAF | P18: 0 | Q18: 1 | R18: Balla | T18: lsjncpsdjnc | U18: Mayo | V18: 125654 | W18: 284185 | X18: 53.80204 | Y18: -9.12912 | Z18: Tarmac | AA18: 125589 | AB18: 284180 | AC18: 53.80198 | AD18: -9.1301 | AE18: Travelling from Claremorris take the N60 for 13km, when arriving into Ball take left turn. Site located 250m on left behind playground. | AF18: ISEO LOCKEN key required for access | AG18: 0 | AH18: 0 | AI18: Yes | AJ18: 0 | AM18: 0 | AN18: 1 | AO18: Garda/eircom area behind site,large field
A19: TRN7002 | B19: 22 | C19: TRN7002 | D19: Ballaghadereen | F19: Active | H19: NO | I19: TRN5014 | J19: 81 | K19: Level 2 | L19: EED | M19: Full SRF | N19: Full SAF | P19: 1 | Q19: 1 | R19: Circular Rd, Ballaghadereen | T19: lsjncpsdjnc | U19: Roscommon | V19: 162085 | W19: 294690 | X19: 53.90034 | Y19: -8.57753 | Z19: Tarmac | AA19: 162096 | AB19: 294661 | AC19: 53.90008 | AD19: -8.57736 | AE19: From Frenchpark take N5 to Ballaghadereen. Arrive in Ballaghadereen and take right turn after Towey's Petrol Station onto Circular Road. Follow road for 125m and site will be on the right hand side. | AF19: Eircom gate with padlock on daisy chain. VF lock on anti climb | AG19: 0 | AH19: 0 | AJ19: 1 | AM19: 0 | AN19: 1 | AO19: Eircom compound | AP19: Pallisade/Chain Link Combination | AQ19: 2.4
A20: TMO1001 | B20: 23 | C20: TMO1001 | D20: Ballina | F20: Active | H20: NO | J20: 18 | K20: Premium | L20: 108 | M20: Full SRF | N20: Full SAF | P20: 1 | Q20: 1 | R20: Ballina | T20: lsjncpsdjnc | U20: Mayo | V20: 123826 | W20: 318432 | X20: 54.109386 | Y20: -9.165398 | AA20: 123883 | AB20: 318275 | AC20: 54.107981 | AD20: -9.164494 | AE20: In Ballina Town, take N26 (towards Foxford). Follow for 0.5km and take right turn (just before train station). Stayed 100m tower is visible on the right hand side. Follow track across field to compound. | AF20: Track across grass field. Muddy in winter, use 4x4. ISEO Locken ekey required for access. | AG20: 0 | AH20: 1 | AI20: No | AJ20: 1 | AL20: Caution advised when driving to site, to stay wires/blocks to be avoided. | AM20: 1 | AN20: 1 | AO20: Towercom | AP20: Pallisade | AQ20: 2.8
A21: TWX5030 | B21: 24 | C21: TWX5030 | D21: Ballinaboola | E21: Ballynabola RSU | F21: Retired | H21: NO | J21: 68 | K21: Level 1 | L21: EED | M21: Full SRF | N21: Full SAF | P21: 1 | Q21: 1 | R21: Ballinaboola | T21: lsjncpsdjnc | U21: Wexford | V21: 279380 | W21: 124670 | X21: 52.368302 | Y21: -6.835331 | Z21: Tarmac | AA21: 279358 | AB21: 124641 | AC21: 52.36805 | AD21: -6.83566 | AE21: From Dublin take N11 to Wexford. In Wexford take turn off for N25 at roundabout heading for New Ross. Continue on road for 22.5km and arrive in Ballinaboola. On entering the town the site will be on left hand side, beside turn off onto R737 heading for Wellington Bridge. | AF21: elock installed | AG21: 0 | AH21: 0 | AJ21: 1 | AM21: 0 | AN21: 1 | AO21: Farmers land | AP21: Pallisade | AQ21: 2.4
A22: TCK6005 | B22: 25 | C22: TCK6005 | D22: Ballinaclashet | F22: Active | H22: NO | J22: 45 | K22: Level 2 | L22: TC68 | M22: Full SRF | N22: Full SAF | P22: 1 | Q22: 1 | R22: Ballinaclashet, Oatlands Cross Roads (R611), Bellgooley | T22: lsjncpsdjnc | U22: Cork | V22: 169290 | W22: 53776 | X22: 51.73608 | Y22: -8.44525 | Z22: Tarmac | AA22: 169302 | AB22: 53751 | AC22: 51.73586 | AD22: -8.44508 | AE22: From Cork take N27 towards airport. At roundabout take R600 towards Belgooley. In Bellgooley take left turn after Campus Petrol Station / Huntsman Bar onto the R611. Follow road for 2.8km. Site will be on the left hand side. | AF22: ISEO LOCKEN Electronic key required for access. | AG22: 0 | AH22: 0 | AJ22: 1 | AM22: 0 | AN22: 1 | AO22: Eircom / farmer | AP22: Timber Fence | AQ22: 1.8
A23: TGY5016 | B23: 26 | C23: TGY5016 | D23: Ballinasloe | F23: Active | H23: NO | J23: 60 | K23: Level 2 | L23: EED | M23: Full SRF | N23: Full SAF | P23: 0 | Q23: 1 | R23: Eircom exchange, St. Michaels Square, Ballinasloe | T23: lsjncpsdjnc | U23: Galway | V23: 185304 | W23: 230974 | X23: 53.32906 | Y23: -8.22131 | Z23: Tarmac | AA23: 185339 | AB23: 230998 | AC23: 53.32928 | AD23: -8.22078 | AE23: From Dublin take N4/N6 towards Galway. On N6 take first Ballinasloe exit. Follow signs into town. After crossing bridge follow road for 130m and take right hand turn onto Bridge St. Continue on road for a further 180m and take left turn on Main St, continue on again for 120m and take left turn in St. Michaels Square. Site will be located at end of square on right hand side opposite church. | AF23: 4m Access ladder required | AG23: 0 | AH23: 0 | AJ23: 1 | AM23: 0 | AN23: 1 | AO23: An Post | AQ23: 1.2
A24: TMO2002 | B24: 28 | C24: TMO2002 | D24: Ballinrobe | F24: Active | H24: NO | J24: 33 | K24: Level 3 | L24: 108 | M24: Full SRF | N24: Full SAF | P24: 1 | Q24: 1 | R24: High Street, Ballinrobe | T24: lsjncpsdjnc | U24: Mayo | V24: 118921 | W24: 264516 | X24: 53.624354 | Y24: -9.226138 | AA24: 119022 | AB24: 264534 | AC24: 53.62453 | AD24: -9.22461 | AE24: From Tuam, travel along the R332 onto N84 to Ballinrobe. Keep left through the town and follow road around to right. Turn left for Castlebar (N84). Turn left immediately after bridge to eircom building entrance. Access to compound through main gates, via carpark. | AF24: ISEO LOCKEN Electronic key required for access | AG24: 0 | AH24: 0 | AJ24: 1 | AM24: 1 | AN24: 1 | AO24: Eircom | AP24: Pallisade | AQ24: 3.2
A25: TDL5019 | B25: 29 | C25: TDL5019 | D25: Ballintra | F25: Active | H25: NO | J25: 40 | K25: Level 1 | L25: EED | M25: Full SRF | N25: Full SAF | P25: 1 | Q25: 1 | R25: Ballintra | T25: lsjncpsdjnc | U25: Donegal | V25: 192067 | W25: 369961 | X25: 54.57787 | Y25: -8.12343 | Z25: Tarmac | AA25: 191965 | AB25: 369974 | AC25: 54.577989 | AD25: -8.12499 | AE25: Travelling from Donegal head South on N15. Continue for 11.2km, then turn left at Abbey Park. After 200m take first left onto Main Street and in 85m site is located on right hand side. | AG25: 0 | AH25: 0 | AJ25: 1 | AM25: 0 | AN25: 1 | AO25: Farmer | AP25: Pallisade | AQ25: 3
A26: TDU5020 | B26: 31 | C26: TDU5020 | D26: Ballyboden | F26: Active | H26: NO | J26: 42 | K26: Premium | L26: EED | M26: Full SRF | N26: Full SAF | P26: 1 | Q26: 1 | R26: Scholarstown Rd, Ballyboden | T26: lsjncpsdjnc | U26: Dublin | V26: 313418 | W26: 226918 | X26: 53.2807 | Y26: -6.30034 | Z26: Tarmac | AA26: 313390 | AB26: 226840 | AC26: 53.28001 | AD26: -6.30079 | AE26: From M50 take exit 12. At roundabout take first exit for Ballyboden / Knocklyon. At next roundabout take second exit. Follow road to another roundabout and take last exit onto Scholarstown Road. Follow road for 650m, site entrance will be on left hand side, directly opposite right turn signposted for Rathfarnham Golf Club / DSPCA. | AF26: Electronic key required. 2 x eircom locks on gates. | AG26: 0 | AH26: 0 | AJ26: 1 | AM26: 0 | AN26: 1 | AO26: Houses/gardens surround compound on all sides | AP26: Pallisade/Chain Link Combination | AQ26: 2.4
A27: TKY6029 | B27: 32 | C27: TKY6029 | D27: Ballydavid | F27: Active | H27: NO | J27: 26 | K27: Level 1 | L27: TC68 | M27: Full SRF | N27: Full SAF | P27: 1 | Q27: 1 | R27: Ballydavid | T27: lsjncpsdjnc | U27: Kerry | V27: 38864 | W27: 106875 | X27: 52.19059 | Y27: -10.35707 | Z27: Tarmac | AA27: 38848 | AB27: 106873 | AC27: 52.19057 | AD27: -10.3573 | AE27: Travelling on N86 from Dingle, take first exit on roundabout onto R559. At next roundabout take first exit and stay on R559. After 8.2km take right turn. Site is located on left hand side. | AF27: ISEO LOCKEN ekey required for access | AG27: 0 | AH27: 0 | AJ27: 1 | AM27: 0 | AN27: 0 | AP27: Pallisade | AQ27: 2.8
A28: TGY6419 | B28: 34 | C28: TGY6419 | D28: Ballygar | F28: Active | H28: NO | I28: TGY6019 | J28: 60 | K28: Level 2 | L28: TC68 | M28: Full SRF | N28: Full SAF | P28: 1 | Q28: 1 | R28: Ballygar | T28: lsjncpsdjnc | U28: Galway | V28: 178262 | W28: 252490 | X28: 53.52213 | Y28: -8.32848 | Z28: Tarmac | AA28: 178281 | AB28: 252458 | AC28: 53.52185 | AD28: -8.3282 | AE28: Traveling from Mountbellew on N63 arrive into Ballygar. Site is located behind Garda Station on left hand side. | AF28: Access/right of way through garda station. ISEO Locken ekey required for access. | AG28: 0 | AH28: 0 | AI28: Yes | AJ28: 0 | AM28: 0 | AN28: 1 | AO28: Housing | AP28: Pallisade | AQ28: 2.8
A29: TCK6006 | B29: 35 | C29: TCK6006 | D29: Ballygarvan | F29: Active | H29: NO | J29: 70 | K29: Level 3 | L29: TC68 | M29: Full SRF | N29: Full SAF | P29: 1 | Q29: 1 | R29: Ballygarvan, Bowens Cross, Ballygarvan | T29: lsjncpsdjnc | U29: Cork | V29: 167465 | W29: 63707 | X29: 51.82523 | Y29: -8.4726 | Z29: Tarmac | AA29: 167465 | AB29: 63714 | AC29: 51.82529 | AD29: -8.4726 | AE29: From Dublin take M7/M8 to Cork, arrive in Cork and proceed through Jack Lynch tunnel onto the N25. Continue until turn off for N27 towards airport. Follow N27 for 3km and take turn on R600 (old Kinsale Road). Continue on for approx 9.2km until you reach crossroads with signs for left turn towards The Garden Pavillion" and "Park Liam McCarthy". Take the left turn and follow road for 50m, site will be located on right hand side. | AF29: ISEO LOCKEN ekey required for access. | AG29: 0 | AH29: 0 | AJ29: 1 | AM29: 0 | AN29: 1 | AO29: Farmer | AP29: Pallisade | AQ29: 2.4
A30: TWW1002 | B30: 37 | C30: TWW1002 | D30: Ballyguile - 52m | F30: Active | H30: NO | J30: 166 | K30: Level 3 | L30: 108 | M30: Full SRF | N30: Full SAF | P30: 0 | Q30: 1 | R30: Ballyguile, Wicklow Town | T30: lsjncpsdjnc | U30: Wicklow | V30: 331119 | W30: 192539 | X30: 52.967899 | Y30: -6.049156 | AA30: 331380 | AB30: 193078 | AC30: 52.97268 | AD30: -6.04504 | AE30: Travel into Wicklow Town, continue on Main Street. Take a right turn onto Kilmainham Hill, follow road onto Convent Road and then take left into Ballyguile housing estate. Take the first right and the gate to site will be on the right hand side after 25m. | AF30: elocks installed on site | AG30: 0 | AH30: 1 | AI30: No | AJ30: 1 | AL30: Anti-social behaviour has been reported in the area of this site. Lone working not recommended. | AM30: 1 | AN30: 1 | AO30: Co.co | AP30: Pallisade | AQ30: 3
A31: TMO6048 | B31: 39 | C31: TMO6048 | D31: Ballyhaunis | F31: Active | H31: NO | J31: 88 | K31: Level 2 | L31: TC68 | M31: Full SRF | N31: Full SAF | P31: 1 | Q31: 1 | R31: Ballyhaunis | T31: lsjncpsdjnc | U31: Mayo | V31: 149388 | W31: 279749 | X31: 53.76503 | Y31: -8.76822 | Z31: Tarmac | AA31: 149398 | AB31: 279751 | AC31: 53.76505 | AD31: -8.76806 | AE31: Travelling from Knock take R323 toward Airport Road for 10.3km. Arrive in Ballyhaunis and continue up to Main Street. Take left turn onto Beach Park and continue straight to St. Gerard's Cresent. Site is located on left hand side. | AG31: 0 | AH31: 0 | AJ31: 1 | AM31: 0 | AN31: 1 | AO31: Housing | AP31: Pallisade | AQ31: 2.8
A32: TMO7003 | B32: 40 | C32: TMO7003 | D32: Ballyhaunis | F32: Active | H32: NO | I32: TMO5023 | J32: 88 | K32: Level 2 | L32: EED | M32: Full SRF | N32: Full SAF | P32: 1 | Q32: 1 | R32: Ballyhaunis | T32: lsjncpsdjnc | U32: Mayo | V32: 149388 | W32: 279749 | X32: 53.76503 | Y32: -8.76822 | Z32: Tarmac | AA32: 149398 | AB32: 279751 | AC32: 53.76505 | AD32: -8.76806 | AE32: Travelling from Knock take R323 toward Airport Road for 10.3km. Arrive in Ballyhaunis and continue up to Main Street. Take left turn onto Beach Park and continue straight to St. Gerard's Cresent. Site is located on left hand side. | AF32: Elock on internal compound and anticlimb | AG32: 0 | AH32: 0 | AJ32: 1 | AM32: 0 | AN32: 1 | AO32: Housing | AP32: Pallisade | AQ32: 2.8
A33: TMO5024 | B33: 41 | C33: TMO5024 | D33: Ballyhean | E33: Ballyhean RSU | F33: Active | H33: NO | J33: 41 | K33: Level 1 | L33: EED | M33: Full SRF | N33: Full SAF | P33: 0 | Q33: 1 | R33: Attavally | T33: lsjncpsdjnc | U33: Mayo | V33: 114001 | W33: 280810 | X33: 53.76993 | Y33: -9.30499 | Z33: Tarmac | AA33: 113977 | AB33: 280819 | AC33: 53.77 | AD33: -9.30536 | AE33: From Ballinrobe take N84 towards Castlebar. Follow for 17km and take sharp right turn signposted for Attavally". Follow road for 75m and site will be on the left hand side." | AG33: 0 | AH33: 0 | AJ33: 1 | AM33: 0 | AN33: 1 | AO33: Farmers field on 3 sides | AP33: Stone/Chain Link Combination | AQ33: 1.2
A34: TKY7004 | B34: 42 | C34: TKY7004 | D34: Ballyheige | F34: Active | H34: NO | I34: TKY5025 | J34: 19 | K34: Level 1 | L34: EED | M34: Full SRF | N34: Full SAF | P34: 0 | Q34: 1 | R34: Ballyheige | T34: lsjncpsdjnc | U34: Kerry | V34: 75724 | W34: 128312 | X34: 52.39267 | Y34: -9.8263 | Z34: Tarmac | AA34: 75707 | AB34: 128314 | AC34: 52.39268 | AD34: -9.82655 | AE34: Travelling from Tralee on the R551 head Northwest. Continue straight and site is located 140m on the right hand side. | AG34: 0 | AH34: 0 | AJ34: 0 | AM34: 0 | AN34: 0
A35: TLK1003 | B35: 43 | C35: TLK1003 | D35: Ballyhoura | F35: Active | H35: NO | J35: 436 | K35: Level 3 | L35: 108 | M35: Full SRF | N35: Full SAF | P35: 0 | Q35: 1 | R35: Ballyhoura Mountain | T35: lsjncpsdjnc | U35: Limerick | V35: 161633 | W35: 117265 | X35: 52.306162 | Y35: -8.563212 | AA35: 163089 | AB35: 112378 | AC35: 52.262344 | AD35: -8.541331 | AE35: From Mitchelstown, take N73 towards Mallow. 3km after Kildorrery, take right turn for Donerail. Take the third right, then first right. This road leads all the way to the mast and is approx 9km long. | AF35: ISEO Locken ekey required for access. | AG35: 0 | AH35: 1 | AJ35: 1 | AM35: 1 | AN35: 1 | AO35: Towercom | AP35: Pallisade | AQ35: 3.2
A36: TCK4002 | B36: 45 | C36: TCK4002 | D36: Ballymakeeraa | F36: Active | H36: NO | J36: 122 | K36: Level 1 | L36: 108 | M36: Full SRF | N36: Full SAF | P36: 0 | Q36: 1 | R36: Cul Na Carrig Rd, Ballymakeera | T36: lsjncpsdjnc | U36: Cork | V36: 121356 | W36: 76663 | X36: 51.937058 | Y36: -9.144212 | AA36: 121360 | AB36: 76638 | AC36: 51.936832 | AD36: -9.144144 | AE36: Travelling from Ballycasheen travel South on the N22 for 14km to the village of Ballymakeeraa. Site entrance located after the centra shop on the left hand side. Entrance located 200m on left hand side. | AG36: 0 | AH36: 0 | AJ36: 1 | AM36: 0 | AN36: 1 | AO36: Eircom | AP36: None
A37: TRN5028 | B37: 46 | C37: TRN5028 | D37: Ballymoe | E37: Ballymoe Exchange | F37: Retired | H37: NO | J37: 59 | K37: Level 1 | L37: EED | M37: Full SRF | N37: Full SAF | P37: 0 | Q37: 1 | R37: Ballymoe | T37: lsjncpsdjnc | U37: Roscommon | V37: 170229 | W37: 272160 | X37: 53.69846 | Y37: -8.45147 | Z37: Tarmac | AA37: 170238 | AB37: 272146 | AC37: 53.69834 | AD37: -8.45133 | AE37: Travelling from Roscommon head North on Castle Street (N61) toward Cherry Drive. After 600m at roundabout take first exit onto racecourse (N60). Continue for 18.7km and site located on the right hand side. | AF37: ISEO electronic key required for site access. | AG37: 0 | AH37: 0 | AJ37: 0 | AM37: 0 | AN37: 1 | AO37: farmer | AP37: Timber Fence | AQ37: 2.4
A38: TWH6065 | B38: 47 | C38: TWH6065 | D38: Ballymore | F38: Active | H38: NO | J38: 81 | K38: Level 2 | L38: TC68 | M38: Full SRF | N38: Full SAF | P38: 1 | Q38: 1 | R38: Ballymore | T38: lsjncpsdjnc | U38: Westmeath | V38: 221854 | W38: 249079 | X38: 53.49148 | Y38: -7.67149 | Z38: Tarmac | AA38: 221861 | AB38: 249063 | AC38: 53.49134 | AD38: -7.67139 | AE38: Travelling from Mullingar heading West on R390, after 19.4km turn left onto Lower Street (R390) and site is located on right hand side. | AF38: ISEO Locken key required for access. | AG38: 0 | AH38: 0 | AJ38: 0 | AM38: 0 | AN38: 1 | AO38: Eircom | AP38: Pallisade | AQ38: 2.8
A39: TKE5029 | B39: 48 | C39: TKE5029 | D39: Ballymore Eustace | E39: Ballymore Eustace TE | F39: Retired | H39: NO | J39: 137 | K39: Level 2 | L39: EED | M39: Full SRF | N39: Full SAF | P39: 0 | Q39: 1 | R39: Ballymore Eustace | T39: lsjncpsdjnc | U39: Kildare | V39: 292585 | W39: 210300 | X39: 53.13551 | Y39: -6.61732 | Z39: Tarmac | AA39: 292580 | AB39: 210297 | AC39: 53.13545 | AD39: -6.61746 | AE39: From Naas take R411 and continue for 9.1km. Site is located on the right hand side. | AF39: elocks installed | AG39: 0 | AH39: 0 | AJ39: 0 | AM39: 0 | AN39: 1 | AO39: School grounds | AP39: Pallisade | AQ39: 2.4
A40: TSO5027 | B40: 49 | C40: TSO5027 | D40: Ballymote | F40: To be retired | H40: NO | J40: 80 | K40: Level 4 | L40: EED | M40: Full SRF | N40: Full SAF | P40: 0 | Q40: 1 | R40: Ballymote | T40: lsjncpsdjnc | U40: Sligo | V40: 166234 | W40: 315598 | X40: 54.08846 | Y40: -8.51674 | Z40: Tarmac | AA40: 166285 | AB40: 315630 | AC40: 54.08875 | AD40: -8.51596 | AE40: Travelling from Tubbercurry take R294 for 5.8km. Continue onto R296 for 1.8km, then turn left. After 550m turn right on R296 and continue for 4.7km. Take right turn and continue for 3km. Take right turn at Lord Edward Street and after 84m site is located on the right hand side. | AF40: Access through an Post gate, also lock on the gate | AG40: 0 | AH40: 0 | AJ40: 1 | AM40: 0 | AN40: 1 | AO40: AN Post
A41: TKK5031 | B41: 50 | C41: TKK5031 | D41: Ballyragget | E41: Ballyragget BRTA | F41: To be retired | H41: NO | J41: 76 | K41: Level 3 | L41: EED | M41: Full SRF | N41: Full SAF | P41: 1 | Q41: 1 | R41: Ballyragget | T41: lsjncpsdjnc | U41: Kilkenny | V41: 245043 | W41: 171293 | X41: 52.79113 | Y41: -7.33307 | Z41: Tarmac | AA41: 245056 | AB41: 171295 | AC41: 52.79115 | AD41: -7.33287 | AE41: From Dublin take N7 towards Portlaoise. Approaching Portlaoise take N8 to Abbeyleix and continue onto Durrow. In Durrow take N77 to Kilkenny, follow for 9km to Ballyragget Main St. Take left turn onto R694 towards Castlecomer. Continue for 100m and take left turn at fork in the road. Follow the road for a further 150m and site will be located on the left hand side. | AF41: Eircom lock on Palisade and Anti climb had padlock and chain | AG41: 0 | AH41: 0 | AJ41: 1 | AM41: 0 | AN41: 1 | AO41: Residential garden | AP41: Pallisade/Stone Wall Combination | AQ41: 1.8
A42: TDL7005 | B42: 51 | C42: TDL7005 | D42: Ballyshannon | E42: Ballyshannon Exch | F42: Active | H42: NO | I42: TDL5032 | J42: 10 | K42: Level 1 | L42: EED | M42: Full SRF | N42: Full SAF | P42: 1 | Q42: 1 | R42: Ballyshannon | T42: lsjncpsdjnc | U42: Donegal | V42: 187772 | W42: 361322 | X42: 54.50018 | Y42: -8.18949 | Z42: Tarmac | AA42: 187753 | AB42: 361357 | AC42: 54.5005 | AD42: -8.18977 | AE42: Travelling Bundoran take Finner Road (R237). After 5.5km go through roundabout, taking the first exit onto Main Street. Site is located on the right hand side. | AF42: barrier gates on way into site | AG42: 0 | AH42: 0 | AI42: Yes | AJ42: 0 | AM42: 0 | AN42: 1 | AO42: Credit union
A43: TKK1004 | B43: 52 | C43: TKK1004 | D43: Ballyspellan | E43: Spahill / Johnstown | F43: Active | H43: NO | J43: 308 | K43: Level 3 | L43: 108 | M43: Full SRF | N43: Full SAF | P43: 1 | Q43: 1 | R43: Spahill, Johnstown | T43: lsjncpsdjnc | U43: Kilkenny | V43: 233252 | W43: 167750 | X43: 52.760144 | Y43: -7.50819 | AA43: 233465 | AB43: 167630 | AC43: 52.759057 | AD43: -7.505049 | AE43: From Dublin, take N8 South towards Cork. In Johnstown Village turn left onto R435. Follow road for 1.2km then turn left onto Spathill. Follow road for 3.3km, site will be located on the left hand side. Mast will be visible from the road. Turn left onto access track and follow for 0.4km. | AF43: ISEO Locken ekey required for access. | AG43: 0 | AH43: 0 | AJ43: 1 | AM43: 1 | AN43: 1 | AO43: Towercom | AP43: Chainlink Fence | AQ43: 3
A44: TCK6407 | B44: 53 | C44: TCK6407 | D44: Baltimore | F44: Active | H44: NO | I44: TCK6007 | J44: 26 | K44: Level 2 | L44: TC68 | M44: Full SRF | N44: Full SAF | P44: 1 | Q44: 1 | R44: Baltimore | T44: lsjncpsdjnc | U44: Cork | V44: 104750 | W44: 26358 | X44: 51.48248 | Y44: -9.37186 | Z44: Tarmac | AA44: 104829 | AB44: 26444 | AC44: 51.48327 | AD44: -9.37075 | AE44: From Skibereen take Market Street (R595) for 4.7km. Turn left and stay on R595 for 3.2km. Take slight right and stay on R595 for 4.6km. Take left turn at New Road, and continue straight for 69m. Take first right turn onto Cliff Estate. After 29m entrance will be on the left hand side. | AF44: access site up many steps | AG44: 0 | AH44: 0 | AJ44: 0 | AM44: 0 | AN44: 0
A45: TWW5033 | B45: 54 | C45: TWW5033 | D45: Baltinglass | E45: Baltinglass Exchange | F45: Retired | H45: NO | J45: 128 | K45: Level 2 | L45: EED | M45: Full SRF | N45: Full SAF | P45: 1 | Q45: 1 | R45: Main St, Baltinglass | T45: lsjncpsdjnc | U45: Wicklow | V45: 286803 | W45: 188240 | X45: 52.93828 | Y45: -6.70967 | Z45: Tarmac | AA45: 286837 | AB45: 188271 | AC45: 52.93855 | AD45: -6.70917 | AE45: From Dublin take N81 to Baltinglass. On entering Baltinglass, stay on Main Street and pass Supevalu on the left. Continue through the crossroads for approx 800m. Site will be located on the right hand side. | AF45: Elock on anticlimb | AG45: 0 | AH45: 0 | AJ45: 0 | AM45: 0 | AN45: 1 | AO45: Residential gardens | AP45: None
A46: TDL1005 | B46: 56 | C46: TDL1005 | D46: Barnesmore | F46: Active | H46: NO | J46: 436 | K46: Level 3 | L46: 108 | M46: Full SRF | N46: Full SAF | P46: 0 | Q46: 1 | R46: Barnesmore Gap | T46: lsjncpsdjnc | U46: Donegal | V46: 203725 | W46: 385420 | X46: 54.716795 | Y46: -7.942951 | AA46: 204502 | AB46: 387713 | AC46: 54.73738 | AD46: -7.93086 | AE46: From Dublin, travel North on M1 to Omagh, then on to Ballybofey. Drive towards Donegal town on N56. Upon entering Barnesmore Gap area, take left turn just before small bridge. (Note: keep right at black/yellow sign on main road just before bridge). Turn left here and continue to second gate. After turning off N56 at small bridge, continue to second gate to access road. Continue along hardcore track to gate, turn left after gate. Continue until second right. Follow road to site location. Access track 3.8km in total. | AF46: ISEO Locken key required for access. | AG46: 0 | AH46: 0 | AI46: No | AJ46: 1 | AL46: Access to site requires 4x4 as some sections of the access track have no verge. The mast is at a higher elevation that the compound, caution required when accessing this area via ramp. | AM46: 1 | AN46: 0 | AO46: Land Owner | AP46: Pallisade | AQ46: 2.8
A47: TCE2003 | B47: 57 | C47: TCE2003 | D47: Behagh | F47: Active | H47: NO | J47: 21 | K47: Level 1 | L47: 108 | M47: Full SRF | N47: Full SAF | P47: 1 | Q47: 1 | R47: Dooneen, Behagh | T47: lsjncpsdjnc | U47: Clare | V47: 128588 | W47: 209187 | X47: 53.128756 | Y47: -9.067557 | AA47: 128586 | AB47: 209191 | AC47: 53.128756 | AD47: -9.067597 | AE47: From Galway, take N18 to Kilcolgan. From Kilcolgan, take N67 to Ballyvaghn. Site is located on the left, 23km from Kilcolgan village. Site entrance is 3m off main road. | AF47: LOCKEN ISEO keys required to access this site | AG47: 0 | AH47: 0 | AJ47: 1 | AM47: 1 | AN47: 1 | AO47: Eircom | AQ47: 1.2
A48: TDU5035 | B48: 58 | C48: TDU5035 | D48: Belcamp | F48: Active | H48: NO | J48: 35 | K48: Premium | L48: EED | M48: Full SRF | N48: Full SAF | P48: 1 | Q48: 1 | R48: Belcamp | T48: lsjncpsdjnc | U48: Dublin | V48: 320335 | W48: 239833 | X48: 53.39517 | Y48: -6.19178 | Z48: Tarmac | AA48: 320369 | AB48: 239890 | AC48: 53.39567 | AD48: -6.19124 | AE48: Travelling North on M50, at junction 3 take the M1 exit. After 1.9km take R104 exit toward Santry. After 500m at roundabout take first exit to Coolock (R104) and after 2.8km continue straight to Brookville Cresent. Turn left on Malahide Road and after 750m take slight left. After 450m turn left at Newtown Road, and left after 260m to Newtown Park and left after 94m to Newton Avenue. | AF48: Access to tower at rear, using ensup at main gate. Ensup required for main building | AG48: 1 | AH48: 0 | AJ48: 1 | AM48: 0 | AN48: 1 | AO48: Eircom | AP48: Pallisade | AQ48: 2.8
A49: TMO2004 | B49: 59 | C49: TMO2004 | D49: Belmullet | E49: Belmullet (BML) | F49: Active | H49: NO | J49: 19 | K49: Level 1 | L49: 108 | M49: Full SRF | N49: Full SAF | P49: 1 | Q49: 1 | R49: Barrack Street, Belmullet | T49: lsjncpsdjnc | U49: Mayo | V49: 70747 | W49: 332086 | X49: 54.221392 | Y49: -9.982388 | AA49: 70956 | AB49: 332000 | AC49: 54.220665 | AD49: -9.979144 | AE49: Follow main road into Belmullet. After passing 60kmh sign, take the next left. Follow road around and site is located on the right hand side. From the gates, walk straight ahead for 100m, turn left for the mast. | AF49: ISEO LOCKEN Electronic key required for access | AG49: 0 | AH49: 0 | AJ49: 1 | AM49: 1 | AN49: 1 | AO49: Eircom | AP49: Pallisade | AQ49: 2.4
A50: TCN5036 | B50: 60 | C50: TCN5036 | D50: Belturbet | E50: Belturbet TE Exchange | F50: Retired | H50: NO | J50: 68 | K50: Level 1 | L50: EED | M50: Full SRF | N50: Full SAF | P50: 0 | Q50: 1 | R50: Belturbert | T50: lsjncpsdjnc | U50: Cavan | V50: 236441 | W50: 316909 | X50: 54.10005 | Y50: -7.44372 | Z50: Tarmac | AA50: 236458 | AB50: 316898 | AC50: 54.09995 | AD50: -7.44346 | AE50: Travel Northwest on N3 from Cavan for 9km. Take left turn and stay on N3 for 2.9km. After turn left at Fairgreen and in 290m, site is located on right hand side. | AF50: ISEO LOCKEN key required for access | AG50: 0 | AH50: 0 | AI50: Yes | AJ50: 1 | AM50: 0 | AN50: 1 | AO50: An Post | AP50: Pallisade | AQ50: 2.4
A51: TCE1006 | B51: 61 | C51: TCE1006 | D51: Ben Dash | F51: Active | H51: NO | J51: 250 | K51: Level 3 | L51: 108 | M51: Full SRF | N51: Full SAF | P51: 0 | Q51: 1 | R51: Ben Dash, Kilmaley, Ennis | T51: lsjncpsdjnc | U51: Clare | V51: 121399 | W51: 171285 | X51: 52.787208 | Y51: -9.165739 | AA51: 121861 | AB51: 171696 | AC51: 52.790967 | AD51: -9.158998 | AE51: From Ennis, take road for Milltown Malbay. About 6 miles from Ennis, take left at Kilmarley Inn. Follow this road for 1 mile, go straight at staggered cross (right then left). Take next turn right. This will lead to tower. Access track is 2.5km long and very rough. After 2km the track splits, keep right. Follow road and take left after 200m through Coillte barrier. This will take you up the last 500m. | AF51: ISEO Locken ekey required for access. | AG51: 0 | AH51: 1 | AJ51: 1 | AM51: 1 | AN51: 1 | AO51: Coillte | AP51: Pallisade | AQ51: 2.8
A52: TMH5037 | B52: 62 | C52: TMH5037 | D52: Bettystown | F52: Retired | H52: NO | J52: 7 | K52: Level 2 | L52: EED | M52: Full SRF | N52: Full SAF | P52: 0 | Q52: 1 | R52: Bettystown | T52: lsjncpsdjnc | U52: Meath | V52: 315928 | W52: 273535 | X52: 53.69881 | Y52: -6.24551 | Z52: Tarmac | AA52: 315947 | AB52: 273512 | AC52: 53.6986 | AD52: -6.24523 | AE52: Travelling from Drogheda head Southeast towards St. Marys Villa's. After 3km turn left at Piltown Road. Continue for 700m, then turn right and stay on Piltown Road. After 1.5km continue on to Balbriggan and in 400m turn right at Narroways. After 900m turn right at Maples and in 500m continue onto Triton Road. Site is located on left hand side. | AF52: Main gate with eircom lock. Elock installed on anticlimb | AG52: 0 | AH52: 0 | AI52: On street parking available - pay & display | AJ52: 0 | AM52: 0 | AN52: 0 | AP52: Pallisade | AQ52: 2.8
A53: TLH5039 | B53: 64 | C53: TLH5039 | D53: Blackrock | E53: Blackrock Exchange | F53: Retired | H53: NO | J53: 13 | K53: Level 3 | L53: EED | M53: Full SRF | N53: Full SAF | P53: 0 | Q53: 1 | R53: Old Golflinks Rd, Dundlak | T53: lsjncpsdjnc | U53: Louth | V53: 305745 | W53: 303574 | X53: 53.97074 | Y53: -6.38931 | Z53: Tarmac | AA53: 305751 | AB53: 303538 | AC53: 53.97042 | AD53: -6.38923 | AE53: From Dublin take M1 to Dundalk, take 1st exit off M1 for Dundalk onto N52. Follow for approx 2.2km and take right turn onto R132. Follow for 1.1km and take left on Old Golf Links Rd. Site is located at junction of R132 and Old Golf Links Rd and is across from Felda Health and Fitness Spa. | AG53: 0 | AH53: 0 | AJ53: 1 | AM53: 0 | AN53: 1 | AO53: Private residence | AQ53: 1.2
A54: TMO6349 | B54: 65 | C54: TMO6349 | D54: Blacksod | F54: To be Retired | H54: NO | I54: TMO6049 | J54: 22 | K54: Level 1 | L54: TC68 | M54: Full SRF | N54: Full SAF | P54: 0 | Q54: 1 | R54: Blacksod | T54: lsjncpsdjnc | U54: Mayo | V54: 62869 | W54: 322412 | X54: 54.13249 | Y54: -10.09868 | Z54: Tarmac | AA54: 62886 | AB54: 322403 | AC54: 54.13242 | AD54: -10.09841 | AE54: Travelling from Belmullet, take the R313 and continue 14.2km. Site is located on the left hand side in Newtown. | AF54: LOCKEN Ekey required for access | AG54: 0 | AH54: 0 | AI54: Yes | AJ54: 1 | AM54: 1 | AN54: 1 | AO54: Farming | AP54: Pallisade | AQ54: 2.4
A55: TWX4003 | B55: 66 | C55: TWX4003 | D55: Blackwater RSU | F55: To be Retired | H55: NO | J55: 51 | K55: Level 2 | L55: 108 | M55: Full SRF | N55: Full SAF | P55: 0 | Q55: 1 | R55: Blackwater GAA pitch, Blackwater | T55: lsjncpsdjnc | U55: Wexford | V55: 312091 | W55: 133687 | X55: 52.44359 | Y55: -6.35227 | Z55: Hardcore | AA55: 312074 | AB55: 133570 | AC55: 52.44255 | AD55: -6.35256 | AE55: From Enniscorthy Town take R744 East for approx 20km to Blackwater. Arrive in Blackwater Village and take right turn at T-Junction. Follow road (R742) for 600m to St. Brigids GAA club. Turn into club and follow road to clubhouse, take right turn and site entrance will be straight ahead. | AF55: Electronic ISEO LOCKEN key required for access | AG55: 0 | AH55: 0 | AJ55: 1 | AM55: 0 | AN55: 1 | AO55: Eircom | AP55: Pallisade | AQ55: 2.8
A56: TTP6063 | B56: 69 | C56: TTP6063 | D56: Borrisokane | F56: Retired | H56: NO | J56: 62 | K56: Level 2 | L56: TC68 | M56: Full SRF | N56: Full SAF | P56: 1 | Q56: 1 | R56: Shesharaghmore, Borrisokane | T56: lsjncpsdjnc | U56: Tipperary | V56: 191632 | W56: 193682 | X56: 52.99412 | Y56: -8.12535 | Z56: Tarmac | AA56: 191623 | AB56: 193630 | AC56: 52.99365 | AD56: -8.12549 | AE56: Traveling from Birr, take N52 towards R489 for 18.4km. Take a left and take first left onto Main Street. Continue out the Cloughjordan Road for 300m and site entrance will be on the left hand side beside pitch entrance. | AF56: access close to neighbouring house. ISEO Locken ekey required for access. | AG56: 0 | AH56: 0 | AJ56: 1 | AM56: 0 | AN56: 1 | AO56: Neighbour house & GAA entrance | AP56: Pallisade | AQ56: 2.8
A57: TRN7007 | B57: 70 | C57: TRN7007 | D57: Boyle | F57: To be Retired | H57: NO | I57: TRN5042 | J57: 69 | K57: Level 2 | L57: EED | M57: Full SRF | N57: Full SAF | P57: 1 | Q57: 1 | R57: Green St, Boyle | T57: lsjncpsdjnc | U57: Roscommon | V57: 180107 | W57: 302772 | X57: 53.97395 | Y57: -8.3039 | Z57: Tarmac | AA57: 180116 | AB57: 302779 | AC57: 53.97402 | AD57: -8.30377 | AE57: From Longford take N4 to Boyle. Nearing Boyle take N61 to roundabout and take last exit onto R294 which leads onto Military Road. Continue on road for 400m onto Main St and take sharp right turn onto Green Street signposted Credit Union" up a steep hilh. Follow road for 170m and site will be on the right hand side." | AF57: Locken ekey required for access. | AG57: 0 | AH57: 0 | AJ57: 1 | AM57: 0 | AN57: 1 | AO57: Eircom compound | AP57: Pallisade | AQ57: 2.4
A58: TOY2005 | B58: 71 | C58: TOY2005 | D58: Bracknagh | F58: UTS | H58: NO | I58: TKE2005 | J58: 64 | K58: Level 1 | L58: 108 | M58: Full SRF | N58: Full SAF | P58: 0 | Q58: 1 | R58: Bracknagh | T58: lsjncpsdjnc | U58: Offaly | V58: 260625 | W58: 217941 | X58: 53.208708 | Y58: -7.093377 | AA58: 260563 | AB58: 217850 | AC58: 53.207908 | AD58: -7.094311 | AE58: Travelling from Rathangan into Bracknagh, site is located down a laneway just before the school on the right hand side. | AF58: ISEO Locken ekey required for access | AG58: 0 | AH58: 0 | AJ58: 1 | AM58: 1 | AN58: 1 | AO58: Eircom | AP58: Pallisade | AQ58: 2.4
A59: TSO1007 | B59: 72 | C59: TSO1007 | D59: Bralee | F59: Active | H59: NO | J59: 235 | K59: Level 3 | L59: 108 | M59: Full SRF | N59: Full SAF | P59: 1 | Q59: 1 | R59: Bralee | T59: lsjncpsdjnc | U59: Sligo | V59: 158235 | W59: 326630 | X59: 54.186974 | Y59: -8.640495 | AA59: 158475 | AB59: 325623 | AC59: 54.17795 | AD59: -8.63668 | AE59: From Dublin, take the N4 towards Sligo. Before Sligo town take the exit for Ballina (N59). Follow signs for Ballina. Turn left at Signpost for Cooloney. After 450m keep left. After 3.5km turn right signposted for The Ox Mountain". Continue along this road ignoring coillte barrier. After 2.5km turn right onto access road to site." | AF59: ISEO Locken ekey required for access. | AG59: 0 | AH59: 0 | AJ59: 1 | AM59: 1 | AN59: 1 | AO59: Towercom | AP59: Pallisade | AQ59: 3.2
A60: TKY6030 | B60: 73 | C60: TKY6030 | D60: Brosna | F60: Active | H60: NO | J60: 124 | K60: Level 2 | L60: TC68 | M60: Full SRF | N60: Full SAF | P60: 1 | Q60: 1 | R60: Brosna | T60: lsjncpsdjnc | U60: Kerry | V60: 113297 | W60: 118691 | X60: 52.31347 | Y60: -9.27207 | Z60: Tarmac | AA60: 113279 | AB60: 118685 | AC60: 52.31341 | AD60: -9.27233 | AE60: From Limerick continue on N21 for 54km,turn left toward R576, then after take slight left at R576, continue 5.7km turn right to Brosna. After 1.3km site is located on the left hand side. | AF60: Electronic LOCKEN key required for access | AG60: 0 | AH60: 0 | AJ60: 1 | AM60: 0 | AN60: 0 | AP60: Pallisade | AQ60: 2.8
A61: TDL2006 | B61: 74 | C61: TDL2006 | D61: Bunbeg | F61: Active | H61: NO | J61: 42 | K61: Level 1 | L61: 108 | M61: Full SRF | N61: Full SAF | P61: 1 | Q61: 1 | R61: Factory Road, Bunbeg | T61: lsjncpsdjnc | U61: Donegal | V61: 181678 | W61: 424468 | X61: 55.06722 | Y61: -8.28753 | AA61: 181696 | AB61: 424443 | AC61: 55.067003 | AD61: -8.287246 | AE61: From N56, take R258 and follow for 2km. Take right turn and follow for 1.4km. Take left turn at end of road, follow for 150m followed by immediate right turn. Continue for 850m (pass NCT centre on left). Tower entrance is on the right hand side. | AF61: ISEO electronic key required for access. | AG61: 0 | AH61: 0 | AI61: No | AJ61: 1 | AM61: 1 | AN61: 1 | AO61: Eircom | AP61: Pallisade | AQ61: 2.4
A62: TDL5043 | B62: 75 | C62: TDL5043 | D62: Bundoran | F62: Retired | H62: NO | J62: 13 | K62: Level 3 | L62: EED | M62: Full SRF | N62: Full SAF | P62: 0 | Q62: 1 | R62: Drumacrin, County Donegal | T62: lsjncpsdjnc | U62: Donegal | V62: 182133 | W62: 358808 | X62: 54.47743 | Y62: -8.27636 | Z62: Tarmac | AA62: 182106 | AB62: 358833 | AC62: 54.47765 | AD62: -8.27678 | AE62: Travelling North on N15 from Sligo, after 31.2km take 2nd exit at roundabout onto Magheracar. Continue onto Main Street and after 400m turn right at Railway Road. Continue through roundabout and site is located on the right hand side. | AF62: Main gate in camping park with a key pad entrance | AG62: 0 | AH62: 0 | AJ62: 0 | AM62: 0 | AN62: 1 | AO62: Camp owner | AP62: Pallisade | AQ62: 3
A63: TCK7008 | B63: 76 | C63: TCK7008 | D63: Buttevant | F63: Active | H63: NO | I63: TCK5044 | J63: 103 | K63: Level 1 | L63: EED | M63: Full SRF | N63: Full SAF | P63: 0 | Q63: 1 | R63: Buttevant | T63: lsjncpsdjnc | U63: Cork | V63: 154188 | W63: 108791 | X63: 52.22944 | Y63: -8.67119 | Z63: Tarmac | AA63: 154205 | AB63: 108758 | AC63: 52.22915 | AD63: -8.67094 | AE63: Travelling South on N20, go straight through Buttevant and pass Kerry Lane (R580) turn off. Take the right turn after it. Site will be located on the left hand side, behind garda station. | AF63: access gate with lock that the neighbours have. | AG63: 0 | AH63: 0 | AJ63: 1 | AM63: 0 | AN63: 1 | AO63: Housing
A64: TCK3002 | B64: 78 | C64: TCK3002 | D64: Bweeng | E64: Bweengduff | F64: Active | H64: YES | J64: 412 | K64: Level 2 | L64: 108 | M64: Full SRF | N64: Full SAF | P64: 1 | Q64: 1 | R64: Bweengduff, Mallow | T64: lsjncpsdjnc | U64: Cork | V64: 146799 | W64: 90392 | X64: 52.063 | Y64: -8.776 | AA64: 145997 | AB64: 91401 | AC64: 52.07243 | AD64: -8.78829 | AE64: Follow road from Mallow to Bweeng. Take right turn in Bweeng. Take first left at fork in the road. Entrance to site is 100m on the left hand side. Coillte gate, follow forrest track to site. | AF64: Keys for Coillte gate on access track can be obtained from Towercom before access is due to go ahead. ISEO Locken ekey required for access. | AG64: 0 | AH64: 0 | AJ64: 0 | AM64: 1 | AN64: 1 | AO64: Coillte | AP64: Pallisade | AQ64: 2.8
A65: TDU5045 | B65: 79 | C65: TDU5045 | D65: Cabra | E65: Cabra Exchange | F65: Active | H65: NO | J65: 51 | K65: Premium | L65: EED | M65: Full SRF | N65: Full SAF | P65: 1 | Q65: 1 | R65: Hampton Rd, Cabra | T65: lsjncpsdjnc | U65: Dublin | V65: 313020 | W65: 236025 | X65: 53.36258 | Y65: -6.30305 | Z65: Tarmac | AA65: 313077 | AB65: 236015 | AC65: 53.36248 | AD65: -6.30221 | AE65: From M50 take N3 exit to City Centre. Stay on Navan Road (N3) for 4.6km. As you approach Audi, Mercedes and Mazda garages on the right hand side, there will be a right hand turn for Hampton Road. Take right turn and follow road for 30m. Site entrance will be on the right hand side. | AF65: ENSUP on main gate and access to rooftop . Locken keys required for access. | AG65: 1 | AH65: 0 | AJ65: 1 | AM65: 0 | AN65: 1 | AO65: Houses on 2 sides of exchange, roads on other sides | AP65: Pallisade/Stone Wall Combination | AQ65: 2.4
A66: TKY6431 | B66: 81 | C66: TKY6431 | D66: Caherdaniel | F66: Active | H66: NO | I66: TKY6031 | J66: 36 | K66: Level 1 | L66: TC68 | M66: Full SRF | N66: Full SAF | P66: 0 | Q66: 1 | R66: Caherdaniel | T66: lsjncpsdjnc | U66: Kerry | V66: 55187 | W66: 59608 | X66: 51.77061 | Y66: -10.09863 | Z66: Tarmac | AA66: 55203 | AB66: 59579 | AC66: 51.77035 | AD66: -10.09838 | AE66: From Kenmare take N70 to Caherdaniel. In Caherdaniel take right turn signposted for Coomnahorna / Garrough". Follow road for 120m, site will be on the right hand side. | AG66: 0 | AH66: 0 | AJ66: 1 | AM66: 0 | AN66: 1 | AO66: Farmer | AP66: Chainlink Fence w/Barbed Wire | AQ66: 1.8
A67: TKY5046 | B67: 82 | C67: TKY5046 | D67: Caherdaniel | F67: Active | H67: NO | J67: 42 | K67: Level 1 | L67: EED | M67: Full SRF | N67: Full SAF | P67: 0 | Q67: 1 | R67: Caherdaniel | T67: lsjncpsdjnc | U67: Kerry | V67: 55187 | W67: 59608 | X67: 51.77061 | Y67: -10.09863 | Z67: Tarmac | AA67: 55203 | AB67: 59579 | AC67: 51.77035 | AD67: -10.09838 | AE67: From Kenmare take N70 to Caherdaniel. In Caherdaniel take right turn signposted for Coomnahorna / Garrough". Follow road for 120m, site will be on the right hand side.] | AG67: 0 | AH67: 0 | AJ67: 1 | AM67: 0 | AN67: 1 | AO67: Farmer | AP67: Chainlink Fence w/Barbed Wire | AQ67: 1.8
A68: TKY1008 | B68: 83 | C68: TKY1008 | D68: Caherdaniel | E68: Caherdaniel (RL) | F68: Active | H68: NO | J68: 60 | K68: Level 1 | L68: 108 | M68: Full SRF | N68: Full SAF | P68: 0 | Q68: 1 | R68: Caherdaniel | T68: lsjncpsdjnc | U68: Kerry | V68: 55383 | W68: 58834 | X68: 51.763704 | Y68: -10.095465 | AA68: 55207 | AB68: 58736 | AC68: 51.762779 | AD68: -10.09797 | AE68: Driving from Sneem to Caherdaniel there is an access track directly off the main road. It is approx 3/4 mile before the village after the Derrynane Hotel. There will be a farmer's gate on the main road, and another approx 50m further up the lane. | AF68: Farmer gate on access track is unlocked. | AG68: 0 | AH68: 0 | AJ68: 1 | AM68: 1 | AN68: 1 | AO68: Land Owner | AP68: Chainlink Fence | AQ68: 1.2
A69: TKY5049 | B69: 85 | C69: TKY5049 | D69: Camp | E69: Camp Exchange | F69: Active | H69: NO | J69: 62 | K69: Level 2 | L69: EED | M69: Full SRF | N69: Full SAF | P69: 1 | Q69: 1 | R69: Camp | T69: lsjncpsdjnc | U69: Kerry | V69: 69828 | W69: 109414 | X69: 52.22157 | Y69: -9.90556 | Z69: Tarmac | AA69: 66490 | AB69: 109474 | AC69: 52.22131 | AD69: -9.9544 | AE69: Travelling from Tralee, take 3rd exit at the roundabout towards Dingle (N86). After 1.9km turn left on Dingle (N86). Continue for 13.3km and site will be located on the left hand side. | AF69: Access at side path of garda station | AG69: 0 | AH69: 0 | AJ69: 1 | AM69: 0 | AN69: 0
A70: TWX2007 | B70: 86 | C70: TWX2007 | D70: Campile | E70: Campile Exchange | F70: Active | H70: NO | J70: 31 | K70: Level 1 | L70: 108 | M70: Full SRF | N70: Full SAF | P70: 1 | Q70: 1 | R70: Campile | T70: lsjncpsdjnc | U70: Wexford | V70: 272289 | W70: 114761 | X70: 52.280249 | Y70: -6.941543 | AA70: 272302 | AB70: 114753 | AC70: 52.280181 | AD70: -6.941359 | AE70: From New Ross, follow R733 towards Campile. Go through the village and take 1st right. Site is located on right approx 400m. Parking available in front of compound. | AF70: ISEO locken key required | AG70: 0 | AH70: 0 | AJ70: 1 | AM70: 1 | AN70: 1 | AO70: Eircom | AP70: Post & Rail Fence | AQ70: 1.2
A71: TLS1010 | B71: 88 | C71: TLS1010 | D71: Capard | F71: Active | H71: YES | J71: 338 | K71: Level 4 | L71: 108 | M71: Full SRF | N71: Full SAF | P71: 0 | Q71: 1 | R71: Ridge of Capard | T71: lsjncpsdjnc | U71: Laois | V71: 236620 | W71: 206760 | X71: 53.110443 | Y71: -7.45391 | Z71: Hardcore | AA71: 237020 | AB71: 206430 | AC71: 53.107451 | AD71: -7.447975 | AE71: Travelling towards 'Rosenallis' from Mountmellick take a left on the bad bend in the middle of the village of 'Rosenallis'. Continue on for approx 3km until you reach a T-Junction. Turn right, after 1km you come to a 'Y' in the road. Keep right, after 0.5km take right on the bend. Continue on this road for 2.5km and black gates to site access will be on your right. | AF71: elocks installed on site | AG71: 0 | AH71: 0 | AJ71: 1 | AL71: Aluminum Structure, therefore it is susceptible to Algae build-up. Extra caution to be used when climbing structure. | AM71: 1 | AN71: 1 | AO71: Land Owner | AP71: Pallisade | AQ71: 2.8
A72: TKE1009 | B72: 89 | C72: TKE1009 | D72: Cappagh | E72: Newtown | F72: Active | H72: NO | J72: 144 | K72: Premium | L72: 108 | M72: Full SRF | N72: Full SAF | P72: 1 | Q72: 1 | R72: Cappagh Hill, Killickaweeny | T72: lsjncpsdjnc | U72: Kildare | V72: 283475 | W72: 240147 | X72: 53.40509 | Y72: -6.745637 | AA72: 283499 | AB72: 240164 | AC72: 53.405239 | AD72: -6.745269 | AE72: From Dublin take N4. Turn off for Kilcock / Enfield exit (before Toll Bridge). Follow signs for Enfield along Old Galway Road. After about 4km arrive at a crossroads, take left turn signposted for Newtown. Follow towards Newtown for approx 2km and tower will be on the right hand side. | AF72: ISEO Locken keys required for access. | AG72: 0 | AH72: 0 | AJ72: 1 | AM72: 1 | AN72: 1 | AO72: Land Owner | AP72: Pallisade | AQ72: 2.8
A73: TKY1011 | B73: 90 | C73: TKY1011 | D73: Capparoe | E73: Templenoe | F73: Active | H73: NO | J73: 170 | K73: Level 2 | L73: 108 | M73: Full SRF | N73: Full SAF | P73: 1 | Q73: 1 | R73: Capparoe | T73: lsjncpsdjnc | U73: Kerry | V73: 80992 | W73: 69335 | X73: 51.864066 | Y73: -9.728336 | AA73: 82022 | AB73: 68998 | AC73: 51.86126 | AD73: -9.713327 | AE73: Coming from Kenmare towards Sneem, about 5km out there is a signpost for 'Coomnakilla'. Take the next right after this (approx 100m). Road follows for approx 2.5km to site. The first 1.5km is small road to a viewing point. After this, road turns into a track (4x4 advised). Last 200m is tarmac. | AF73: ISEO Locken electronic key required for access. | AG73: 0 | AH73: 1 | AJ73: 1 | AM73: 1 | AN73: 1 | AO73: Coillte | AP73: Pallisade | AQ73: 2.4
A74: TGY1012 | B74: 92 | C74: TGY1012 | D74: Cappataggle | F74: Active | H74: YES | J74: 134 | K74: Level 2 | L74: 108 | M74: Full SRF | N74: Full SAF | P74: 1 | Q74: 1 | R74: Cappataggle | T74: lsjncpsdjnc | U74: Galway | V74: 172630 | W74: 225270 | X74: 53.27731 | Y74: -8.411025 | AA74: 172664 | AB74: 225275 | AC74: 53.27735 | AD74: -8.41052 | AE74: From Ballinasloe, follow N6 to Galway City for 12km. Take right turn at junction with sign for Cappataggle. Follow road for 1.2km, take right turn. Follow for 120m, tower entrance on the right. | AF74: ISEO Locken electronic key required for access | AG74: 0 | AH74: 0 | AJ74: 1 | AM74: 1 | AN74: 1 | AO74: Towercom | AP74: Pallisade | AQ74: 2.8
A75: TMH5050 | B75: 93 | C75: TMH5050 | D75: Carlanstown | E75: Carlanstown Exch | F75: Retired | H75: NO | J75: 62 | K75: Level 1 | L75: EED | M75: Full SRF | N75: Full SAF | P75: 0 | Q75: 1 | R75: Carlanstown | T75: lsjncpsdjnc | U75: Meath | V75: 276534 | W75: 279588 | X75: 53.76043 | Y75: -6.8403 | Z75: Tarmac | AA75: 276534 | AB75: 279571 | AC75: 53.76028 | AD75: -6.84031 | AE75: Travelling from Kells take Northeast on Maudlin Street toward Stonebridge for 4.6km on N52. Site will be located on the right hand side. | AF75: elocks installed on site | AG75: 0 | AH75: 0 | AJ75: 1 | AM75: 0 | AN75: 1 | AO75: School grounds | AP75: Pallisade | AQ75: 2.4
A76: TLH7010 | B76: 94 | C76: TLH7010 | D76: Carlingford | F76: Retired | H76: NO | I76: TLH5051 | J76: 13 | K76: Level 2 | L76: EED | M76: Full SRF | N76: Full SAF | P76: 0 | Q76: 1 | R76: Castle Hill St, Carlingford | T76: lsjncpsdjnc | U76: Louth | V76: 318774 | W76: 311731 | X76: 54.04116 | Y76: -6.18767 | Z76: Tarmac | AA76: 318775 | AB76: 311716 | AC76: 54.04103 | AD76: -6.18766 | AE76: From Dundalk take R173 to Carlingford. Arrive in town and follow one way system around town until you reach the dock. Go past and take right turn onto Market St, then take 2nd right turn and follow road for 300m and take sharp left turn onto Castle Hill St. Follow for 100m and site will be on L.H.S. | AF76: 1 x eircom padlock on pedestrian gate | AG76: 0 | AH76: 0 | AJ76: 1 | AM76: 0 | AN76: 1 | AO76: Garda station on one side / residential garden on other side | AP76: Stone Wall | AQ76: 1.8
A77: TCW5053 | B77: 95 | C77: TCW5053 | D77: Carlow Town Centre | E77: Carlow Exchange | F77: Active | H77: NO | J77: 83 | K77: Level 4 | L77: EED | M77: Full SRF | N77: Full SAF | P77: 0 | Q77: 1 | R77: Eircom exchange, Kennedy Ave, Carlow | T77: lsjncpsdjnc | U77: Carlow | V77: 272072 | W77: 176612 | X77: 52.83599 | Y77: -6.93131 | Z77: Tarmac | AA77: 272049 | AB77: 176572 | AC77: 52.83563 | AD77: -6.93165 | AE77: From Dublin take N7 onto N9 towards Carlow. Take N80 turnoff for Carlow town. Follow road for 4.4km to roundabout and go straight through onto R431. Follow R431 (Tullow Rd) for 1.2km, proceeding through 2 more roundabouts and take left turn and follow road for 120m to another roundabout. Take last exit onto Kennedy Avenue and site will be 200m down on R.H.S. beside Main An Post office | AF77: ENSUP for rooftop and ground access | AG77: 1 | AH77: 0 | AJ77: 0 | AM77: 0 | AN77: 1 | AO77: Urban area - commercial land surrounds site | AQ77: 1.2
A78: TCW5052 | B78: 96 | C78: TCW5052 | D78: Carlow Town North | E78: Carlow | F78: Retired | H78: NO | J78: 57 | K78: Level 3 | L78: EED | M78: Full SRF | N78: Full SAF | P78: 1 | Q78: 1 | R78: Eircom exchange, Cannery Rd, Carlow | T78: lsjncpsdjnc | U78: Carlow | V78: 272602 | W78: 177690 | X78: 52.8456 | Y78: -6.9232 | Z78: Tarmac | AA78: 272608 | AB78: 177615 | AC78: 52.84493 | AD78: -6.92313 | AE78: From Dublin take N7 onto N9 towards Carlow. Take N80 turnoff for Carlow town. Follow road for 4.4km to roundabout and continue on ring road around onto Dr. Cullen road and then onto Cannery Rd. Take left turn before Athy Rd roundabout, turn will be signposted for "Delta Sensory Gardens". Take turn and follow around industrial estate for 550m. Site will be on R.H.S. | AF78: elocks installed on this site. LOCKEN ISEO key required | AG78: 0 | AH78: 0 | AJ78: 1 | AM78: 0 | AN78: 1 | AO78: Commercial buildings and eircom compound | AP78: Pallisade | AQ78: 2.4
A79: TDL6312 | B79: 97 | C79: TDL6312 | D79: Carndonagh | F79: To be Retired | H79: NO | I79: TDL6012 | J79: 34 | K79: Level 3 | L79: TC68 | M79: Full SRF | N79: Full SAF | P79: 1 | Q79: 1 | R79: Carndonagh | T79: lsjncpsdjnc | U79: Donegal | V79: 246916 | W79: 445236 | X79: 55.25188 | Y79: -7.26301 | Z79: Tarmac | AA79: 246963 | AB79: 445239 | AC79: 55.2519 | AD79: -7.26227 | AE79: Travelling northwest from quigley point R242 continue 12.1km,at roundabout take 1st exit onto station rd,after 120m turn left onto malin head and continue onto back lane and exchange is located on the right. | AF79: Main gate eircom lock. Electronic key required for access. | AG79: 0 | AH79: 0 | AJ79: 1 | AM79: 0 | AN79: 0 | AO79: Eircom | AQ79: 2.8
A80: TCE1013 | B80: 98 | C80: TCE1013 | D80: Carran | F80: To be Retired | H80: NO | J80: 151 | K80: Level 1 | L80: 108 | M80: Full SRF | N80: Full SAF | P80: 1 | Q80: 1 | R80: Carran | T80: lsjncpsdjnc | U80: Clare | V80: 127561 | W80: 198620 | X80: 53.03365 | Y80: -9.080527 | AA80: 127552 | AB80: 198592 | AC80: 53.033397 | AD80: -9.080645 | AE80: From Carran town, as you pass church on the right, take right turn 300m after the Church. Follow road for 400m. Site is located on the right hand side. | AF80: ISEO Locken electronic key required for access. | AG80: 0 | AH80: 0 | AJ80: 1 | AM80: 1 | AN80: 1 | AO80: Towercom | AP80: Stone Wall | AQ80: 1.5
A81: TMN2008 | B81: 99 | C81: TMN2008 | D81: Carrickmacross | F81: Active | H81: NO | J81: 44 | K81: Level 3 | L81: 108 | M81: Full SRF | N81: Full SAF | P81: 1 | Q81: 1 | R81: Chapel Lane, Carrickmacross | T81: lsjncpsdjnc | U81: Monaghan | V81: 284138 | W81: 303848 | X81: 53.977166 | Y81: -6.718398 | AA81: 284194 | AB81: 303827 | AC81: 53.976965 | AD81: -6.717553 | AE81: From Dublin, travel North on N2. Take exit for Carrickmacross and continue towards town centre. N2 -> R178 -> O'Neill Street -> Main Street. Turn right off Carrickmacross main street into Chapel Lane. After 100m turn left into site entrance. | AF81: ISEO Locken key required for access. | AG81: 0 | AH81: 0 | AJ81: 1 | AM81: 1 | AN81: 1 | AO81: Eircom | AP81: Pallisade | AQ81: 2.8
A82: TLM5054 | B82: 100 | C82: TLM5054 | D82: Carrick-on-Shannon | F82: UTS | H82: NO | J82: 58 | K82: Level 3 | L82: EED | M82: Full SRF | N82: Full SAF | P82: 1 | Q82: 1 | R82: Carrick-on-Shannon | T82: lsjncpsdjnc | U82: Leitrim | V82: 193677 | W82: 299614 | X82: 53.94593 | Y82: -8.09704 | Z82: Tarmac | AA82: 193748 | AB82: 299549 | AC82: 53.94534 | AD82: -8.09595 | AE82: Travelling from boyle take Carrick Rd/R294 for 2.1km,turn right at N4 continue 12.2km,after take 1st exit on roundabout,700m take 1st exit at roundabout onto dublin road,400mturn left at main St,after 350m turn right to St.Georges terrace,site located on right. | AF82: Ensup required for main gate. Elock installed | AG82: 0 | AH82: 0 | AJ82: 1 | AM82: 0 | AN82: 1 | AO82: Eircom
A83: TTP3003 | B83: 101 | C83: TTP3003 | D83: Carrigadoon Hill | E83: Carrigadoon | F83: Active | H83: NO | J83: 270 | K83: Level 3 | L83: 108 | M83: Full SRF | N83: Full SAF | P83: 1 | Q83: 1 | R83: Carrigadoon Hill, Ahenny | T83: lsjncpsdjnc | U83: Tipperary | V83: 240111 | W83: 128900 | X83: 52.41059 | Y83: -7.411295 | AA83: 241300 | AB83: 127875 | AC83: 52.401292 | AD83: -7.39395 | AE83: From Carrick-on-Suir, take R697 for 9km. Turn left at sign for Ahenny high crosses?". Follow road for 1km. Turn left in Ahenny. Go straight for 100m, then follow road to left. Follow for 2km. Just after sign for 80km/h turn right onto Coillte access track. Follow track for 3km to site. | AF83: Unlocked Coillte barrier on access track. Forest Manager: Finbarr Welsh (086-3813512). ISEO LOCKEN Electronic key required for access | AG83: 0 | AH83: 1 | AJ83: 1 | AM83: 1 | AN83: 1 | AO83: Coillte | AP83: Pallisade | AQ83: 2.8
A84: TCK5089 | B84: 102 | C84: TCK5089 | D84: Dennehy's Cross | E84: Carrigrohane | F84: Active | H84: NO | J84: 29 | K84: Level 4 | L84: EED | M84: Full SRF | N84: Full SAF | P84: 1 | Q84: 1 | R84: Victoria Cross | T84: lsjncpsdjnc | U84: Cork | V84: 165134 | W84: 71675 | X84: 51.890753 | Y84: -8.507228 | Z84: Tarmac | AA84: 165142 | AB84: 71037 | AC84: 51.890753 | AD84: -8.507228 | AE84: From Merchants Quay in Cork City stay on N22 westbound. Follow for approx 3km. Shortly after passing by UCC (on L.H.S.) take left turn onto N71. Follow N71 for 250m and take right turn onto Victoria Cross (turn is opposite Balckwater Motors). Follow road for 50m and site will be on L.H.S. | AF84: ENSUP for rooftop and site access | AG84: 1 | AH84: 0 | AJ84: 1 | AM84: 0 | AN84: 1 | AO84: Sitre surrounded by apartments | AP84: Pallisade/Stone Wall Combination | AQ84: 2.4
A85: TGY6020 | B85: 103 | C85: TGY6020 | D85: Cashel | F85: Active | H85: NO | J85: 8 | K85: Level 2 | L85: TC68 | M85: Full SRF | N85: Full SAF | P85: 1 | Q85: 1 | R85: Scrahallia, Cashel | T85: lsjncpsdjnc | U85: Galway | V85: 78567 | W85: 242879 | X85: 53.42226 | Y85: -9.82736 | Z85: Tarmac | AA85: 78550 | AB85: 242883 | AC85: 53.42229 | AD85: -9.82762 | AE85: Travelling from Recess northwest on N59, take left onto R340 and continue 4.9km, turn right and continue 5.6km and site located on left hand side. | AF85: elocks installed on site - electronic LOCKEN key required | AG85: 0 | AH85: 0 | AJ85: 1 | AM85: 0 | AN85: 1 | AO85: Eircom | AP85: Pallisade | AQ85: 2.8
A86: TSO2009 | B86: 104 | C86: TSO2009 | D86: Cashelgarren | F86: Active | H86: NO | J86: 90 | K86: Level 3 | L86: 108 | M86: Full SRF | N86: Full SAF | P86: 1 | Q86: 1 | R86: Cashelgarren | T86: lsjncpsdjnc | U86: Sligo | V86: 166261 | W86: 346799 | X86: 54.368751 | Y86: -8.51983 | AA86: 166233 | AB86: 346777 | AC86: 54.368544 | AD86: -8.520264 | AE86: From Sligo, drive along N15 towards Bundoran. After travelling 18km, turn right just after Henry's Bar and Restaurant. (note: old Shell station on left side of the road at this turn). Travel 900m along this road to site entrance on the right hand side. | AF86: Locken ekeys required for this site. | AG86: 0 | AH86: 0 | AJ86: 1 | AL86: Access hatch is small 670mm x 430mm with ladder. Climber certified access only. MEWP required for some works | AM86: 1 | AN86: 1 | AO86: Eircom | AP86: Pallisade | AQ86: 3
A87: TKY7013 | B87: 105 | C87: TKY7013 | D87: Castleisland | F87: Active | H87: NO | I87: TKY5060 | J87: 36 | K87: Level 2 | L87: EED | M87: Full SRF | N87: Full SAF | P87: 0 | Q87: 1 | R87: Castleisland | T87: lsjncpsdjnc | U87: Kerry | V87: 99918 | W87: 109635 | X87: 52.22984 | Y87: -9.46549 | Z87: Tarmac | AA87: 99899 | AB87: 109662 | AC87: 52.23008 | AD87: -9.46577 | AE87: Travelling from Tralee take the N21 for 15.1km,then take slight left at market cross,then take right onto Killarney Rd(N23),site located on left after 69m | AF87: OPW main gate lock | AG87: 0 | AH87: 0 | AJ87: 1 | AM87: 0 | AN87: 0
A88: TMO2010 | B88: 106 | C88: TMO2010 | D88: Castlebar | F88: Active | H88: NO | J88: 41 | K88: Level 4 | L88: 108 | M88: Full SRF | N88: Full SAF | P88: 0 | Q88: 1 | R88: Castlebar | T88: lsjncpsdjnc | U88: Mayo | V88: 114744 | W88: 290074 | X88: 53.853255 | Y88: -9.29629 | AA88: 114677 | AB88: 289992 | AC88: 53.85251 | AD88: -9.29729 | AE88: From Dublin, drive along the N4 and onto the N5 at Longford to Castlebar. In Castlebar take the 2nd exit at first roundabout. At next roundabout take 3rd exit for Town Centre. Follow the road around a left turn. Turn left when yellow B&B is directly ahead. Continue along this road to Castlebar Exchange on the left hand side. | AF88: ISEO Locken electronic key required for access. | AG88: 1 | AH88: 0 | AJ88: 1 | AM88: 1 | AN88: 1 | AO88: Eircom | AP88: Pallisade | AQ88: 3
A89: TLH5055 | B89: 107 | C89: TLH5055 | D89: Castlebellingham | F89: Active | H89: NO | J89: 18 | K89: Level 2 | L89: EED | M89: Full SRF | N89: Full SAF | P89: 0 | Q89: 1 | R89: Castlebellingham | T89: lsjncpsdjnc | U89: Louth | V89: 305890 | W89: 295607 | X89: 53.89917 | Y89: -6.38985 | Z89: Tarmac | AA89: 305896 | AB89: 295611 | AC89: 53.8992 | AD89: -6.38975 | AE89: Travelling toward dundalk on M1 take exit at junction 15 to castlebellingham,in 350m turn right at R166 and after 2.2km turn left at Dundalk road and in 110m site located on left. | AG89: 0 | AH89: 0 | AJ89: 1 | AM89: 0 | AN89: 1 | AO89: Garda
A90: TMN7011 | B90: 108 | C90: TMN7011 | D90: Castleblaney | F90: To be Retired | H90: NO | I90: TMN5056 | J90: 122 | K90: Level 2 | L90: EED | M90: Full SRF | N90: Full SAF | P90: 0 | Q90: 1 | R90: Old Railway Rd, Castlblaney | T90: lsjncpsdjnc | U90: Monaghan | V90: 282452 | W90: 319647 | X90: 54.11934 | Y90: -6.73979 | Z90: Tarmac | AA90: 282460 | AB90: 319677 | AC90: 54.11961 | AD90: -6.73967 | AE90: Take N2 to Castleblaney, take R181 exit into Castleblaney. Follow road for 1.3km and take right turn onto Old Railway Rd. Site is located 50m ffurther down road on R.H.S. Directly opposite Supervalu. | AF90: 1 x eircom padlock on main gate. ENSUP also required for rooftop access | AG90: 1 | AH90: 0 | AJ90: 1 | AM90: 0 | AN90: 1 | AO90: Eircom compound and supervalu car park | AQ90: 1.2
A91: TKK5057 | B91: 109 | C91: TKK5057 | D91: Castlecomer | F91: Active | H91: NO | J91: 158 | K91: Level 2 | L91: EED | M91: Full SRF | N91: Full SAF | P91: 0 | Q91: 1 | R91: Castlecomer | T91: lsjncpsdjnc | U91: Kilkenny | V91: 252987 | W91: 172875 | X91: 52.80462 | Y91: -7.21506 | Z91: Tarmac | AA91: 252980 | AB91: 172925 | AC91: 52.80507 | AD91: -7.21516 | AE91: From Kilkenny take N77 heading for Ballyragget, after 3.4km take right turn onto N78. Follow for 12km into Castlecomer. In Castlecomer take left turn onto R694 Barrack St" follow for 210m and keep left at Y-junction onto "Barrack Hill, follow road uphill for approx 100m. Take left turn into driveway, turn is lcoated imediately after "Slow Scholl Ahead" sign printed into road | AF91: 1 x padlock on main gate | AG91: 0 | AH91: 0 | AJ91: 0 | AM91: 0 | AN91: 1 | AO91: Eircom compound and OPW land | AP91: Pallisade | AQ91: 2.4
A92: TLK5058 | B92: 110 | C92: TLK5058 | D92: Castleconnell | F92: Active | H92: NO | J92: 35 | K92: Level 4 | L92: EED | M92: Full SRF | N92: Full SAF | P92: 1 | Q92: 1 | R92: Castleconnell | T92: lsjncpsdjnc | U92: Limerick | V92: 166345 | W92: 162573 | X92: 52.7136 | Y92: -8.49872 | Z92: Tarmac | AA92: 166371 | AB92: 162539 | AC92: 52.7133 | AD92: -8.49833 | AE92: Travelling from nenagh on N1,take exit onto R494,at first roundabout take 2nd exit,at 2nd roundabout take 1st exit,after 5.3km continue straight onto dublin rd,turn right R525 and after 1st left onto railway rd, site located on left. | AF92: Access through gate on left hand side. LOCKEN ISEO key required for access. | AG92: 0 | AH92: 0 | AJ92: 1 | AM92: 0 | AN92: 0
A93: TKE7012 | B93: 111 | C93: TKE7012 | D93: Castledermot | F93: Active | H93: NO | I93: TKE5059 | J93: 89 | K93: Level 2 | L93: EED | M93: Full SRF | N93: Full SAF | P93: 0 | Q93: 1 | R93: Main St, Castledermot | T93: lsjncpsdjnc | U93: Kildare | V93: 278294 | W93: 185325 | X93: 52.9134 | Y93: -6.83691 | Z93: Tarmac | AA93: 278271 | AB93: 185351 | AC93: 52.91363 | AD93: -6.83724 | AE93: From Dublin take M7 to Limerick. After Naas exits prepare to take M9 turnoff for Kilkenny. After approx 35km take exit for Casteldermot. Follow N9 into Castledermot and straight onto Main St. Go straight through crossroads, ignore R418 to Athy and continue on main st for 150m more. Site will be on R.H.S. beside Bus Eireann bus stop and the Dales Lounge Pub"" | AG93: 0 | AH93: 0 | AJ93: 1 | AM93: 0 | AN93: 1 | AO93: House with garden to one side, pub on other side | AP93: Stone Wall | AQ93: 1.5
A94: TRN5062 | B94: 113 | C94: TRN5062 | D94: Castlerea | F94: Active | H94: NO | J94: 73 | K94: Level 4 | L94: EED | M94: Full SRF | N94: Full SAF | P94: 1 | Q94: 1 | R94: Castlerea | T94: lsjncpsdjnc | U94: Roscommon | V94: 168657 | W94: 279667 | X94: 53.76581 | Y94: -8.47603 | Z94: Tarmac | AA94: 168608 | AB94: 279698 | AC94: 53.76609 | AD94: -8.47677 | AE94: Travelling from ballyhaunis on N60 toward cashel park,continue straight onto square,after 56m continue onto barrack st,after 250m turn left at henry byrne rd and after 550m site located on the right. | AF94: Main gate with lock. Barrier lock. Elock installed | AG94: 0 | AH94: 0 | AJ94: 1 | AM94: 0 | AN94: 0
A95: TCK2011 | B95: 114 | C95: TCK2011 | D95: Castletownbere | E95: Castletownbere Exchange | F95: Active | H95: NO | J95: 5 | K95: Level 1 | L95: 108 | M95: Full SRF | N95: Full SAF | P95: 1 | Q95: 1 | R95: Dinish Island, Castletownbere | T95: lsjncpsdjnc | U95: Cork | V95: 68602 | W95: 45829 | X95: 51.650147 | Y95: -9.89922 | AA95: 68630 | AB95: 45807 | AC95: 51.649958 | AD95: -9.898805 | AE95: Travelling along the R572, turn left into Dinish Island before Castletownbere. Site is located on the right hand site, directly off the main road. | AF95: ISEO locken ekey required for access | AG95: 0 | AH95: 0 | AJ95: 0 | AM95: 1 | AN95: 1 | AO95: Eircom | AP95: Pallisade | AQ95: 2.4
A96: TCN5063 | B96: 115 | C96: TCN5063 | D96: Cavan | E96: Cavan town | F96: To be Retired | H96: NO | J96: 75 | K96: Level 3 | L96: EED | M96: Full SRF | N96: Full SAF | P96: 1 | Q96: 1 | R96: Main Street | T96: lsjncpsdjnc | U96: Cavan | V96: 241869 | W96: 304686 | X96: 53.98984 | Y96: -7.36244 | Z96: Tarmac | AA96: 241890 | AB96: 304680 | AC96: 53.98978 | AD96: -7.36211 | AE96: Travelling into cavan head west onto dublin road toward meadow park,after 1.9km continue onto college street, in 280m at roundabout take 2nd exit onto farham street, and in 97m turn right at abbey street and site located on right in 110m. | AF96: Main gate with Ensup to open | AG96: 1 | AH96: 0 | AJ96: 1 | AM96: 0 | AN96: 1 | AO96: Town houses
A97: TKE6435 | B97: 116 | C97: TKE6435 | D97: Celbridge | F97: Active | H97: NO | I97: TKE6035 | J97: 63 | K97: Level 4 | L97: TC68 | M97: Full SRF | N97: Full SAF | P97: 1 | Q97: 1 | R97: Eircom exchange, Whitethorn Grove, Celbridge | T97: lsjncpsdjnc | U97: Kildare | V97: 296968 | W97: 233708 | X97: 53.34495 | Y97: -6.5448 | Z97: Tarmac | AA97: 296987 | AB97: 233716 | AC97: 53.34502 | AD97: -6.5445 | AE97: Traveling on M1 take exit 2A, at the roundabout take 4th exit onto R405,after 1.5km, next roundabout take 1st exit onto R405, turn right at Willowbrook rd,100m take 1st right after 100m on Whitethorn grove and site located 54m on left. | AF97: Ensup required for main gate | AG97: 1 | AH97: 0 | AJ97: 1 | AM97: 0 | AN97: 0
A98: TKE5065 | B98: 117 | C98: TKE5065 | D98: Celbridge | F98: Active | H98: NO | J98: 64 | K98: Premium | L98: EED | M98: Full SRF | N98: Full SAF | P98: 1 | Q98: 1 | R98: Eircom Exchange, Whitethorn Grove, Celbridge | T98: lsjncpsdjnc | U98: Kildare | V98: 296968 | W98: 233708 | X98: 53.34495 | Y98: -6.5448 | Z98: Tarmac | AA98: 296987 | AB98: 233716 | AC98: 53.34502 | AD98: -6.5445 | AE98: Travelling on M1 take exit 2A,at the roundabout take 4th exit onto R405,after 1.5km, next roundabout take 1st exit onto R405, turn right at willowbrook rd,100m take 1st right after 100m on whitethorn grove and site located 54m on left. | AF98: Ensup required for main gate. Elock installed on compound | AG98: 1 | AH98: 0 | AI98: Yes | AJ98: 1 | AM98: 0 | AN98: 1 | AO98: Eircom | AP98: Pallisade | AQ98: 2.8
A99: TCK2012 | B99: 118 | C99: TCK2012 | D99: Churchfield | F99: Active | H99: NO | J99: 117 | K99: Level 4 | L99: 108 | M99: Full SRF | N99: Full SAF | P99: 0 | Q99: 1 | R99: Mount Agnes Road, Churchfield | T99: lsjncpsdjnc | U99: Cork | V99: 166300 | W99: 73444 | X99: 51.912663 | Y99: -8.490449 | AA99: 166394 | AB99: 73400 | AC99: 51.912273 | AD99: -8.489076 | AE99: From M8, take R639 towards Churchfield. Travel 4.5km then turn right onto R616. Follow for 9km, then turn left onto Thomas Davis Street. After 1km, turn right onto Fairfield Avenue. Follow for 1km to roundabout. Straight throught roundabout, tower is located 90m on right. | AF99: Tenant card required for main gate, however it is always open. ISEO Locken ekey required access. | AG99: 1 | AH99: 0 | AJ99: 1 | AM99: 1 | AN99: 1 | AO99: Eircom | AP99: Pallisade | AQ99: 2.4
A100: TDU4004 | B100: 119 | C100: TDU4004 | D100: City West | F100: Active | H100: NO | J100: 103 | K100: Level 4 | L100: 108 | M100: Full SRF | N100: Full SAF | P100: 0 | Q100: 1 | R100: City West | T100: lsjncpsdjnc | U100: Dublin | V100: 304654 | W100: 227998 | X100: 53.292208 | Y100: -6.431305 | AA100: 304585 | AB100: 227875 | AC100: 53.291114 | AD100: -6.432388 | AE100: Take City West turn off N7. After roundabout go to City West Rd, follow for 100m and take right turn onto Bianconi road. Follow for 350m and site entrance will be on right hand side. | AF100: Manual Towercom E-lock installed on Anticlimb. 3m portable ladder required to access climbing ladder. | AG100: 1 | AH100: 0 | AJ100: 1 | AM100: 0 | AN100: 1 | AO100: Eircom | AP100: None
...

Sheet INFRASTRUCTURE TEST DATA
A2: Site | B2: Infrastructure Type | C2: Infrastructure ID | D2: Legacy ID | E2: Schedule | F2: Status | G2: Infrastructure Ownership | H2: O&M Ownership | I2: Insurance Ownership | J2: Marketing Status | K2: SRF Status | L2: SAF Status | M2: Public | N2: Comments | O2: Structure Type | P2: Tower Family | Q2: Structure Height (m) | R2: Future Planned Structure Height (m) | S2: Rooftop Height (m) | T2: SAF Auto Approve | U2: Fall Arrest Status | V2: Fall Arrest Type | W2: Anti Climb | X2: Easting | Y2: Northing | Z2: Longitude | AA2: Latitude | AB2: Next Site Inspection Date | AC2: Next Fall Arrest Certification Date | AD2: Tower Last Painted Date | AE2: Scheduled Next Painting Date | AF2: Painting Warranty Expiry Date | AG2: Structure Design | AH2: Year of Build | AI2: Geotype | AJ2: Proximity to Body of Water (km) | AK2: Land Topology | AL2: Wind Map Vb,map (m/s) | AM2: Foundation Type | AN2: Foundation Design | AO2: Foundation Dimensions | AP2: Foundation Contractor | AQ2: Soil Bearing DCP/SI (kN/m) | AR2: Ground Water (BGL) | AS2: Foundation FOS | AT2: Foundation Overturning (kN/m) | AU2: Structure Capacity Σ ESA_(m²) | AV2: Structure Capacity Σ E-BM_(m².m) | AW2: Structure Equipment loading Σ E-BM_(m².m) | AX2: % Capacity used | AY2: % Capacity remaining | AZ2: TLM | BA2: Accomodation Type | BB2: Accommodation Dimensions | BC2: Rack Spaces Available | BD2: Units | BE2: Model | BF2: Installed | BG2: AC Feed Phase | BH2: Loadings | BI2: Noise Level | BJ2: Next Aircon Service | BK2: Intruder Alarm Present | BL2: Intruder Code | BM2: Fire Alarm Present | BN2: Next Fire Service | BO2: Next Alarm Service | BP2: Generator Model | BQ2: Power Capacity | BR2: Tank Capacity (l) | BS2: Next Generator Service | BT2: Next Generator Service Type | BU2: Fibre Infrastructure Status | BV2: Fibre Duct Installed | BW2: Fibre Infrastructure Type | BX2: Fibre Service Providers | BY2: Fibre Priority | BZ2: Fibre Phase | CA2: Fibre Partner Priority | CB2: Fibre Comments
A3: TLK5001 | B3: Structure | C3: TLK5001-T01 | E3: MLA | F3: To be Retired | G3: Vodafone | H3: Towercom | I3: Vodafone | J3: 0 | K3: Remove Only | L3: Full SAF | M3: 1 | O3: Lattice Tower | P3: Eve Type 6 | Q3: 12 | T3: 0 | U3: 0 | W3: 0 | X3: 111282 | Y3: 126159 | Z3: 52.38024 | AA3: -9.30358 | AB3: 45585.958 | AG3: DEL-6 A-E | AH3: 1993-1996 | AI3: Country | AJ3: 23 | AK3: Flat | AL3: 26.5 | AM3: Pile | AN3: Concrete Grade: Main Rebar: Corner/Secondary Rebar: Concrete Quantity (m3): Reinforcement Quantity (kg): | AO3: 0 | AP3: Obelisk | AQ3: 0 | AR3: 0 | AS3: 21 | AT3: 0 | AU3: 1.932 | AV3: 200.1 | AW3: 232 | AX3: 0 | AY3: 1 | AZ3: 0
A4: TLK5001 | B4: Structure | C4: TLK5001-T02 | D4: TLK7301 | E4: Option A (EED) | F4: Active | G4: Eircom | H4: Towercom | I4: Eircom | J4: 1 | K4: Full SRF | L4: Full SAF | M4: 1 | O4: Lattice Tower | P4: V6X | Q4: 20 | T4: 0 | U4: 0 | W4: 0 | X4: 111282 | Y4: 126159 | Z4: 52.38024 | AA4: -9.30358 | AB4: 45585.958 | AG4: FL87 | AH4: 2022 | AI4: Country | AJ4: 24 | AK4: Flat | AL4: 26.5 | AM4: Pad | AN4: Concrete Grade: Main Rebar: Corner/Secondary Rebar: Concrete Quantity (m3): Reinforcement Quantity (kg): | AO4: 6.6 x 6.6 x 1.25 | AP4: KTL | AQ4: 0 | AR4: 0 | AS4: 393 | AT4: 0 | AU4: 23.93 | AV4: 10.22 | AW4: 10.22 | AX4: 0.65 | AY4: 0.35 | AZ4: Green
A5: TCK5002 | B5: Structure | C5: TCK5002-T01 | E5: MLA | F5: Retired | G5: Vodafone | H5: Towercom | I5: Vodafone | J5: 0 | K5: No SRF | L5: TL Only | M5: 0 | T5: 0 | U5: 1 | V5: Latchway | W5: 1 | X5: 150500 | Y5: 67057 | Z5: 51.85409 | AA5: -8.71912 | AB5: 46589.958 | AC5: 46224 | AG5: DEL-6 A-E | AH5: #N/A | AI5: #N/A | AJ5: 25 | AK5: #N/A | AL5: #N/A | AM5: Slab | AN5: Concrete Grade: Main Rebar: Corner/Secondary Rebar: Concrete Quantity (m3): Reinforcement Quantity (kg): | AO5: #N/A | AP5: Obelisk | AQ5: #N/A | AR5: #N/A | AS5: 12 | AT5: #N/A | AU5: 100.23 | AV5: 90.5 | AW5: 90.5 | AX5: #N/A | AY5: #N/A | AZ5: #N/A
A6: TCK5002 | B6: Structure | C6: TCK5002-T02 | E6: MLA | F6: Active | G6: Vodafone | H6: Towercom | I6: Vodafone | J6: 1 | K6: Full SRF | L6: Full SAF | M6: 1 | T6: 1 | U6: 1 | V6: Latchway | W6: 1 | X6: 150500 | Y6: 67057 | Z6: 51.85409 | AA6: -8.71912 | AB6: 46589.958 | AC6: 46224 | AG6: FL88 | AH6: #N/A | AI6: #N/A | AJ6: 26 | AK6: #N/A | AL6: #N/A | AM6: Pile | AN6: Concrete Grade: Main Rebar: Corner/Secondary Rebar: Concrete Quantity (m3): Reinforcement Quantity (kg): | AO6: #N/A | AP6: KTL | AQ6: #N/A | AR6: #N/A | AS6: 133 | AT6: #N/A | AU6: 140.32867 | AV6: -9.3266667 | AW6: -9.3266667 | AX6: #N/A | AY6: #N/A | AZ6: #N/A
A7: TKY6028 | B7: Structure | C7: TKY6028-T01 | E7: Schedule 3f | F7: Active | G7: Towercom | H7: Towercom | I7: Towercom | J7: 1 | K7: Full SRF | L7: Full SAF | M7: 1 | O7: Monopole | P7: Type - 25m - 03 | Q7: 25 | T7: 1 | U7: 1 | V7: Metreel | W7: 1 | X7: 102505 | Y7: 96387 | Z7: 52.11128 | AA7: -9.42384 | AB7: 46126.958 | AG7: DEL-6 A-E | AH7: 2008-2010 | AI7: country | AJ7: 27 | AK7: flat | AL7: 26.5 | AM7: Pad | AN7: Concrete Grade: Main Rebar: Corner/Secondary Rebar: Concrete Quantity (m3): Reinforcement Quantity (kg): | AO7: 5.3 x 5.3 x 1.0 | AP7: Obelisk | AQ7: 0 | AR7: 0 | AS7: 128.5 | AT7: 0 | AU7: 189.47767 | AV7: -64.126667 | AW7: 10.917778 | AX7: 0.45 | AY7: 0.55 | AZ7: green
A8: TGY5003 | B8: Structure | C8: TGY5003-T01 | E8: MLA | F8: Active | G8: Vodafone | H8: Towercom | I8: Vodafone | J8: 1 | K8: Full SRF | L8: Full SAF | M8: 1 | O8: Lattice Tower | P8: Eve Type 6 | Q8: 15 | T8: 1 | U8: 0 | W8: 1 | X8: 146050 | Y8: 212030 | Z8: 53.15632 | AA8: -8.80721 | AB8: 46369 | AG8: FL89 | AH8: 1993-1996 | AI8: Country | AJ8: 28 | AK8: Flat | AL8: 26.5 | AM8: Slab | AN8: Concrete Grade: Main Rebar: Corner/Secondary Rebar: Concrete Quantity (m3): Reinforcement Quantity (kg): | AO8: 3.55 x 3.55 | AP8: KTL | AQ8: 0 | AR8: 0 | AS8: 124 | AT8: 549 | AU8: 238.62667 | AV8: -118.92667 | AW8: 1.1444444 | AX8: 0.94998624 | AY8: 0.050013761 | AZ8: Amber
A9: TGY5003 | B9: Structure | C9: TGY5003-T02 | D9: TGY7302 | E9: Option A (EED) | F9: Option | G9: Eircom | H9: Towercom | I9: Eircom | J9: 1 | K9: Full SRF | L9: Full SAF | M9: 1 | P9: No Structure | Q9: 0 | T9: 0 | U9: 0 | W9: 1 | X9: 146050 | Y9: 212030 | Z9: 53.15632 | AA9: -8.80721 | AB9: 46369 | AG9: DEL-6 A-E | AH9: N/A | AI9: Country | AJ9: 29 | AK9: Flat | AL9: 26.5 | AM9: Pile | AN9: Concrete Grade: Main Rebar: Corner/Secondary Rebar: Concrete Quantity (m3): Reinforcement Quantity (kg): | AO9: 0 | AP9: Obelisk | AQ9: 0 | AR9: 0 | AS9: 119.5 | AT9: 0 | AU9: 287.77567 | AV9: -173.72667 | AW9: -8.6288889 | AX9: 0 | AY9: 1 | AZ9: 0
A10: TWW3001 | B10: Structure | C10: TWW3001-T01 | E10: Schedule 3a | F10: Active | G10: Towercom | H10: Towercom | I10: Towercom | J10: 1 | K10: Full SRF | L10: Full SAF | M10: 1 | O10: Lattice Tower | P10: Type - JCM - 4 | Q10: 12 | T10: 1 | U10: 0 | W10: 1 | X10: 324473 | Y10: 173563 | Z10: 52.799062 | AA10: -6.155261 | AB10: 46595.958 | AC10: 46224 | AG10: FL90 | AH10: 0 | AI10: town | AJ10: 30 | AK10: flat | AL10: 25 | AM10: Pad | AN10: Concrete Grade: Main Rebar: Corner/Secondary Rebar: Concrete Quantity (m3): Reinforcement Quantity (kg): | AO10: 0 | AP10: KTL | AQ10: 0 | AR10: 0 | AS10: 115 | AT10: 0 | AU10: 336.92467 | AV10: -228.52667 | AW10: -18.402222 | AX10: 0.86 | AY10: 0.14 | AZ10: Amber
A11: TWW5005 | B11: Structure | C11: TWW5005-R01 | E11: MLA | F11: Active | G11: Vodafone | H11: Towercom | I11: Vodafone | J11: 1 | K11: Full SRF | L11: Full SAF | M11: 1 | O11: Rooftop | P11: Ballast & Pole Mount | Q11: 15.4 | S11: 10 | T11: 1 | U11: 0 | W11: 0 | X11: 324456 | Y11: 173522 | Z11: 52.7987 | AA11: -6.15554 | AB11: 46345 | AG11: DEL-6 A-E | AH11: N/A | AI11: town | AJ11: 31 | AK11: flat | AL11: 25 | AM11: Slab | AN11: Concrete Grade: Main Rebar: Corner/Secondary Rebar: Concrete Quantity (m3): Reinforcement Quantity (kg): | AO11: 0 | AP11: Obelisk | AQ11: 0 | AR11: 0 | AS11: 110.5 | AT11: 0 | AU11: 386.07367 | AV11: -283.32667 | AW11: -28.175556 | AX11: 0.9 | AY11: 0.1 | AZ11: Amber
A12: TWW5004 | B12: Structure | C12: TWW5004-T01 | E12: MLA | F12: Active | G12: Vodafone | H12: Towercom | I12: Vodafone | J12: 1 | K12: Full SRF | L12: Full SAF | M12: 1 | O12: Lattice Tower | P12: Eve Type 5 | Q12: 30 | T12: 0 | U12: 0 | W12: 1 | X12: 323288 | Y12: 172548 | Z12: 52.79022 | AA12: -6.17321 | AB12: 46190.958 | AG12: FL91 | AH12: 1993-1996 | AI12: Town | AJ12: 32 | AK12: flat | AL12: 25 | AM12: Pile | AN12: Concrete Grade: Main Rebar: Corner/Secondary Rebar: Concrete Quantity (m3): Reinforcement Quantity (kg): | AO12: 7.4m x 7.4m | AP12: KTL | AQ12: 0 | AR12: N/A | AS12: 106 | AT12: 0 | AU12: 435.22267 | AV12: -338.12667 | AW12: -37.948889 | AX12: 0.41 | AY12: 0.59 | AZ12: Green
A13: TDL2001 | B13: Structure | C13: TDL2001-T01 | E13: Schedule 2 | F13: Active | G13: Towercom | H13: Towercom | I13: Towercom | J13: 1 | K13: Full SRF | L13: Full SAF | M13: 1 | O13: Guyed Mast | P13: Type - P&T - 4 | Q13: 20 | T13: 0 | U13: 0 | W13: 0 | X13: 168195 | Y13: 415600 | Z13: 54.986888 | AA13: -8.49757 | AB13: 46197.958 | AG13: DEL-6 A-E | AH13: 0 | AI13: country | AJ13: 33 | AK13: hill | AL13: 27 | AM13: Pad | AN13: Concrete Grade: Main Rebar: Corner/Secondary Rebar: Concrete Quantity (m3): Reinforcement Quantity (kg): | AO13: 0 | AP13: Obelisk | AQ13: 0 | AR13: 0 | AS13: 101.5 | AT13: 0 | AU13: 484.37167 | AV13: -392.92667 | AW13: -47.722222 | AX13: 0.85 | AY13: 0.15 | AZ13: Amber
A14: TCN5006 | B14: Structure | C14: TCN5006-T01 | E14: MLA | F14: Retired | G14: Vodafone | H14: Towercom | I14: Vodafone | J14: 0 | K14: No SRF | L14: TL Only | M14: 0 | T14: 0 | U14: 1 | V14: Latchway | W14: 1 | X14: 227855 | Y14: 296831 | Z14: 53.92021 | AA14: -7.57679 | AB14: 46129.958 | AG14: FL92 | AH14: #N/A | AI14: #N/A | AJ14: 34 | AK14: #N/A | AL14: #N/A | AM14: Slab | AN14: Concrete Grade: Main Rebar: Corner/Secondary Rebar: Concrete Quantity (m3): Reinforcement Quantity (kg): | AO14: #N/A | AP14: KTL | AQ14: #N/A | AR14: #N/A | AS14: 97 | AT14: #N/A | AU14: 533.52067 | AV14: -447.72667 | AW14: -57.495556 | AX14: #N/A | AY14: #N/A | AZ14: #N/A
A15: TCN5006 | B15: Structure | C15: TCN5006-T02 | E15: MLA | F15: Active | G15: Vodafone | H15: Towercom | I15: Vodafone | J15: 1 | K15: Full SRF | L15: Full SAF | M15: 1 | O15: Lattice Tower | P15: V6X | Q15: 24 | T15: 0 | U15: 1 | V15: Latchway | W15: 1 | X15: 227855 | Y15: 296831 | Z15: 53.92021 | AA15: -7.57679 | AB15: 46129.958 | AG15: DEL-6 A-E | AH15: 2023 | AI15: Country | AJ15: 35 | AK15: Flat | AL15: 25.5 | AM15: Pile | AN15: Concrete Grade: Main Rebar: Corner/Secondary Rebar: Concrete Quantity (m3): Reinforcement Quantity (kg): | AO15: 6.6 x 6.6 x 1.25 | AP15: Obelisk | AQ15: 0 | AR15: 0 | AS15: 92.5 | AT15: 0 | AU15: 582.66967 | AV15: -502.52667 | AW15: -67.268889 | AX15: 0.65 | AY15: 0.35 | AZ15: Green
A16: TMH6457 | B16: Structure | C16: TMH6457-T01 | D16: TMH6057 | E16: Schedule 3b | F16: UTS | G16: Towercom | H16: Towercom | I16: Towercom | J16: 1 | K16: Full SRF | L16: Full SAF | M16: 1 | T16: 0 | U16: 0 | W16: 0 | X16: 271766 | Y16: 264326 | Z16: 53.62401 | AA16: -6.91612 | AB16: 46540.958 | AG16: FL93 | AH16: #N/A | AI16: #N/A | AJ16: 36 | AK16: #N/A | AL16: #N/A | AM16: Pad | AN16: Concrete Grade: Main Rebar: Corner/Secondary Rebar: Concrete Quantity (m3): Reinforcement Quantity (kg): | AO16: #N/A | AP16: KTL | AQ16: #N/A | AR16: #N/A | AS16: 88 | AT16: #N/A | AU16: 631.81867 | AV16: -557.32667 | AW16: -77.042222 | AX16: #N/A | AY16: #N/A | AZ16: #N/A
A17: TLK5007 | B17: Structure | C17: TLK5007-T01 | E17: MLA | F17: Active | G17: Vodafone | H17: Towercom | I17: Vodafone | J17: 1 | K17: Full SRF | L17: Full SAF | M17: 1 | T17: 0 | U17: 0 | W17: 0 | X17: 112555 | Y17: 134994 | Z17: 52.45982 | AA17: -9.2872 | AB17: 46532.958 | AG17: DEL-6 A-E | AH17: #N/A | AI17: #N/A | AJ17: 37 | AK17: #N/A | AL17: #N/A | AM17: Slab | AN17: Concrete Grade: Main Rebar: Corner/Secondary Rebar: Concrete Quantity (m3): Reinforcement Quantity (kg): | AO17: #N/A | AP17: Obelisk | AQ17: #N/A | AR17: #N/A | AS17: 83.5 | AT17: #N/A | AU17: 680.96767 | AV17: -612.12667 | AW17: -86.815556 | AX17: #N/A | AY17: #N/A | AZ17: #N/A
A18: TLK5007 | B18: Structure | C18: TLK5007-T02 | D18: TLK7303 | E18: Option A (EED) | F18: Option | G18: Eircom | H18: Towercom | I18: Eircom | J18: 1 | K18: Full SRF | L18: Full SAF | M18: 1 | T18: 0 | U18: 0 | W18: 0 | X18: 112555 | Y18: 134994 | Z18: 52.45982 | AA18: -9.2872 | AB18: 46532.958 | AG18: FL94 | AH18: #N/A | AI18: #N/A | AJ18: 38 | AK18: #N/A | AL18: #N/A | AM18: Pile | AN18: Concrete Grade: Main Rebar: Corner/Secondary Rebar: Concrete Quantity (m3): Reinforcement Quantity (kg): | AO18: #N/A | AP18: KTL | AQ18: #N/A | AR18: #N/A | AS18: 79 | AT18: #N/A | AU18: 730.11667 | AV18: -666.92667 | AW18: -96.588889 | AX18: #N/A | AY18: #N/A | AZ18: #N/A
A19: TGY5008 | B19: Structure | C19: TGY5008-T01 | E19: MLA | F19: Retired | G19: Vodafone | H19: Towercom | I19: Vodafone | J19: 0 | K19: No SRF | L19: TL Only | M19: 0 | T19: 0 | U19: 1 | V19: Metreel | W19: 1 | X19: 150227 | Y19: 227784 | Z19: 53.29826 | AA19: -8.74724 | AB19: 46477.958 | AG19: DEL-6 A-E | AH19: #N/A | AI19: #N/A | AJ19: 39 | AK19: #N/A | AL19: #N/A | AM19: Pad | AN19: Concrete Grade: Main Rebar: Corner/Secondary Rebar: Concrete Quantity (m3): Reinforcement Quantity (kg): | AO19: #N/A | AP19: Obelisk | AQ19: #N/A | AR19: #N/A | AS19: 74.5 | AT19: #N/A | AU19: 779.26567 | AV19: -721.72667 | AW19: -106.36222 | AX19: #N/A | AY19: #N/A | AZ19: #N/A
A20: TGY5008 | B20: Structure | C20: TGY5008-T02 | E20: MLA | F20: Active | G20: Vodafone | H20: Towercom | I20: Vodafone | J20: 1 | K20: Full SRF | L20: Full SAF | M20: 1 | T20: 0 | U20: 1 | V20: Metreel | W20: 1 | X20: 150227 | Y20: 227784 | Z20: 53.29826 | AA20: -8.74724 | AB20: 46477.958 | AG20: FL95 | AH20: #N/A | AI20: #N/A | AJ20: 40 | AK20: #N/A | AL20: #N/A | AM20: Slab | AN20: Concrete Grade: Main Rebar: Corner/Secondary Rebar: Concrete Quantity (m3): Reinforcement Quantity (kg): | AO20: #N/A | AP20: KTL | AQ20: #N/A | AR20: #N/A | AS20: 70 | AT20: #N/A | AU20: 828.41467 | AV20: -776.52667 | AW20: -116.13556 | AX20: #N/A | AY20: #N/A | AZ20: #N/A
A21: TWH4001 | B21: Structure | C21: TWH4001-T01 | E21: Schedule 3b | F21: Active | G21: Towercom | H21: Towercom | I21: Towercom | J21: 1 | K21: Full SRF | L21: Full SAF | M21: 1 | O21: Lattice Tower | P21: Type - JCM - 6 | Q21: 37 | T21: 0 | U21: 0 | W21: 0 | X21: 203705 | Y21: 241477 | Z21: 53.423629 | AA21: -7.945005 | AB21: 46038 | AD21: 45505.958 | AF21: 49157.958 | AG21: DEL-6 A-E | AH21: 0 | AI21: town | AJ21: 41 | AK21: flat | AL21: 25.5 | AM21: Pile | AN21: Concrete Grade: Main Rebar: Corner/Secondary Rebar: Concrete Quantity (m3): Reinforcement Quantity (kg): | AO21: Strengthening works 2024 | AP21: Obelisk | AQ21: 0 | AR21: 0 | AS21: 65.5 | AT21: 0 | AU21: 877.56367 | AV21: -831.32667 | AW21: -125.90889 | AX21: 0.85 | AY21: 0.15 | AZ21: Amber
A22: TLK5009 | B22: Structure | C22: TLK5009-T01 | E22: MLA | F22: Active | G22: Vodafone | H22: Towercom | I22: Vodafone | J22: 1 | K22: Full SRF | L22: Full SAF | M22: 1 | O22: Lattice Tower | P22: Eve Type 5 | Q22: 20 | T22: 1 | U22: 1 | V22: Latchway | W22: 1 | X22: 159171 | Y22: 159411 | Z22: 52.6847 | AA22: -8.60446 | AB22: 46651.958 | AG22: FL96 | AH22: 1993-1996 | AI22: Country | AJ22: 42 | AK22: Flat | AL22: 26 | AM22: Pad | AN22: Concrete Grade: Main Rebar: Corner/Secondary Rebar: Concrete Quantity (m3): Reinforcement Quantity (kg): | AO22: 7.1m x 7.1m | AP22: KTL | AQ22: 0 | AR22: Headframe | AS22: 61 | AT22: 0 | AU22: 926.71267 | AV22: -886.12667 | AW22: -135.68222 | AX22: 0.45 | AY22: 0.55 | AZ22: Green
A23: TGY6318 | B23: Structure | C23: TGY6318-T01 | D23: TGY6018 | E23: Schedule 3a | F23: Active | G23: Towercom | H23: Towercom | I23: Towercom | J23: 1 | K23: Full SRF | L23: Full SAF | M23: 1 | T23: 0 | U23: 0 | W23: 0 | X23: 178899 | Y23: 228106 | Z23: 53.30307 | AA23: -8.31724 | AB23: 45791.958 | AG23: DEL-6 A-E | AH23: #N/A | AI23: #N/A | AJ23: 43 | AK23: #N/A | AL23: #N/A | AM23: Slab | AN23: Concrete Grade: Main Rebar: Corner/Secondary Rebar: Concrete Quantity (m3): Reinforcement Quantity (kg): | AO23: #N/A | AP23: Obelisk | AQ23: #N/A | AR23: #N/A | AS23: 56.5 | AT23: #N/A | AU23: 975.86167 | AV23: -940.92667 | AW23: -145.45556 | AX23: #N/A | AY23: #N/A | AZ23: #N/A
A24: TGY5010 | B24: Structure | C24: TGY5010-T01 | E24: MLA | F24: UTS | G24: Vodafone | H24: Towercom | I24: Vodafone | J24: 1 | K24: Full SRF | L24: Full SAF | M24: 1 | O24: Wooden Pole | P24: Wooden Pole | Q24: 12 | T24: 0 | U24: 0 | W24: 0 | X24: 178899 | Y24: 228099 | Z24: 53.30301 | AA24: -8.31725 | AB24: 45820.958 | AG24: FL97 | AH24: 1990-2001 | AI24: Country | AJ24: 44 | AK24: Flat | AL24: 25.5 | AM24: Pile | AN24: Concrete Grade: Main Rebar: Corner/Secondary Rebar: Concrete Quantity (m3): Reinforcement Quantity (kg): | AO24: 0 | AP24: KTL | AQ24: 0 | AR24: 0 | AS24: 52 | AT24: 0 | AU24: 1025.0107 | AV24: -995.72667 | AW24: -155.22889 | AX24: 0.95 | AY24: 0.05 | AZ24: Blue
A25: TMO6047 | B25: Structure | C25: TMO6047-T01 | E25: Schedule 3f | F25: Active | G25: Towercom | H25: Towercom | I25: Towercom | J25: 1 | K25: Full SRF | L25: Full SAF | M25: 1 | O25: Monopole | P25: Del_3 - 15 | Q25: 15 | T25: 1 | U25: 1 | V25: Metreel | W25: 1 | X25: 107088 | Y25: 281651 | Z25: 53.77629 | AA25: -9.41005 | AB25: 46457 | AG25: DEL-6 A-E | AH25: 2008-2010 | AI25: country | AJ25: 45 | AK25: flat | AL25: 26.5 | AM25: Pad | AN25: Concrete Grade: Main Rebar: Corner/Secondary Rebar: Concrete Quantity (m3): Reinforcement Quantity (kg): | AO25: 3.5 x 3.5 x 1.25 | AP25: Obelisk | AQ25: 0 | AR25: 0 | AS25: 47.5 | AT25: 0 | AU25: 1074.1597 | AV25: -1050.5267 | AW25: -165.00222 | AX25: 0.45 | AY25: 0.55 | AZ25: green
A26: TDU7001 | B26: Structure | C26: TDU7001-T01 | D26: TDU5011 | E26: Non MLA | F26: UTS | G26: Vodafone | H26: Towercom | I26: Vodafone | J26: 1 | K26: Full SRF | L26: Full SAF | M26: 1 | T26: 1 | U26: 0 | W26: 1 | X26: 319949 | Y26: 263990 | Z26: 53.61219 | AA26: -6.18836 | AB26: 46247.958 | AG26: FL98 | AH26: #N/A | AI26: #N/A | AJ26: 46 | AK26: #N/A | AL26: #N/A | AM26: Slab | AN26: Concrete Grade: Main Rebar: Corner/Secondary Rebar: Concrete Quantity (m3): Reinforcement Quantity (kg): | AO26: #N/A | AP26: KTL | AQ26: #N/A | AR26: #N/A | AS26: 43 | AT26: #N/A | AU26: 1123.3087 | AV26: -1105.3267 | AW26: -174.77556 | AX26: #N/A | AY26: #N/A | AZ26: #N/A
A27: TMO5012 | B27: Structure | C27: TMO5012-T01 | E27: MLA | F27: Retired | G27: Vodafone | H27: Towercom | I27: Vodafone | J27: 0 | K27: No SRF | L27: TL Only | M27: 0 | T27: 0 | U27: 1 | V27: Metreel | W27: 1 | X27: 125654 | Y27: 284185 | Z27: 53.80204 | AA27: -9.12912 | AB27: 46620.958 | AG27: DEL-6 A-E | AH27: #N/A | AI27: #N/A | AJ27: 47 | AK27: #N/A | AL27: #N/A | AM27: Pile | AN27: Concrete Grade: Main Rebar: Corner/Secondary Rebar: Concrete Quantity (m3): Reinforcement Quantity (kg): | AO27: #N/A | AP27: Obelisk | AQ27: #N/A | AR27: #N/A | AS27: 38.5 | AT27: #N/A | AU27: 1172.4577 | AV27: -1160.1267 | AW27: -184.54889 | AX27: #N/A | AY27: #N/A | AZ27: #N/A
A28: TMO5012 | B28: Structure | C28: TMO5012-T02 | E28: MLA | F28: Active | G28: Vodafone | H28: Towercom | I28: Vodafone | J28: 1 | K28: Full SRF | L28: Full SAF | M28: 1 | T28: 0 | U28: 1 | V28: Metreel | W28: 1 | X28: 125654 | Y28: 284185 | Z28: 53.80204 | AA28: -9.12912 | AB28: 46620.958 | AG28: FL99 | AH28: #N/A | AI28: #N/A | AJ28: 48 | AK28: #N/A | AL28: #N/A | AM28: Pad | AN28: Concrete Grade: Main Rebar: Corner/Secondary Rebar: Concrete Quantity (m3): Reinforcement Quantity (kg): | AO28: #N/A | AP28: KTL | AQ28: #N/A | AR28: #N/A | AS28: 34 | AT28: #N/A | AU28: 1221.6067 | AV28: -1214.9267 | AW28: -194.32222 | AX28: #N/A | AY28: #N/A | AZ28: #N/A
A29: TRN7002 | B29: Structure | C29: TRN7002-T01 | D29: TRN5014 | E29: Non MLA | F29: Active | G29: Vodafone | H29: Towercom | I29: Vodafone | J29: 1 | K29: Full SRF | L29: Full SAF | M29: 1 | T29: 1 | U29: 0 | W29: 1 | X29: 162085 | Y29: 294690 | Z29: 53.90034 | AA29: -8.57753 | AB29: 45938.958 | AG29: DEL-6 A-E | AH29: #N/A | AI29: #N/A | AJ29: 49 | AK29: #N/A | AL29: #N/A | AM29: Slab | AN29: Concrete Grade: Main Rebar: Corner/Secondary Rebar: Concrete Quantity (m3): Reinforcement Quantity (kg): | AO29: #N/A | AP29: Obelisk | AQ29: #N/A | AR29: #N/A | AS29: 29.5 | AT29: #N/A | AU29: 1270.7557 | AV29: -1269.7267 | AW29: -204.09556 | AX29: #N/A | AY29: #N/A | AZ29: #N/A
A30: TMO1001 | B30: Structure | C30: TMO1001-T01 | E30: Schedule 1 | F30: Active | G30: Towercom | H30: Towercom | I30: Towercom | J30: 1 | K30: Full SRF | L30: Full SAF | M30: 1 | O30: Guyed Mast | P30: Type - FLI - 1 | Q30: 106 | T30: 1 | U30: 0 | W30: 0 | X30: 123826 | Y30: 318432 | Z30: 54.109386 | AA30: -9.165398 | AB30: 46422 | AD30: 42850.958 | AF30: 46502.958 | AG30: FL100 | AH30: 0 | AI30: town | AJ30: 50 | AK30: flat | AL30: 26.5 | AM30: Pile | AN30: Concrete Grade: Main Rebar: Corner/Secondary Rebar: Concrete Quantity (m3): Reinforcement Quantity (kg): | AO30: 0 | AP30: KTL | AQ30: 0 | AR30: 0 | AS30: 25 | AT30: 0 | AU30: 1319.9047 | AV30: -1324.5267 | AW30: -213.86889 | AX30: 0.95 | AY30: 0.05 | AZ30: Amber
A31: TWX5030 | B31: Structure | C31: TWX5030-T01 | E31: MLA | F31: Retired | G31: Vodafone | H31: Towercom | I31: Vodafone | J31: 0 | K31: No SRF | L31: TL Only | M31: 0 | T31: 0 | U31: 1 | V31: Latchway | W31: 1 | X31: 279380 | Y31: 124670 | Z31: 52.368302 | AA31: -6.835331 | AB31: 46596.958 | AG31: DEL-6 A-E | AH31: #N/A | AI31: #N/A | AJ31: 51 | AK31: #N/A | AL31: #N/A | AM31: Pad | AN31: Concrete Grade: Main Rebar: Corner/Secondary Rebar: Concrete Quantity (m3): Reinforcement Quantity (kg): | AO31: #N/A | AP31: Obelisk | AQ31: #N/A | AR31: #N/A | AS31: 20.5 | AT31: #N/A | AU31: 1369.0537 | AV31: -1379.3267 | AW31: -223.64222 | AX31: #N/A | AY31: #N/A | AZ31: #N/A
A32: TWX5030 | B32: Structure | C32: TWX5030-T02 | E32: MLA | F32: Active | G32: Vodafone | H32: Towercom | I32: Vodafone | J32: 1 | K32: Full SRF | L32: Full SAF | M32: 1 | T32: 1 | U32: 1 | V32: Latchway | W32: 1 | X32: 279380 | Y32: 124670 | Z32: 52.368302 | AA32: -6.835331 | AB32: 46596.958 | AG32: FL101 | AH32: #N/A | AI32: #N/A | AJ32: 52 | AK32: #N/A | AL32: #N/A | AM32: Slab | AN32: Concrete Grade: Main Rebar: Corner/Secondary Rebar: Concrete Quantity (m3): Reinforcement Quantity (kg): | AO32: #N/A | AP32: KTL | AQ32: #N/A | AR32: #N/A | AS32: 16 | AT32: #N/A | AU32: 1418.2027 | AV32: -1434.1267 | AW32: -233.41556 | AX32: #N/A | AY32: #N/A | AZ32: #N/A
A33: TCK6005 | B33: Structure | C33: TCK6005-T01 | E33: Schedule 3f | F33: Active | G33: Towercom | H33: Towercom | I33: Towercom | J33: 1 | K33: Full SRF | L33: Full SAF | M33: 1 | O33: Monopole | P33: Type - 25m - 03 | Q33: 25 | T33: 1 | U33: 1 | V33: Metreel | W33: 1 | X33: 169290 | Y33: 53776 | Z33: 51.73608 | AA33: -8.44525 | AB33: 46193.958 | AG33: DEL-6 A-E | AH33: 2008-2010 | AI33: country | AJ33: 53 | AK33: flat | AL33: 26 | AM33: Pile | AN33: Concrete Grade: Main Rebar: Corner/Secondary Rebar: Concrete Quantity (m3): Reinforcement Quantity (kg): | AO33: 5.3 x 5.3 x 1.0 | AP33: Obelisk | AQ33: 0 | AR33: 0 | AS33: 11.5 | AT33: 0 | AU33: 1467.3517 | AV33: -1488.9267 | AW33: -243.18889 | AX33: 0.45 | AY33: 0.55 | AZ33: green
A34: TGY5016 | B34: Structure | C34: TGY5016-R01 | E34: MLA | F34: Active | G34: Vodafone | H34: Towercom | I34: Vodafone | J34: 1 | K34: Full SRF | L34: Full SAF | M34: 1 | O34: Rooftop | P34: Pole Mount | Q34: 10 | S34: 10 | T34: 0 | U34: 1 | V34: Metreel | W34: 0 | X34: 185304 | Y34: 230974 | Z34: 53.32906 | AA34: -8.22131 | AB34: 46668.958 | AG34: FL102 | AH34: N/A | AI34: town | AJ34: 54 | AK34: flat | AL34: 25.5 | AM34: Pad | AN34: Concrete Grade: Main Rebar: Corner/Secondary Rebar: Concrete Quantity (m3): Reinforcement Quantity (kg): | AO34: 0 | AP34: KTL | AQ34: 0 | AR34: metreel ladder issue | AS34: 7 | AT34: 0 | AU34: 1516.5007 | AV34: -1543.7267 | AW34: -252.96222 | AX34: 0.9 | AY34: 0.1 | AZ34: Amber
A35: TCK5018 | B35: Structure | C35: TCK5018-T01 | D35: TCK7400 | E35: MLA | F35: To be Retired | G35: Vodafone | H35: Towercom | I35: Vodafone | J35: 0 | K35: Remove Only | L35: Full SAF | M35: 1 | T35: 0 | U35: 0 | W35: 0 | X35: 162189 | Y35: 62061 | Z35: 51.81011 | AA35: -8.54894 | AB35: 45897.958 | AG35: DEL-6 A-E | AH35: #N/A | AI35: #N/A | AJ35: 55 | AK35: #N/A | AL35: #N/A | AM35: Slab | AN35: Concrete Grade: Main Rebar: Corner/Secondary Rebar: Concrete Quantity (m3): Reinforcement Quantity (kg): | AO35: #N/A | AP35: Obelisk | AQ35: #N/A | AR35: #N/A | AS35: 2.5 | AT35: #N/A | AU35: 1565.6497 | AV35: -1598.5267 | AW35: -262.73556 | AX35: #N/A | AY35: #N/A | AZ35: #N/A
A36: TCK5018 | B36: Structure | C36: TCK5018-T02 | D36: TCK7400 | E36: MLA | F36: Active | G36: Vodafone | H36: Towercom | I36: Vodafone | J36: 1 | K36: Full SRF | L36: Full SAF | M36: 1 | T36: 0 | U36: 0 | W36: 0 | X36: 162189 | Y36: 62061 | Z36: 51.81011 | AA36: -8.54894 | AB36: 45897.958 | AG36: FL103 | AH36: #N/A | AI36: #N/A | AJ36: 56 | AK36: #N/A | AL36: #N/A | AM36: Pile | AN36: Concrete Grade: Main Rebar: Corner/Secondary Rebar: Concrete Quantity (m3): Reinforcement Quantity (kg): | AO36: #N/A | AP36: KTL | AQ36: #N/A | AR36: #N/A | AS36: -2 | AT36: #N/A | AU36: 1614.7987 | AV36: -1653.3267 | AW36: -272.50889 | AX36: #N/A | AY36: #N/A | AZ36: #N/A
A37: TMO2002 | B37: Structure | C37: TMO2002-T01 | E37: Schedule 2 | F37: Active | G37: Towercom | H37: Towercom | I37: Towercom | J37: 1 | K37: Full SRF | L37: Full SAF | M37: 1 | O37: Lattice Tower | P37: Type - ARU - 1 | Q37: 83 | T37: 1 | U37: 0 | W37: 1 | X37: 118921 | Y37: 264516 | Z37: 53.624354 | AA37: -9.226138 | AB37: 46620.958 | AG37: DEL-6 A-E | AH37: 0 | AI37: town | AJ37: 57 | AK37: flat | AL37: 26 | AM37: Pad | AN37: Concrete Grade: Main Rebar: Corner/Secondary Rebar: Concrete Quantity (m3): Reinforcement Quantity (kg): | AO37: 0 | AP37: Obelisk | AQ37: 0 | AR37: 0 | AS37: -6.5 | AT37: 0 | AU37: 1663.9477 | AV37: -1708.1267 | AW37: -282.28222 | AX37: 0.65 | AY37: 0.35 | AZ37: Green
A38: TDL5019 | B38: Structure | C38: TDL5019-T01 | E38: MLA | F38: Active | G38: Vodafone | H38: Towercom | I38: Vodafone | J38: 1 | K38: Full SRF | L38: Full SAF | M38: 1 | O38: Lattice Tower | P38: Eve Type 6 | Q38: 15 | T38: 1 | U38: 0 | W38: 1 | X38: 192067 | Y38: 369961 | Z38: 54.57787 | AA38: -8.12343 | AB38: 46585.958 | AG38: FL104 | AH38: 1993-1996 | AI38: Country | AJ38: 58 | AK38: Flat | AL38: 26.5 | AM38: Slab | AN38: Concrete Grade: Main Rebar: Corner/Secondary Rebar: Concrete Quantity (m3): Reinforcement Quantity (kg): | AO38: 0 | AP38: KTL | AQ38: 0 | AR38: 0 | AS38: -11 | AT38: 0 | AU38: 1713.0967 | AV38: -1762.9267 | AW38: -292.05556 | AX38: 0.7 | AY38: 0.3 | AZ38: Green
A39: TCN5015 | B39: Structure | C39: TCN5015-T01 | D39: TCN7401 | E39: MLA | F39: UTS | G39: Vodafone | H39: Towercom | I39: Vodafone | J39: 1 | K39: Full SRF | L39: Full SAF | M39: 1 | O39: Wooden Pole | P39: Wooden Pole | Q39: 10 | T39: 0 | U39: 0 | W39: 0 | X39: 238788 | Y39: 298142 | Z39: 53.93129 | AA39: -7.41024 | AB39: 46183.958 | AG39: DEL-6 A-E | AH39: 1990-2001 | AI39: town | AJ39: 59 | AK39: Flat | AL39: 25.5 | AM39: Pile | AN39: Concrete Grade: Main Rebar: Corner/Secondary Rebar: Concrete Quantity (m3): Reinforcement Quantity (kg): | AO39: 0 | AP39: Obelisk | AQ39: 0 | AR39: 0 | AS39: -15.5 | AT39: 0 | AU39: 1762.2457 | AV39: -1817.7267 | AW39: -301.82889 | AX39: 0.95 | AY39: 0.05 | AZ39: Red
A40: TDU5020 | B40: Structure | C40: TDU5020-T01 | E40: MLA | F40: Active | G40: Vodafone | H40: Towercom | I40: Vodafone | J40: 1 | K40: Full SRF | L40: Full SAF | M40: 1 | O40: Lattice Tower | P40: Eve Type 5 | Q40: 20 | T40: 1 | U40: 1 | V40: latchway | W40: 1 | X40: 313418 | Y40: 226918 | Z40: 53.2807 | AA40: -6.30034 | AB40: 46228.958 | AG40: FL105 | AH40: 1993-1996 | AI40: Town | AJ40: 60 | AK40: Flat | AL40: 25 | AM40: Pad | AN40: Concrete Grade: Main Rebar: Corner/Secondary Rebar: Concrete Quantity (m3): Reinforcement Quantity (kg): | AO40: 4.4 x 4.4 x 1.2 | AP40: KTL | AQ40: 0 | AR40: Headframe | AS40: -20 | AT40: 0 | AU40: 1811.3947 | AV40: -1872.5267 | AW40: -311.60222 | AX40: 0.9 | AY40: 0.1 | AZ40: Amber
A41: TLS5013 | B41: Structure | C41: TLS5013-T01 | D41: TLS7402 | E41: MLA | F41: Retired | G41: Vodafone | H41: Towercom | I41: Vodafone | J41: 0 | K41: No SRF | L41: TL Only | M41: 0 | T41: 0 | U41: 0 | W41: 0 | X41: 237246 | Y41: 181356 | Z41: 52.88214 | AA41: -7.44748 | AG41: DEL-6 A-E | AH41: #N/A | AI41: #N/A | AJ41: 61 | AK41: #N/A | AL41: #N/A | AM41: Slab | AN41: Concrete Grade: Main Rebar: Corner/Secondary Rebar: Concrete Quantity (m3): Reinforcement Quantity (kg): | AO41: #N/A | AP41: Obelisk | AQ41: #N/A | AR41: #N/A | AS41: -24.5 | AT41: #N/A | AU41: 1860.5437 | AV41: -1927.3267 | AW41: -321.37556 | AX41: #N/A | AY41: #N/A | AZ41: #N/A
A42: TLS5013 | B42: Structure | C42: TLS5013-T02 | D42: TLS7402 | E42: MLA | F42: Active | G42: Vodafone | H42: Towercom | I42: Vodafone | J42: 1 | K42: Full SRF | L42: Full SAF | M42: 1 | T42: 0 | U42: 0 | W42: 0 | X42: 237246 | Y42: 181356 | Z42: 52.88214 | AA42: -7.44748 | AG42: FL106 | AH42: #N/A | AI42: #N/A | AJ42: 62 | AK42: #N/A | AL42: #N/A | AM42: Pile | AN42: Concrete Grade: Main Rebar: Corner/Secondary Rebar: Concrete Quantity (m3): Reinforcement Quantity (kg): | AO42: #N/A | AP42: KTL | AQ42: #N/A | AR42: #N/A | AS42: -29 | AT42: #N/A | AU42: 1909.6927 | AV42: -1982.1267 | AW42: -331.14889 | AX42: #N/A | AY42: #N/A | AZ42: #N/A
A43: TKY6029 | B43: Structure | C43: TKY6029-T01 | E43: Schedule 3f | F43: Active | G43: Towercom | H43: Towercom | I43: Towercom | J43: 1 | K43: Full SRF | L43: Full SAF | M43: 1 | O43: Monopole | P43: Del_3 - 15 | Q43: 15 | T43: 1 | U43: 1 | V43: Metreel | W43: 1 | X43: 38864 | Y43: 106875 | Z43: 52.19059 | AA43: -10.35707 | AB43: 46570.958 | AG43: DEL-6 A-E | AH43: 2008-2010 | AI43: country | AJ43: 63 | AK43: base of hill | AL43: 27.5 | AM43: Pad | AN43: Concrete Grade: Main Rebar: Corner/Secondary Rebar: Concrete Quantity (m3): Reinforcement Quantity (kg): | AO43: 3.5 x 3.5 x 1.25 | AP43: Obelisk | AQ43: 0 | AR43: 0 | AS43: -33.5 | AT43: 0 | AU43: 1958.8417 | AV43: -2036.9267 | AW43: -340.92222 | AX43: 0.6 | AY43: 0.4 | AZ43: green
A44: TRN5021 | B44: Structure | C44: TRN5021-T01 | D44: TRN7403 | E44: MLA | F44: Retired | G44: Vodafone | H44: Towercom | I44: Vodafone | J44: 0 | K44: No SRF | L44: TL Only | M44: 0 | T44: 0 | U44: 0 | W44: 0 | X44: 186635 | Y44: 313932 | Z44: 54.07442 | AA44: -8.20492 | AG44: FL107 | AH44: #N/A | AI44: #N/A | AJ44: 64 | AK44: #N/A | AL44: #N/A | AM44: Slab | AN44: Concrete Grade: Main Rebar: Corner/Secondary Rebar: Concrete Quantity (m3): Reinforcement Quantity (kg): | AO44: #N/A | AP44: KTL | AQ44: #N/A | AR44: #N/A | AS44: -38 | AT44: #N/A | AU44: 2007.9907 | AV44: -2091.7267 | AW44: -350.69556 | AX44: #N/A | AY44: #N/A | AZ44: #N/A
A45: TRN5021 | B45: Structure | C45: TRN5021-T02 | D45: TRN7403 | E45: MLA | F45: Active | G45: Vodafone | H45: Towercom | I45: Vodafone | J45: 1 | K45: Full SRF | L45: Full SAF | M45: 1 | T45: 0 | U45: 0 | W45: 0 | X45: 186635 | Y45: 313932 | Z45: 54.07442 | AA45: -8.20492 | AG45: DEL-6 A-E | AH45: #N/A | AI45: #N/A | AJ45: 65 | AK45: #N/A | AL45: #N/A | AM45: Pile | AN45: Concrete Grade: Main Rebar: Corner/Secondary Rebar: Concrete Quantity (m3): Reinforcement Quantity (kg): | AO45: #N/A | AP45: Obelisk | AQ45: #N/A | AR45: #N/A | AS45: -42.5 | AT45: #N/A | AU45: 2057.1397 | AV45: -2146.5267 | AW45: -360.46889 | AX45: #N/A | AY45: #N/A | AZ45: #N/A
A46: TGY6419 | B46: Structure | C46: TGY6419-T01 | D46: TGY6019 | E46: Schedule 3b | F46: Active | G46: Towercom | H46: Towercom | I46: Towercom | J46: 1 | K46: Full SRF | L46: Full SAF | M46: 1 | T46: 1 | U46: 1 | V46: Metreel | W46: 1 | X46: 178262 | Y46: 252490 | Z46: 53.52213 | AA46: -8.32848 | AB46: 46599.958 | AG46: FL108 | AH46: #N/A | AI46: #N/A | AJ46: 66 | AK46: #N/A | AL46: #N/A | AM46: Pad | AN46: Concrete Grade: Main Rebar: Corner/Secondary Rebar: Concrete Quantity (m3): Reinforcement Quantity (kg): | AO46: #N/A | AP46: KTL | AQ46: #N/A | AR46: #N/A | AS46: -47 | AT46: #N/A | AU46: 2106.2887 | AV46: -2201.3267 | AW46: -370.24222 | AX46: #N/A | AY46: #N/A | AZ46: #N/A
A47: TCK6006 | B47: Structure | C47: TCK6006-T01 | E47: Schedule 3f | F47: Active | G47: Towercom | H47: Towercom | I47: Towercom | J47: 1 | K47: Full SRF | L47: Full SAF | M47: 1 | O47: Monopole | P47: Type - 25m - 03 | Q47: 25 | T47: 1 | U47: 1 | V47: Metreel | W47: 1 | X47: 167465 | Y47: 63707 | Z47: 51.82523 | AA47: -8.4726 | AB47: 46193.958 | AG47: DEL-6 A-E | AH47: 2008-2010 | AI47: country | AJ47: 67 | AK47: hill | AL47: 25.5 | AM47: Slab | AN47: Concrete Grade: Main Rebar: Corner/Secondary Rebar: Concrete Quantity (m3): Reinforcement Quantity (kg): | AO47: 5.3 x 5.3 x 1.0 | AP47: Obelisk | AQ47: 0 | AR47: 0 | AS47: -51.5 | AT47: 0 | AU47: 2155.4377 | AV47: -2256.1267 | AW47: -380.01556 | AX47: 0.45 | AY47: 0.55 | AZ47: green
A48: TWW1002 | B48: Structure | C48: TWW1002-T01 | E48: Schedule 1 | F48: Active | G48: Towercom | H48: Towercom | I48: Towercom | J48: 1 | K48: Full SRF | L48: Full SAF | M48: 1 | O48: Lattice Tower | P48: Type - WAT - 3 | Q48: 52 | T48: 0 | U48: 0 | W48: 1 | X48: 331119 | Y48: 192539 | Z48: 52.967899 | AA48: -6.049156 | AB48: 46177.958 | AD48: 41436.958 | AF48: 45088.958 | AG48: FL109 | AH48: 0 | AI48: town | AJ48: 68 | AK48: hill | AL48: 25 | AM48: Pile | AN48: Concrete Grade: Main Rebar: Corner/Secondary Rebar: Concrete Quantity (m3): Reinforcement Quantity (kg): | AO48: 0 | AP48: KTL | AQ48: 0 | AR48: 0 | AS48: -56 | AT48: 0 | AU48: 2204.5867 | AV48: -2310.9267 | AW48: -389.78889 | AX48: 0.7 | AY48: 0.3 | AZ48: Green
A49: TCN5022 | B49: Structure | C49: TCN5022-T01 | E49: MLA | F49: Retired | G49: Vodafone | H49: Towercom | I49: Vodafone | J49: 0 | K49: No SRF | L49: TL Only | M49: 0 | T49: 0 | U49: 0 | W49: 0 | X49: 244782 | Y49: 311217 | Z49: 54.04826 | AA49: -7.31707 | AG49: DEL-6 A-E | AH49: #N/A | AI49: #N/A | AJ49: 69 | AK49: #N/A | AL49: #N/A | AM49: Pad | AN49: Concrete Grade: Main Rebar: Corner/Secondary Rebar: Concrete Quantity (m3): Reinforcement Quantity (kg): | AO49: #N/A | AP49: Obelisk | AQ49: #N/A | AR49: #N/A | AS49: -60.5 | AT49: #N/A | AU49: 2253.7357 | AV49: -2365.7267 | AW49: -399.56222 | AX49: #N/A | AY49: #N/A | AZ49: #N/A
A50: TCN5022 | B50: Structure | C50: TCN5022-T02 | D50: TCN7304 | E50: Option A (EED) | F50: Active | G50: Eircom | H50: Towercom | I50: Eircom | J50: 1 | K50: Full SRF | L50: Full SAF | M50: 1 | T50: 0 | U50: 0 | W50: 0 | X50: 244782 | Y50: 311217 | Z50: 54.04826 | AA50: -7.31707 | AG50: FL110 | AH50: #N/A | AI50: #N/A | AJ50: 70 | AK50: #N/A | AL50: #N/A | AM50: Slab | AN50: Concrete Grade: Main Rebar: Corner/Secondary Rebar: Concrete Quantity (m3): Reinforcement Quantity (kg): | AO50: #N/A | AP50: KTL | AQ50: #N/A | AR50: #N/A | AS50: -65 | AT50: #N/A | AU50: 2302.8847 | AV50: -2420.5267 | AW50: -409.33556 | AX50: #N/A | AY50: #N/A | AZ50: #N/A
A51: TMO6048 | B51: Structure | C51: TMO6048-T01 | E51: Schedule 3f | F51: Active | G51: Towercom | H51: Towercom | I51: Towercom | J51: 1 | K51: Full SRF | L51: Full SAF | M51: 1 | O51: Lattice Tower | P51: Eve Type 6 | Q51: 15 | T51: 1 | U51: 1 | V51: Latchway | W51: 1 | X51: 149388 | Y51: 279749 | Z51: 53.76503 | AA51: -8.76822 | AB51: 46655.958 | AG51: DEL-6 A-E | AH51: 1993-1996 | AI51: town | AJ51: 71 | AK51: flat | AL51: 26 | AM51: Pile | AN51: Concrete Grade: Main Rebar: Corner/Secondary Rebar: Concrete Quantity (m3): Reinforcement Quantity (kg): | AO51: 0 | AP51: Obelisk | AQ51: 0 | AR51: 0 | AS51: -69.5 | AT51: 0 | AU51: 2352.0337 | AV51: -2475.3267 | AW51: -419.10889 | AX51: 0.5 | AY51: 0.5 | AZ51: green
A52: TMO7003 | B52: Structure | C52: TMO7003-T01 | D52: TMO5023 | E52: Non MLA | F52: Active | G52: Vodafone | H52: Towercom | I52: Vodafone | J52: 1 | K52: Full SRF | L52: Full SAF | M52: 1 | T52: 1 | U52: 1 | V52: Latchway | W52: 1 | X52: 149388 | Y52: 279749 | Z52: 53.76503 | AA52: -8.76822 | AB52: 46655.958 | AG52: FL111 | AH52: #N/A | AI52: #N/A | AJ52: 72 | AK52: #N/A | AL52: #N/A | AM52: Pad | AN52: Concrete Grade: Main Rebar: Corner/Secondary Rebar: Concrete Quantity (m3): Reinforcement Quantity (kg): | AO52: #N/A | AP52: KTL | AQ52: #N/A | AR52: #N/A | AS52: -74 | AT52: #N/A | AU52: 2401.1827 | AV52: -2530.1267 | AW52: -428.88222 | AX52: #N/A | AY52: #N/A | AZ52: #N/A
A53: TMO5024 | B53: Structure | C53: TMO5024-T01 | E53: MLA | F53: Active | G53: Vodafone | H53: Towercom | I53: Vodafone | J53: 1 | K53: Full SRF | L53: Full SAF | M53: 1 | O53: Wooden Pole | P53: Wooden Pole | Q53: 10 | T53: 0 | U53: 0 | W53: 0 | X53: 114001 | Y53: 280810 | Z53: 53.76993 | AA53: -9.30499 | AB53: 46508.958 | AG53: DEL-6 A-E | AH53: 1990-2001 | AI53: Country | AJ53: 73 | AK53: Flat | AL53: 26.5 | AM53: Slab | AN53: Concrete Grade: Main Rebar: Corner/Secondary Rebar: Concrete Quantity (m3): Reinforcement Quantity (kg): | AO53: 0 | AP53: Obelisk | AQ53: 0 | AR53: 0 | AS53: -78.5 | AT53: 0 | AU53: 2450.3317 | AV53: -2584.9267 | AW53: -438.65556 | AX53: 0.95 | AY53: 0.05 | AZ53: Blue
A54: TKY7004 | B54: Structure | C54: TKY7004-T01 | D54: TKY5025 | E54: Non MLA | F54: Active | G54: Vodafone | H54: Towercom | I54: Vodafone | J54: 1 | K54: Full SRF | L54: Full SAF | M54: 1 | T54: 0 | U54: 0 | W54: 0 | X54: 75724 | Y54: 128312 | Z54: 52.39267 | AA54: -9.8263 | AB54: 46141.958 | AG54: FL112 | AH54: #N/A | AI54: #N/A | AJ54: 74 | AK54: #N/A | AL54: #N/A | AM54: Pile | AN54: Concrete Grade: Main Rebar: Corner/Secondary Rebar: Concrete Quantity (m3): Reinforcement Quantity (kg): | AO54: #N/A | AP54: KTL | AQ54: #N/A | AR54: #N/A | AS54: -83 | AT54: #N/A | AU54: 2499.4807 | AV54: -2639.7267 | AW54: -448.42889 | AX54: #N/A | AY54: #N/A | AZ54: #N/A
A55: TLK1003 | B55: Structure | C55: TLK1003-T01 | E55: Schedule 1 | F55: Active | G55: Towercom | H55: Towercom | I55: Towercom | J55: 1 | K55: Full SRF | L55: Full SAF | M55: 1 | O55: Lattice Tower | P55: Type - ARU - 1 | Q55: 30 | T55: 0 | U55: 0 | W55: 1 | X55: 161633 | Y55: 117265 | Z55: 52.306162 | AA55: -8.563212 | AB55: 46192.958 | AG55: DEL-6 A-E | AH55: 0 | AI55: country | AJ55: 75 | AK55: hill | AL55: 25.5 | AM55: Pad | AN55: Concrete Grade: Main Rebar: Corner/Secondary Rebar: Concrete Quantity (m3): Reinforcement Quantity (kg): | AO55: 0 | AP55: Obelisk | AQ55: 0 | AR55: 0 | AS55: -87.5 | AT55: 0 | AU55: 2548.6297 | AV55: -2694.5267 | AW55: -458.20222 | AX55: 0.55 | AY55: 0.45 | AZ55: Green
A56: TCK4002 | B56: Structure | C56: TCK4002-T01 | E56: Schedule 3b | F56: Active | G56: Towercom | H56: Towercom | I56: Towercom | J56: 1 | K56: Full SRF | L56: Full SAF | M56: 1 | O56: Wooden Pole | P56: Wooden Pole | Q56: 10 | T56: 0 | U56: 0 | W56: 0 | X56: 121356 | Y56: 76663 | Z56: 51.937058 | AA56: -9.144212 | AB56: 46540.958 | AG56: FL113 | AH56: 0 | AI56: country | AJ56: 76 | AK56: base of hill | AL56: 27 | AM56: Slab | AN56: Concrete Grade: Main Rebar: Corner/Secondary Rebar: Concrete Quantity (m3): Reinforcement Quantity (kg): | AO56: 0 | AP56: KTL | AQ56: 0 | AR56: 0 | AS56: -92 | AT56: 0 | AU56: 2597.7787 | AV56: -2749.3267 | AW56: -467.97556 | AX56: 1 | AY56: 0 | AZ56: Red
A57: TRN5028 | B57: Structure | C57: TRN5028-T01 | E57: MLA | F57: Retired | G57: Vodafone | H57: Towercom | I57: Vodafone | J57: 0 | K57: No SRF | L57: TL Only | M57: 0 | T57: 0 | U57: 1 | V57: Metreel | W57: 1 | X57: 170229 | Y57: 272160 | Z57: 53.69846 | AA57: -8.45147 | AB57: 46359 | AG57: DEL-6 A-E | AH57: #N/A | AI57: #N/A | AJ57: 77 | AK57: #N/A | AL57: #N/A | AM57: Pile | AN57: Concrete Grade: Main Rebar: Corner/Secondary Rebar: Concrete Quantity (m3): Reinforcement Quantity (kg): | AO57: #N/A | AP57: Obelisk | AQ57: #N/A | AR57: #N/A | AS57: -96.5 | AT57: #N/A | AU57: 2646.9277 | AV57: -2804.1267 | AW57: -477.74889 | AX57: #N/A | AY57: #N/A | AZ57: #N/A
A58: TRN5028 | B58: Structure | C58: TRN5028-T02 | E58: MLA | F58: Active | G58: Vodafone | H58: Towercom | I58: Vodafone | J58: 1 | K58: Full SRF | L58: Full SAF | M58: 1 | T58: 0 | U58: 1 | V58: Metreel | W58: 1 | X58: 170229 | Y58: 272160 | Z58: 53.69846 | AA58: -8.45147 | AB58: 46359 | AG58: FL114 | AH58: #N/A | AI58: #N/A | AJ58: 78 | AK58: #N/A | AL58: #N/A | AM58: Pad | AN58: Concrete Grade: Main Rebar: Corner/Secondary Rebar: Concrete Quantity (m3): Reinforcement Quantity (kg): | AO58: #N/A | AP58: KTL | AQ58: #N/A | AR58: #N/A | AS58: -101 | AT58: #N/A | AU58: 2696.0767 | AV58: -2858.9267 | AW58: -487.52222 | AX58: #N/A | AY58: #N/A | AZ58: #N/A
A59: TWH6065 | B59: Structure | C59: TWH6065-T01 | E59: Schedule 3f | F59: Active | G59: Towercom | H59: Towercom | I59: Towercom | J59: 1 | K59: Full SRF | L59: Full SAF | M59: 1 | O59: Monopole | P59: Del_3 - 15 | Q59: 15 | T59: 1 | U59: 1 | V59: Metreel | W59: 1 | X59: 221854 | Y59: 249079 | Z59: 53.49148 | AA59: -7.67149 | AB59: 46309.958 | AG59: DEL-6 A-E | AH59: 2008-2010 | AI59: town | AJ59: 79 | AK59: flat | AL59: 25 | AM59: Slab | AN59: Concrete Grade: Main Rebar: Corner/Secondary Rebar: Concrete Quantity (m3): Reinforcement Quantity (kg): | AO59: 3.5 x 3.5 x 1.0 | AP59: Obelisk | AQ59: 0 | AR59: 0 | AS59: -105.5 | AT59: 0 | AU59: 2745.2257 | AV59: -2913.7267 | AW59: -497.29556 | AX59: 0.45 | AY59: 0.55 | AZ59: green
A60: TKE5029 | B60: Structure | C60: TKE5029-T01 | E60: MLA | F60: Retired | G60: Vodafone | H60: Towercom | I60: Vodafone | J60: 0 | K60: No SRF | L60: TL Only | M60: 0 | T60: 0 | U60: 1 | V60: Metreel | W60: 1 | X60: 292585 | Y60: 210300 | Z60: 53.13551 | AA60: -6.61732 | AB60: 46541.958 | AG60: FL115 | AH60: #N/A | AI60: #N/A | AJ60: 80 | AK60: #N/A | AL60: #N/A | AM60: Pile | AN60: Concrete Grade: Main Rebar: Corner/Secondary Rebar: Concrete Quantity (m3): Reinforcement Quantity (kg): | AO60: #N/A | AP60: KTL | AQ60: #N/A | AR60: #N/A | AS60: -110 | AT60: #N/A | AU60: 2794.3747 | AV60: -2968.5267 | AW60: -507.06889 | AX60: #N/A | AY60: #N/A | AZ60: #N/A
A61: TKE5029 | B61: Structure | C61: TKE5029-T02 | E61: MLA | F61: Active | G61: Vodafone | H61: Towercom | I61: Vodafone | J61: 1 | K61: Full SRF | L61: Full SAF | M61: 1 | T61: 0 | U61: 1 | V61: Metreel | W61: 1 | X61: 292585 | Y61: 210300 | Z61: 53.13551 | AA61: -6.61732 | AB61: 46541.958 | AG61: DEL-6 A-E | AH61: #N/A | AI61: #N/A | AJ61: 81 | AK61: #N/A | AL61: #N/A | AM61: Pad | AN61: Concrete Grade: Main Rebar: Corner/Secondary Rebar: Concrete Quantity (m3): Reinforcement Quantity (kg): | AO61: #N/A | AP61: Obelisk | AQ61: #N/A | AR61: #N/A | AS61: -114.5 | AT61: #N/A | AU61: 2843.5237 | AV61: -3023.3267 | AW61: -516.84222 | AX61: #N/A | AY61: #N/A | AZ61: #N/A
A62: TSO5027 | B62: Structure | C62: TSO5027-T01 | E62: MLA | F62: To be Retired | G62: Vodafone | H62: Towercom | I62: Vodafone | J62: 0 | K62: Remove Only | L62: Full SAF | M62: 1 | T62: 0 | U62: 0 | W62: 0 | X62: 166234 | Y62: 315598 | Z62: 54.08846 | AA62: -8.51674 | AB62: 46143.958 | AG62: FL116 | AH62: #N/A | AI62: #N/A | AJ62: 82 | AK62: #N/A | AL62: #N/A | AM62: Slab | AN62: Concrete Grade: Main Rebar: Corner/Secondary Rebar: Concrete Quantity (m3): Reinforcement Quantity (kg): | AO62: #N/A | AP62: KTL | AQ62: #N/A | AR62: #N/A | AS62: -119 | AT62: #N/A | AU62: 2892.6727 | AV62: -3078.1267 | AW62: -526.61556 | AX62: #N/A | AY62: #N/A | AZ62: #N/A
A63: TSO5027 | B63: Structure | C63: TSO5027-T02 | E63: MLA | F63: Active | G63: Vodafone | H63: Towercom | I63: Vodafone | J63: 1 | K63: Full SRF | L63: Full SAF | M63: 1 | T63: 0 | U63: 0 | W63: 0 | X63: 166234 | Y63: 315598 | Z63: 54.08846 | AA63: -8.51674 | AB63: 46143.958 | AG63: DEL-6 A-E | AH63: #N/A | AI63: #N/A | AJ63: 83 | AK63: #N/A | AL63: #N/A | AM63: Pile | AN63: Concrete Grade: Main Rebar: Corner/Secondary Rebar: Concrete Quantity (m3): Reinforcement Quantity (kg): | AO63: #N/A | AP63: Obelisk | AQ63: #N/A | AR63: #N/A | AS63: -123.5 | AT63: #N/A | AU63: 2941.8217 | AV63: -3132.9267 | AW63: -536.38889 | AX63: #N/A | AY63: #N/A | AZ63: #N/A
A64: TKK5031 | B64: Structure | C64: TKK5031-T01 | E64: MLA | F64: To be Retired | G64: Vodafone | H64: Towercom | I64: Vodafone | J64: 0 | K64: Remove Only | L64: Full SAF | M64: 1 | T64: 0 | U64: 0 | W64: 1 | X64: 245043 | Y64: 171293 | Z64: 52.79113 | AA64: -7.33307 | AB64: 46443 | AG64: FL117 | AH64: #N/A | AI64: #N/A | AJ64: 84 | AK64: #N/A | AL64: #N/A | AM64: Pad | AN64: Concrete Grade: Main Rebar: Corner/Secondary Rebar: Concrete Quantity (m3): Reinforcement Quantity (kg): | AO64: #N/A | AP64: KTL | AQ64: #N/A | AR64: #N/A | AS64: -128 | AT64: #N/A | AU64: 2990.9707 | AV64: -3187.7267 | AW64: -546.16222 | AX64: #N/A | AY64: #N/A | AZ64: #N/A
A65: TKK5031 | B65: Structure | C65: TKK5031-T02 | D65: TKK7305 | E65: Option A (EED) | F65: Active | G65: Eircom | H65: Towercom | I65: Eircom | J65: 1 | K65: Full SRF | L65: Full SAF | M65: 1 | T65: 1 | U65: 0 | W65: 1 | X65: 245043 | Y65: 171293 | Z65: 52.79113 | AA65: -7.33307 | AB65: 46443 | AG65: DEL-6 A-E | AH65: #N/A | AI65: #N/A | AJ65: 85 | AK65: #N/A | AL65: #N/A | AM65: Slab | AN65: Concrete Grade: Main Rebar: Corner/Secondary Rebar: Concrete Quantity (m3): Reinforcement Quantity (kg): | AO65: #N/A | AP65: Obelisk | AQ65: #N/A | AR65: #N/A | AS65: -132.5 | AT65: #N/A | AU65: 3040.1197 | AV65: -3242.5267 | AW65: -555.93556 | AX65: #N/A | AY65: #N/A | AZ65: #N/A
A66: TDL7005 | B66: Structure | C66: TDL7005-R01 | D66: TDL5032 | E66: Non MLA | F66: Active | G66: Vodafone | H66: Towercom | I66: Vodafone | J66: 1 | K66: Full SRF | L66: Full SAF | M66: 1 | S66: 3 | T66: 1 | U66: 0 | W66: 0 | X66: 187772 | Y66: 361322 | Z66: 54.50018 | AA66: -8.18949 | AB66: 46225.958 | AG66: FL118 | AH66: #N/A | AI66: #N/A | AJ66: 86 | AK66: #N/A | AL66: #N/A | AM66: Pile | AN66: Concrete Grade: Main Rebar: Corner/Secondary Rebar: Concrete Quantity (m3): Reinforcement Quantity (kg): | AO66: #N/A | AP66: KTL | AQ66: #N/A | AR66: #N/A | AS66: -137 | AT66: #N/A | AU66: 3089.2687 | AV66: -3297.3267 | AW66: -565.70889 | AX66: #N/A | AY66: #N/A | AZ66: #N/A
A67: TKK1004 | B67: Structure | C67: TKK1004-T01 | E67: Schedule 1 | F67: Active | G67: Towercom | H67: Towercom | I67: Towercom | J67: 1 | K67: Full SRF | L67: Full SAF | M67: 1 | O67: Lattice Tower | P67: Type - ARU - 1 | Q67: 42 | T67: 1 | U67: 0 | W67: 1 | X67: 233252 | Y67: 167750 | Z67: 52.760144 | AA67: -7.50819 | AB67: 46076 | AG67: DEL-6 A-E | AH67: 0 | AI67: country | AJ67: 87 | AK67: hill | AL67: 25.5 | AM67: Pad | AN67: Concrete Grade: Main Rebar: Corner/Secondary Rebar: Concrete Quantity (m3): Reinforcement Quantity (kg): | AO67: 0 | AP67: Obelisk | AQ67: 0 | AR67: 0 | AS67: -141.5 | AT67: 0 | AU67: 3138.4177 | AV67: -3352.1267 | AW67: -575.48222 | AX67: 0.75 | AY67: 0.25 | AZ67: Green
A68: TCK6407 | B68: Structure | C68: TCK6407-R01 | D68: TCK6007 | E68: Schedule 3b | F68: Active | G68: Towercom | H68: Towercom | I68: Towercom | J68: 1 | K68: Full SRF | L68: Full SAF | M68: 1 | S68: 7 | T68: 1 | U68: 0 | W68: 0 | X68: 104750 | Y68: 26358 | Z68: 51.48248 | AA68: -9.37186 | AB68: 46205.958 | AG68: FL119 | AH68: #N/A | AI68: #N/A | AJ68: 88 | AK68: #N/A | AL68: #N/A | AM68: Slab | AN68: Concrete Grade: Main Rebar: Corner/Secondary Rebar: Concrete Quantity (m3): Reinforcement Quantity (kg): | AO68: #N/A | AP68: KTL | AQ68: #N/A | AR68: #N/A | AS68: -146 | AT68: #N/A | AU68: 3187.5667 | AV68: -3406.9267 | AW68: -585.25556 | AX68: #N/A | AY68: #N/A | AZ68: #N/A
A69: TWW5033 | B69: Structure | C69: TWW5033-T01 | E69: MLA | F69: Retired | G69: Vodafone | H69: Towercom | I69: Vodafone | J69: 0 | K69: No SRF | L69: TL Only | M69: 0 | S69: 6 | T69: 0 | U69: 1 | V69: Metreel | W69: 1 | X69: 286803 | Y69: 188240 | Z69: 52.93828 | AA69: -6.70967 | AB69: 46499.958 | AG69: DEL-6 A-E | AH69: #N/A | AI69: #N/A | AJ69: 89 | AK69: #N/A | AL69: #N/A | AM69: Pile | AN69: Concrete Grade: Main Rebar: Corner/Secondary Rebar: Concrete Quantity (m3): Reinforcement Quantity (kg): | AO69: #N/A | AP69: Obelisk | AQ69: #N/A | AR69: #N/A | AS69: -150.5 | AT69: #N/A | AU69: 3236.7157 | AV69: -3461.7267 | AW69: -595.02889 | AX69: #N/A | AY69: #N/A | AZ69: #N/A
A70: TWW5033 | B70: Structure | C70: TWW5033-T02 | E70: MLA | F70: Active | G70: Vodafone | H70: Towercom | I70: Vodafone | J70: 1 | K70: Full SRF | L70: Full SAF | M70: 1 | S70: 6 | T70: 1 | U70: 1 | V70: Metreel | W70: 1 | X70: 286803 | Y70: 188240 | Z70: 52.93828 | AA70: -6.70967 | AB70: 46499.958 | AG70: FL120 | AH70: #N/A | AI70: #N/A | AJ70: 90 | AK70: #N/A | AL70: #N/A | AM70: Pad | AN70: Concrete Grade: Main Rebar: Corner/Secondary Rebar: Concrete Quantity (m3): Reinforcement Quantity (kg): | AO70: #N/A | AP70: KTL | AQ70: #N/A | AR70: #N/A | AS70: -155 | AT70: #N/A | AU70: 3285.8647 | AV70: -3516.5267 | AW70: -604.80222 | AX70: #N/A | AY70: #N/A | AZ70: #N/A
A71: TCK5034 | B71: Structure | C71: TCK5034-R01 | E71: MLA | F71: To be Retired | G71: Vodafone | H71: Towercom | I71: Vodafone | J71: 0 | K71: Remove Only | L71: Full SAF | M71: 1 | S71: 12 | T71: 0 | U71: 0 | W71: 0 | X71: 99858 | Y71: 48400 | Z71: 51.67968 | AA71: -9.44853 | AB71: 46205.958 | AG71: DEL-6 A-E | AH71: #N/A | AI71: #N/A | AJ71: 91 | AK71: #N/A | AL71: #N/A | AM71: Slab | AN71: Concrete Grade: Main Rebar: Corner/Secondary Rebar: Concrete Quantity (m3): Reinforcement Quantity (kg): | AO71: #N/A | AP71: Obelisk | AQ71: #N/A | AR71: #N/A | AS71: -159.5 | AT71: #N/A | AU71: 3335.0137 | AV71: -3571.3267 | AW71: -614.57556 | AX71: #N/A | AY71: #N/A | AZ71: #N/A
A72: TCK5034 | B72: Structure | C72: TCK5034-T01 | D72: TCK7306 | E72: Option A (EED) | F72: UTS | G72: Eircom | H72: Towercom | I72: Eircom | J72: 1 | K72: Full SRF | L72: Full SAF | M72: 1 | S72: 12 | T72: 0 | U72: 0 | W72: 0 | X72: 99858 | Y72: 48400 | Z72: 51.67968 | AA72: -9.44853 | AB72: 46205.958 | AG72: FL121 | AH72: #N/A | AI72: #N/A | AJ72: 92 | AK72: #N/A | AL72: #N/A | AM72: Pile | AN72: Concrete Grade: Main Rebar: Corner/Secondary Rebar: Concrete Quantity (m3): Reinforcement Quantity (kg): | AO72: #N/A | AP72: KTL | AQ72: #N/A | AR72: #N/A | AS72: -164 | AT72: #N/A | AU72: 3384.1627 | AV72: -3626.1267 | AW72: -624.34889 | AX72: #N/A | AY72: #N/A | AZ72: #N/A
A73: TDL1005 | B73: Structure | C73: TDL1005-T01 | E73: Schedule 1 | F73: Active | G73: Towercom | H73: Towercom | I73: Towercom | J73: 1 | K73: Full SRF | L73: Full SAF | M73: 1 | O73: Lattice Tower | P73: Type - GTE - 2 | Q73: 19 | T73: 0 | U73: 0 | W73: 1 | X73: 203725 | Y73: 385420 | Z73: 54.716795 | AA73: -7.942951 | AB73: 46486.958 | AD73: 40057 | AF73: 43709 | AG73: DEL-6 A-E | AH73: 0 | AI73: country | AJ73: 93 | AK73: hill | AL73: 26.5 | AM73: Pad | AN73: Concrete Grade: Main Rebar: Corner/Secondary Rebar: Concrete Quantity (m3): Reinforcement Quantity (kg): | AO73: 0 | AP73: Obelisk | AQ73: 0 | AR73: 0 | AS73: -168.5 | AT73: 0 | AU73: 3433.3117 | AV73: -3680.9267 | AW73: -634.12222 | AX73: 0.79 | AY73: 0.21 | AZ73: Green
A74: TCE2003 | B74: Structure | C74: TCE2003-T01 | E74: Schedule 2 | F74: Active | G74: Towercom | H74: Towercom | I74: Towercom | J74: 1 | K74: Full SRF | L74: Full SAF | M74: 1 | O74: Lattice Tower | P74: Type - EVE - 6 | Q74: 21 | T74: 1 | U74: 0 | W74: 1 | X74: 128588 | Y74: 209187 | Z74: 53.128756 | AA74: -9.067557 | AB74: 46403 | AG74: FL122 | AH74: 0 | AI74: country | AJ74: 94 | AK74: base of hill | AL74: 26 | AM74: Slab | AN74: Concrete Grade: Main Rebar: Corner/Secondary Rebar: Concrete Quantity (m3): Reinforcement Quantity (kg): | AO74: 0 | AP74: KTL | AQ74: 0 | AR74: 0 | AS74: -173 | AT74: 0 | AU74: 3482.4607 | AV74: -3735.7267 | AW74: -643.89556 | AX74: 0.89 | AY74: 0.11 | AZ74: Amber
A75: TDU5035 | B75: Structure | C75: TDU5035-T01 | E75: MLA | F75: Active | G75: Vodafone | H75: Towercom | I75: Vodafone | J75: 1 | K75: Full SRF | L75: Full SAF | M75: 1 | O75: Lattice Tower | P75: Eve Type 5 | Q75: 30 | S75: 10 | T75: 1 | U75: 1 | V75: Latchway | W75: 0 | X75: 320335 | Y75: 239833 | Z75: 53.39517 | AA75: -6.19178 | AB75: 46603.958 | AD75: 45458.958 | AF75: 49110.958 | AG75: DEL-6 A-E | AH75: 1993-1996 | AI75: town | AJ75: 95 | AK75: Flat | AL75: 25 | AM75: Pile | AN75: Concrete Grade: Main Rebar: Corner/Secondary Rebar: Concrete Quantity (m3): Reinforcement Quantity (kg): | AO75: 7.4m x 7.4m | AP75: Obelisk | AQ75: 0 | AR75: Headframe | AS75: -177.5 | AT75: 0 | AU75: 3531.6097 | AV75: -3790.5267 | AW75: -653.66889 | AX75: 0.98 | AY75: 0.02 | AZ75: Amber
A76: TMO2004 | B76: Structure | C76: TMO2004-T01 | E76: Schedule 2 | F76: Active | G76: Towercom | H76: Towercom | I76: Towercom | J76: 1 | K76: Full SRF | L76: Full SAF | M76: 1 | O76: Lattice Tower | P76: Type - EVE - 2 | Q76: 20 | T76: 1 | U76: 0 | W76: 1 | X76: 70747 | Y76: 332086 | Z76: 54.221392 | AA76: -9.982388 | AB76: 46540.958 | AG76: FL123 | AH76: 0 | AI76: town | AJ76: 96 | AK76: flat | AL76: 27 | AM76: Pad | AN76: Concrete Grade: Main Rebar: Corner/Secondary Rebar: Concrete Quantity (m3): Reinforcement Quantity (kg): | AO76: 0 | AP76: KTL | AQ76: 0 | AR76: 0 | AS76: -182 | AT76: 0 | AU76: 3580.7587 | AV76: -3845.3267 | AW76: -663.44222 | AX76: 0.8 | AY76: 0.2 | AZ76: Green
A77: TCN5036 | B77: Structure | C77: TCN5036-T01 | E77: MLA | F77: Retired | G77: Vodafone | H77: Towercom | I77: Vodafone | J77: 0 | K77: No SRF | L77: TL Only | M77: 0 | T77: 0 | U77: 1 | V77: Metreel | W77: 1 | X77: 236441 | Y77: 316909 | Z77: 54.10005 | AA77: -7.44372 | AB77: 46400 | AG77: DEL-6 A-E | AH77: #N/A | AI77: #N/A | AJ77: 97 | AK77: #N/A | AL77: #N/A | AM77: Slab | AN77: Concrete Grade: Main Rebar: Corner/Secondary Rebar: Concrete Quantity (m3): Reinforcement Quantity (kg): | AO77: #N/A | AP77: Obelisk | AQ77: #N/A | AR77: #N/A | AS77: -186.5 | AT77: #N/A | AU77: 3629.9077 | AV77: -3900.1267 | AW77: -673.21556 | AX77: #N/A | AY77: #N/A | AZ77: #N/A
A78: TCN5036 | B78: Structure | C78: TCN5036-T02 | E78: MLA | F78: Active | G78: Vodafone | H78: Towercom | I78: Vodafone | J78: 1 | K78: Full SRF | L78: Full SAF | M78: 1 | T78: 0 | U78: 1 | V78: Metreel | W78: 1 | X78: 236441 | Y78: 316909 | Z78: 54.10005 | AA78: -7.44372 | AB78: 46400 | AG78: FL124 | AH78: #N/A | AI78: #N/A | AJ78: 98 | AK78: #N/A | AL78: #N/A | AM78: Pile | AN78: Concrete Grade: Main Rebar: Corner/Secondary Rebar: Concrete Quantity (m3): Reinforcement Quantity (kg): | AO78: #N/A | AP78: KTL | AQ78: #N/A | AR78: #N/A | AS78: -191 | AT78: #N/A | AU78: 3679.0567 | AV78: -3954.9267 | AW78: -682.98889 | AX78: #N/A | AY78: #N/A | AZ78: #N/A
A79: TCE1006 | B79: Structure | C79: TCE1006-T01 | E79: Schedule 1 | F79: Active | G79: Towercom | H79: Towercom | I79: Towercom | J79: 1 | K79: Full SRF | L79: Full SAF | M79: 1 | O79: Lattice Tower | P79: Type - EVE - 3 | Q79: 42 | T79: 0 | U79: 0 | W79: 1 | X79: 121399 | Y79: 171285 | Z79: 52.787208 | AA79: -9.165739 | AB79: 46047 | AG79: DEL-6 A-E | AH79: 0 | AI79: country | AJ79: 99 | AK79: flat | AL79: 26 | AM79: Pad | AN79: Concrete Grade: Main Rebar: Corner/Secondary Rebar: Concrete Quantity (m3): Reinforcement Quantity (kg): | AO79: 0 | AP79: Obelisk | AQ79: 0 | AR79: 0 | AS79: -195.5 | AT79: 0 | AU79: 3728.2057 | AV79: -4009.7267 | AW79: -692.76222 | AX79: 0.95 | AY79: 0.05 | AZ79: Amber
A80: TMH5037 | B80: Structure | C80: TMH5037-T01 | E80: MLA | F80: Retired | G80: Vodafone | H80: Towercom | I80: Vodafone | J80: 0 | K80: No SRF | L80: TL Only | M80: 0 | T80: 0 | U80: 1 | V80: Latchway | W80: 1 | X80: 315928 | Y80: 273535 | Z80: 53.69881 | AA80: -6.24551 | AB80: 46660.958 | AG80: FL125 | AH80: #N/A | AI80: #N/A | AJ80: 100 | AK80: #N/A | AL80: #N/A | AM80: Slab | AN80: Concrete Grade: Main Rebar: Corner/Secondary Rebar: Concrete Quantity (m3): Reinforcement Quantity (kg): | AO80: #N/A | AP80: KTL | AQ80: #N/A | AR80: #N/A | AS80: -200 | AT80: #N/A | AU80: 3777.3547 | AV80: -4064.5267 | AW80: -702.53556 | AX80: #N/A | AY80: #N/A | AZ80: #N/A
A81: TMH5037 | B81: Structure | C81: TMH5037-T02 | E81: MLA | F81: Active | G81: Vodafone | H81: Towercom | I81: Vodafone | J81: 1 | K81: Full SRF | L81: Full SAF | M81: 1 | T81: 0 | U81: 1 | V81: Latchway | W81: 1 | X81: 315928 | Y81: 273535 | Z81: 53.69881 | AA81: -6.24551 | AB81: 46660.958 | AG81: DEL-6 A-E | AH81: #N/A | AI81: #N/A | AJ81: 101 | AK81: #N/A | AL81: #N/A | AM81: Pile | AN81: Concrete Grade: Main Rebar: Corner/Secondary Rebar: Concrete Quantity (m3): Reinforcement Quantity (kg): | AO81: #N/A | AP81: Obelisk | AQ81: #N/A | AR81: #N/A | AS81: -204.5 | AT81: #N/A | AU81: 3826.5037 | AV81: -4119.3267 | AW81: -712.30889 | AX81: #N/A | AY81: #N/A | AZ81: #N/A
A82: TLH5039 | B82: Structure | C82: TLH5039-T01 | E82: MLA | F82: Retired | G82: Vodafone | H82: Towercom | I82: Vodafone | J82: 0 | K82: No SRF | L82: TL Only | M82: 0 | T82: 0 | U82: 0 | W82: 0 | X82: 305745 | Y82: 303574 | Z82: 53.97074 | AA82: -6.38931 | AB82: 45786.958 | AG82: FL126 | AH82: #N/A | AI82: #N/A | AJ82: 102 | AK82: #N/A | AL82: #N/A | AM82: Pad | AN82: Concrete Grade: Main Rebar: Corner/Secondary Rebar: Concrete Quantity (m3): Reinforcement Quantity (kg): | AO82: #N/A | AP82: KTL | AQ82: #N/A | AR82: #N/A | AS82: -209 | AT82: #N/A | AU82: 3875.6527 | AV82: -4174.1267 | AW82: -722.08222 | AX82: #N/A | AY82: #N/A | AZ82: #N/A
A83: TLH5039 | B83: Structure | C83: TLH5039-T02 | D83: TLH7307 | E83: Option A (EED) | F83: Option | G83: Eircom | H83: Towercom | I83: Eircom | J83: 1 | K83: Full SRF | L83: Full SAF | M83: 1 | T83: 0 | U83: 0 | W83: 0 | X83: 305745 | Y83: 303574 | Z83: 53.97074 | AA83: -6.38931 | AB83: 45786.958 | AG83: DEL-6 A-E | AH83: #N/A | AI83: #N/A | AJ83: 103 | AK83: #N/A | AL83: #N/A | AM83: Slab | AN83: Concrete Grade: Main Rebar: Corner/Secondary Rebar: Concrete Quantity (m3): Reinforcement Quantity (kg): | AO83: #N/A | AP83: Obelisk | AQ83: #N/A | AR83: #N/A | AS83: -213.5 | AT83: #N/A | AU83: 3924.8017 | AV83: -4228.9267 | AW83: -731.85556 | AX83: #N/A | AY83: #N/A | AZ83: #N/A
A84: TMO6349 | B84: Structure | C84: TMO6349-T01 | D84: TMO6049 | E84: Schedule 3a | F84: To be Retired | G84: Towercom | H84: Towercom | I84: Towercom | J84: 0 | K84: Remove Only | L84: Full SAF | M84: 1 | T84: 0 | U84: 1 | V84: Metreel | W84: 0 | X84: 62869 | Y84: 322412 | Z84: 54.13249 | AA84: -10.09868 | AB84: 46186.958 | AG84: FL127 | AH84: #N/A | AI84: #N/A | AJ84: 104 | AK84: #N/A | AL84: #N/A | AM84: Pile | AN84: Concrete Grade: Main Rebar: Corner/Secondary Rebar: Concrete Quantity (m3): Reinforcement Quantity (kg): | AO84: #N/A | AP84: KTL | AQ84: #N/A | AR84: #N/A | AS84: -218 | AT84: #N/A | AU84: 3973.9507 | AV84: -4283.7267 | AW84: -741.62889 | AX84: #N/A | AY84: #N/A | AZ84: #N/A
A85: TMO6349 | B85: Structure | C85: TMO6349-T02 | D85: TMO6049 | E85: Schedule 3a | F85: Active | G85: Towercom | H85: Towercom | I85: Towercom | J85: 1 | K85: Full SRF | L85: Full SAF | M85: 1 | T85: 0 | U85: 1 | V85: Metreel | W85: 0 | X85: 62869 | Y85: 322412 | Z85: 54.13249 | AA85: -10.09868 | AB85: 46186.958 | AG85: DEL-6 A-E | AH85: #N/A | AI85: #N/A | AJ85: 105 | AK85: #N/A | AL85: #N/A | AM85: Pad | AN85: Concrete Grade: Main Rebar: Corner/Secondary Rebar: Concrete Quantity (m3): Reinforcement Quantity (kg): | AO85: #N/A | AP85: Obelisk | AQ85: #N/A | AR85: #N/A | AS85: -222.5 | AT85: #N/A | AU85: 4023.0997 | AV85: -4338.5267 | AW85: -751.40222 | AX85: #N/A | AY85: #N/A | AZ85: #N/A
A86: TWX4003 | B86: Structure | C86: TWX4003-T01 | E86: Schedule 3b | F86: To be Retired | G86: Towercom | H86: Towercom | I86: Towercom | J86: 0 | K86: Remove Only | L86: Full SAF | M86: 1 | T86: 0 | U86: 1 | V86: Metreel | W86: 1 | X86: 312091 | Y86: 133687 | Z86: 52.44359 | AA86: -6.35227 | AB86: 46121.958 | AG86: FL128 | AH86: #N/A | AI86: #N/A | AJ86: 106 | AK86: #N/A | AL86: #N/A | AM86: Slab | AN86: Concrete Grade: Main Rebar: Corner/Secondary Rebar: Concrete Quantity (m3): Reinforcement Quantity (kg): | AO86: #N/A | AP86: KTL | AQ86: #N/A | AR86: #N/A | AS86: -227 | AT86: #N/A | AU86: 4072.2487 | AV86: -4393.3267 | AW86: -761.17556 | AX86: #N/A | AY86: #N/A | AZ86: #N/A
A87: TWX4003 | B87: Structure | C87: TWX4003-T02 | E87: Schedule 3b | F87: Active | G87: Towercom | H87: Towercom | I87: Towercom | J87: 1 | K87: Full SRF | L87: Full SAF | M87: 1 | T87: 0 | U87: 1 | V87: Metreel | W87: 1 | X87: 312091 | Y87: 133687 | Z87: 52.44359 | AA87: -6.35227 | AB87: 46121.958 | AG87: DEL-6 A-E | AH87: #N/A | AI87: #N/A | AJ87: 107 | AK87: #N/A | AL87: #N/A | AM87: Pile | AN87: Concrete Grade: Main Rebar: Corner/Secondary Rebar: Concrete Quantity (m3): Reinforcement Quantity (kg): | AO87: #N/A | AP87: Obelisk | AQ87: #N/A | AR87: #N/A | AS87: -231.5 | AT87: #N/A | AU87: 4121.3977 | AV87: -4448.1267 | AW87: -770.94889 | AX87: #N/A | AY87: #N/A | AZ87: #N/A
A88: TDU5040 | B88: Structure | C88: TDU5040-T01 | E88: MLA | F88: Retired | G88: Vodafone | H88: Towercom | I88: Vodafone | J88: 0 | K88: No SRF | L88: TL Only | M88: 0 | T88: 0 | U88: 0 | W88: 0 | X88: 307234 | Y88: 239312 | Z88: 53.393306 | AA88: -6.388812 | AB88: 45520.958 | AG88: FL129 | AH88: #N/A | AI88: #N/A | AJ88: 108 | AK88: #N/A | AL88: #N/A | AM88: Pad | AN88: Concrete Grade: Main Rebar: Corner/Secondary Rebar: Concrete Quantity (m3): Reinforcement Quantity (kg): | AO88: #N/A | AP88: KTL | AQ88: #N/A | AR88: #N/A | AS88: -236 | AT88: #N/A | AU88: 4170.5467 | AV88: -4502.9267 | AW88: -780.72222 | AX88: #N/A | AY88: #N/A | AZ88: #N/A
A89: TDU5040 | B89: Structure | C89: TDU5040-T02 | D89: TDU7308 | E89: Option A (EED) | F89: Active | G89: Eircom | H89: Towercom | I89: Eircom | J89: 1 | K89: Full SRF | L89: Full SAF | M89: 1 | T89: 0 | U89: 0 | W89: 0 | X89: 307234 | Y89: 239312 | Z89: 53.393306 | AA89: -6.388812 | AB89: 45520.958 | AG89: DEL-6 A-E | AH89: #N/A | AI89: #N/A | AJ89: 109 | AK89: #N/A | AL89: #N/A | AM89: Slab | AN89: Concrete Grade: Main Rebar: Corner/Secondary Rebar: Concrete Quantity (m3): Reinforcement Quantity (kg): | AO89: #N/A | AP89: Obelisk | AQ89: #N/A | AR89: #N/A | AS89: -240.5 | AT89: #N/A | AU89: 4219.6957 | AV89: -4557.7267 | AW89: -790.49556 | AX89: #N/A | AY89: #N/A | AZ89: #N/A
A90: TCK5041 | B90: Structure | C90: TCK5041-R01 | E90: MLA | F90: Retired | G90: Vodafone | H90: Towercom | I90: Vodafone | J90: 0 | K90: No SRF | L90: TL Only | M90: 0 | S90: 5 | T90: 0 | U90: 0 | W90: 0 | X90: 161501 | Y90: 75594 | Z90: 51.93168 | AA90: -8.56043 | AG90: FL130 | AH90: #N/A | AI90: #N/A | AJ90: 110 | AK90: #N/A | AL90: #N/A | AM90: Pile | AN90: Concrete Grade: Main Rebar: Corner/Secondary Rebar: Concrete Quantity (m3): Reinforcement Quantity (kg): | AO90: #N/A | AP90: KTL | AQ90: #N/A | AR90: #N/A | AS90: -245 | AT90: #N/A | AU90: 4268.8447 | AV90: -4612.5267 | AW90: -800.26889 | AX90: #N/A | AY90: #N/A | AZ90: #N/A
A91: TCK5041 | B91: Structure | C91: TCK5041-T01 | D91: TCK7309 | E91: Option A (EED) | F91: Active | G91: Eircom | H91: Towercom | I91: Eircom | J91: 1 | K91: Full SRF | L91: Full SAF | M91: 1 | S91: 5 | T91: 0 | U91: 0 | W91: 0 | X91: 161501 | Y91: 75594 | Z91: 51.93168 | AA91: -8.56043 | AG91: DEL-6 A-E | AH91: #N/A | AI91: #N/A | AJ91: 111 | AK91: #N/A | AL91: #N/A | AM91: Pad | AN91: Concrete Grade: Main Rebar: Corner/Secondary Rebar: Concrete Quantity (m3): Reinforcement Quantity (kg): | AO91: #N/A | AP91: Obelisk | AQ91: #N/A | AR91: #N/A | AS91: -249.5 | AT91: #N/A | AU91: 4317.9937 | AV91: -4667.3267 | AW91: -810.04222 | AX91: #N/A | AY91: #N/A | AZ91: #N/A
A92: TTP6063 | B92: Structure | C92: TTP6063-T01 | E92: Schedule 3f | F92: Retired | G92: Towercom | H92: Towercom | I92: Towercom | J92: 0 | K92: No SRF | L92: TL Only | M92: 0 | T92: 0 | U92: 1 | V92: Metreel | W92: 1 | X92: 191632 | Y92: 193682 | Z92: 52.99412 | AA92: -8.12535 | AB92: 46547.958 | AG92: FL131 | AH92: #N/A | AI92: #N/A | AJ92: 112 | AK92: #N/A | AL92: #N/A | AM92: Slab | AN92: Concrete Grade: Main Rebar: Corner/Secondary Rebar: Concrete Quantity (m3): Reinforcement Quantity (kg): | AO92: #N/A | AP92: KTL | AQ92: #N/A | AR92: #N/A | AS92: -254 | AT92: #N/A | AU92: 4367.1427 | AV92: -4722.1267 | AW92: -819.81556 | AX92: #N/A | AY92: #N/A | AZ92: #N/A
A93: TTP6063 | B93: Structure | C93: TTP6063-T02 | E93: Schedule 3f | F93: Active | G93: Towercom | H93: Towercom | I93: Towercom | J93: 1 | K93: Full SRF | L93: Full SAF | M93: 1 | T93: 1 | U93: 1 | V93: Metreel | W93: 1 | X93: 191632 | Y93: 193682 | Z93: 52.99412 | AA93: -8.12535 | AB93: 46547.958 | AG93: DEL-6 A-E | AH93: #N/A | AI93: #N/A | AJ93: 113 | AK93: #N/A | AL93: #N/A | AM93: Pile | AN93: Concrete Grade: Main Rebar: Corner/Secondary Rebar: Concrete Quantity (m3): Reinforcement Quantity (kg): | AO93: #N/A | AP93: Obelisk | AQ93: #N/A | AR93: #N/A | AS93: -258.5 | AT93: #N/A | AU93: 4416.2917 | AV93: -4776.9267 | AW93: -829.58889 | AX93: #N/A | AY93: #N/A | AZ93: #N/A
A94: TRN7007 | B94: Structure | C94: TRN7007-R01 | D94: TRN5042 | E94: Non MLA | F94: To be Retired | G94: Vodafone | H94: Towercom | I94: Vodafone | J94: 0 | K94: Remove Only | L94: Full SAF | M94: 1 | T94: 0 | U94: 1 | V94: Latchway | W94: 1 | X94: 180107 | Y94: 302772 | Z94: 53.97395 | AA94: -8.3039 | AB94: 46477.958 | AG94: FL132 | AH94: #N/A | AI94: #N/A | AJ94: 114 | AK94: #N/A | AL94: #N/A | AM94: Pad | AN94: Concrete Grade: Main Rebar: Corner/Secondary Rebar: Concrete Quantity (m3): Reinforcement Quantity (kg): | AO94: #N/A | AP94: KTL | AQ94: #N/A | AR94: #N/A | AS94: -263 | AT94: #N/A | AU94: 4465.4407 | AV94: -4831.7267 | AW94: -839.36222 | AX94: #N/A | AY94: #N/A | AZ94: #N/A
A95: TRN7007 | B95: Structure | C95: TRN7007-T01 | D95: TRN5042 | E95: Non MLA | F95: Active | G95: Vodafone | H95: Towercom | I95: Vodafone | J95: 1 | K95: Full SRF | L95: Full SAF | M95: 1 | T95: 1 | U95: 1 | V95: Latchway | W95: 1 | X95: 180107 | Y95: 302772 | Z95: 53.97395 | AA95: -8.3039 | AB95: 46477.958 | AG95: DEL-6 A-E | AH95: #N/A | AI95: #N/A | AJ95: 115 | AK95: #N/A | AL95: #N/A | AM95: Slab | AN95: Concrete Grade: Main Rebar: Corner/Secondary Rebar: Concrete Quantity (m3): Reinforcement Quantity (kg): | AO95: #N/A | AP95: Obelisk | AQ95: #N/A | AR95: #N/A | AS95: -267.5 | AT95: #N/A | AU95: 4514.5897 | AV95: -4886.5267 | AW95: -849.13556 | AX95: #N/A | AY95: #N/A | AZ95: #N/A
A96: TOY2005 | B96: Structure | C96: TOY2005-T01 | D96: TKE2005 | E96: Schedule 2 | F96: UTS | G96: Towercom | H96: Towercom | I96: Towercom | J96: 1 | K96: Full SRF | L96: Full SAF | M96: 1 | T96: 0 | U96: 0 | W96: 0 | X96: 260625 | Y96: 217941 | Z96: 53.208708 | AA96: -7.093377 | AB96: 46458 | AG96: FL133 | AH96: #N/A | AI96: #N/A | AJ96: 116 | AK96: #N/A | AL96: #N/A | AM96: Pile | AN96: Concrete Grade: Main Rebar: Corner/Secondary Rebar: Concrete Quantity (m3): Reinforcement Quantity (kg): | AO96: #N/A | AP96: KTL | AQ96: #N/A | AR96: #N/A | AS96: -272 | AT96: #N/A | AU96: 4563.7387 | AV96: -4941.3267 | AW96: -858.90889 | AX96: #N/A | AY96: #N/A | AZ96: #N/A
A97: TSO1007 | B97: Structure | C97: TSO1007-T01 | E97: Schedule 1 | F97: Active | G97: Towercom | H97: Towercom | I97: Towercom | J97: 1 | K97: Full SRF | L97: Full SAF | M97: 1 | O97: Lattice Tower | P97: Type - ARU - 1 | Q97: 63 | T97: 1 | U97: 0 | W97: 1 | X97: 158235 | Y97: 326630 | Z97: 54.186974 | AA97: -8.640495 | AB97: 45952.958 | AG97: DEL-6 A-E | AH97: 0 | AI97: country | AJ97: 117 | AK97: hill | AL97: 26 | AM97: Pad | AN97: Concrete Grade: Main Rebar: Corner/Secondary Rebar: Concrete Quantity (m3): Reinforcement Quantity (kg): | AO97: 0 | AP97: Obelisk | AQ97: 0 | AR97: 0 | AS97: -276.5 | AT97: 0 | AU97: 4612.8877 | AV97: -4996.1267 | AW97: -868.68222 | AX97: 0.7 | AY97: 0.3 | AZ97: Green
A98: TKY6030 | B98: Structure | C98: TKY6030-T01 | E98: Schedule 3f | F98: Active | G98: Towercom | H98: Towercom | I98: Towercom | J98: 1 | K98: Full SRF | L98: Full SAF | M98: 1 | O98: Monopole | P98: Del_4 - 25 | Q98: 25 | T98: 1 | U98: 1 | V98: Metreel | W98: 1 | X98: 113297 | Y98: 118691 | Z98: 52.31347 | AA98: -9.27207 | AB98: 46126.958 | AG98: FL134 | AH98: 2008-2010 | AI98: town | AJ98: 118 | AK98: valley | AL98: 26.5 | AM98: Slab | AN98: Concrete Grade: Main Rebar: Corner/Secondary Rebar: Concrete Quantity (m3): Reinforcement Quantity (kg): | AO98: 4.7 x 4.7 x 1.25 | AP98: KTL | AQ98: 0 | AR98: 0 | AS98: -281 | AT98: 0 | AU98: 4662.0367 | AV98: -5050.9267 | AW98: -878.45556 | AX98: 0.45 | AY98: 0.55 | AZ98: green
A99: TDL2006 | B99: Structure | C99: TDL2006-T01 | E99: Schedule 2 | F99: Active | G99: Towercom | H99: Towercom | I99: Towercom | J99: 1 | K99: Full SRF | L99: Full SAF | M99: 1 | O99: Lattice Tower | P99: Type - EVE - 3 | Q99: 20 | T99: 1 | U99: 0 | W99: 1 | X99: 181678 | Y99: 424468 | Z99: 55.06722 | AA99: -8.28753 | AB99: 46197.958 | AG99: DEL-6 A-E | AH99: 0 | AI99: town | AJ99: 119 | AK99: hill | AL99: 27 | AM99: Pile | AN99: Concrete Grade: Main Rebar: Corner/Secondary Rebar: Concrete Quantity (m3): Reinforcement Quantity (kg): | AO99: 0 | AP99: Obelisk | AQ99: 0 | AR99: 0 | AS99: -285.5 | AT99: 0 | AU99: 4711.1857 | AV99: -5105.7267 | AW99: -888.22889 | AX99: 0.65 | AY99: 0.35 | AZ99: Green
A100: TDL5043 | B100: Structure | C100: TDL5043-T01 | E100: MLA | F100: Retired | G100: Vodafone | H100: Towercom | I100: Vodafone | J100: 0 | K100: No SRF | L100: TL Only | M100: 0 | T100: 0 | U100: 0 | W100: 1 | X100: 182133 | Y100: 358808 | Z100: 54.47743 | AA100: -8.27636 | AG100: FL135 | AH100: #N/A | AI100: #N/A | AJ100: 120 | AK100: #N/A | AL100: #N/A | AM100: Pad | AN100: Concrete Grade: Main Rebar: Corner/Secondary Rebar: Concrete Quantity (m3): Reinforcement Quantity (kg): | AO100: #N/A | AP100: KTL | AQ100: #N/A | AR100: #N/A | AS100: -290 | AT100: #N/A | AU100: 4760.3347 | AV100: -5160.5267 | AW100: -898.00222 | AX100: #N/A | AY100: #N/A | AZ100: #N/A
A101: TDL5043 | B101: Structure | C101: TDL5043-T02 | D101: TDL7310 | E101: Option A (EED) | F101: Active | G101: Eircom | H101: Towercom | I101: Eircom | J101: 1 | K101: Full SRF | L101: Full SAF | M101: 1 | T101: 0 | U101: 0 | W101: 1 | X101: 182133 | Y101: 358808 | Z101: 54.47743 | AA101: -8.27636 | AG101: DEL-6 A-E | AH101: #N/A | AI101: #N/A | AJ101: 121 | AK101: #N/A | AL101: #N/A | AM101: Slab | AN101: Concrete Grade: Main Rebar: Corner/Secondary Rebar: Concrete Quantity (m3): Reinforcement Quantity (kg): | AO101: #N/A | AP101: Obelisk | AQ101: #N/A | AR101: #N/A | AS101: -294.5 | AT101: #N/A | AU101: 4809.4837 | AV101: -5215.3267 | AW101: -907.77556 | AX101: #N/A | AY101: #N/A | AZ101: #N/A
...

Sheet CUSTOMER PRESENCE
A1: Site | B1: Customer | C1: Customer Site ID | D1: Presence Type | E1: check
A2: TCK5002 | B2: 72 | C2: CKAHA | D2: Installed | E2: =MATCH(A2,'SITES TEST DATA'!A:A,0) -> 2
A3: TGY5003 | B3: 72 | C3: GYADN | D3: Licenced | E3: =MATCH(A3,'SITES TEST DATA'!A:A,0) -> 4
A4: TWW5005 | B4: 72 | C4: WWAKW | D4: Installed | E4: =MATCH(A4,'SITES TEST DATA'!A:A,0) -> 6
A5: TWW5004 | B5: 72 | C5: WW004 | D5: Licenced | E5: =MATCH(A5,'SITES TEST DATA'!A:A,0) -> 7
A6: TCN5006 | B6: 72 | C6: CN027 | D6: Installed | E6: =MATCH(A6,'SITES TEST DATA'!A:A,0) -> 9
A7: TGY5008 | B7: 72 | C7: GYANR | D7: Licenced | E7: =MATCH(A7,'SITES TEST DATA'!A:A,0) -> 11
A8: TWH4001 | B8: 72 | C8: WH013 | D8: Installed | E8: =MATCH(A8,'SITES TEST DATA'!A:A,0) -> 12
A9: TLK5009 | B9: 72 | C9: LKATD | D9: Licenced | E9: =MATCH(A9,'SITES TEST DATA'!A:A,0) -> 13
A10: TMO5012 | B10: 72 | C10: MO056 | D10: Installed | E10: =MATCH(A10,'SITES TEST DATA'!A:A,0) -> 18
A11: TMO1001 | B11: 72 | C11: MOBLA | D11: Licenced | E11: =MATCH(A11,'SITES TEST DATA'!A:A,0) -> 20
A12: TWX5030 | B12: 72 | C12: WX029 | D12: Installed | E12: =MATCH(A12,'SITES TEST DATA'!A:A,0) -> 21
A13: TGY5016 | B13: 72 | C13: GYBSE | D13: Licenced | E13: =MATCH(A13,'SITES TEST DATA'!A:A,0) -> 23
... A496: TGY6327 | B496: 63 | C496: EE875 | D496: Licenced | E496: =MATCH(A496,'SITES TEST DATA'!A:A,0) -> 359

Sheet LOCKS TEST DATA
A1: Lock ID | B1: Site | C1: Lock Location Category | D1: Secured Infrastructure | E1: Comment | F1: Lock Type | G1: Lock Config | H1: Locken Lock Name | I1: Locken Access Point Reference | J1: Other Reference
A2: LOCK-00001 | B2: TCK5154 | C2: Anti-Climb | D2: TCK5154-T01 | F2: Locken | G2: Euro Cylinder | H2: aljcbqwdjsb | I2: G9L-1056 0000Z_131
A3: LOCK-00002 | B3: TKY7009 | C3: Anti-Climb | D3: TKY7009-T01 | F3: Locken | G3: Long Padlock | H3: aljcbqwdjsb | I3: G9L-1056 0000Z_132
A4: LOCK-00003 | B4: TKE1019 | C4: Anti-Climb | D4: TKE1019-T01 | F4: Locken | G4: Short Padlock | H4: aljcbqwdjsb | I4: G9L-1056 0000Z_133
A5: LOCK-00004 | B5: TCK5154 | C5: Gate | F5: Locken | G5: Key Safe | H5: aljcbqwdjsb | I5: G9L-1056 0000Z_134
A6: LOCK-00005 | B6: TCK5018 | C6: Anti-Climb | D6: TCK5018-T01 | F6: Locken | G6: Euro Cylinder | H6: aljcbqwdjsb | I6: G9L-1056 0000Z_135
A7: LOCK-00006 | B7: TDU5113 | C7: Anti-Climb | D7: TDU5113-T01 | F7: Locken | G7: Long Padlock | H7: aljcbqwdjsb | I7: G9L-1056 0000Z_136
A8: LOCK-00007 | B8: TWH6066 | C8: Anti-Climb | D8: TWH6066-T01 | F8: Locken | G8: Short Padlock | H8: aljcbqwdjsb | I8: G9L-1056 0000Z_138
A9: LOCK-00008 | B9: TWH6066 | C9: Gate | F9: Locken | G9: Key Safe | H9: aljcbqwdjsb | I9: G9L-1056 0000Z_139
A10: LOCK-00009 | B10: TLK7036 | C10: Anti-Climb | D10: TLK7036-T01 | F10: Locken | G10: Euro Cylinder | H10: aljcbqwdjsb | I10: G9L-1056 0000Z_141
A11: LOCK-00010 | B11: TGY6324 | C11: Gate | F11: Locken | G11: Long Padlock | H11: aljcbqwdjsb | I11: G9L-1056 0000Z_142
A12: LOCK-00011 | B12: TLK5001 | C12: Gate | F12: Locken | G12: Short Padlock | H12: aljcbqwdjsb | I12: G9L-1056 0000Z_143
A13: LOCK-00012 | B13: TKY7041 | C13: Anti-Climb | D13: TKY7041-T01 | F13: Locken | G13: Key Safe | H13: aljcbqwdjsb | I13: G9L-1056 0000Z_128
A14: LOCK-00013 | B14: TKY7041 | C14: Gate | F14: Locken | G14: Euro Cylinder | H14: aljcbqwdjsb | I14: G9L-1056 0000Z_129
A15: LOCK-00014 | B15: TDU7034 | C15: Gate | F15: Locken | G15: Long Padlock | H15: aljcbqwdjsb | I15: G9L-1056 0000Z_130
A16: LOCK-00015 | B16: TLK5001 | C16: Anti-Climb | D16: TLK5001-T01 | F16: Locken | G16: Short Padlock | H16: aljcbqwdjsb | I16: G9L-1056 0000Z_144
A17: LOCK-00016 | B17: TLK5137 | C17: Anti-Climb | D17: TLK5137-T01 | F17: Locken | G17: Key Safe | H17: aljcbqwdjsb | I17: G9L-1056 0000Z_145
A18: LOCK-00017 | B18: TCK5097 | C18: Anti-Climb | D18: TCK5097-T01 | F18: Locken | G18: Euro Cylinder | H18: aljcbqwdjsb | I18: G9L-1056 0000Z_146
A19: LOCK-00018 | B19: TLK5137 | C19: Gate | F19: Locken | G19: Long Padlock | H19: aljcbqwdjsb | I19: G9L-1056 0000Z_147
A20: LOCK-00019 | B20: TKK5132 | C20: Gate | F20: Locken | G20: Short Padlock | H20: aljcbqwdjsb | I20: G9L-1056 0000Z_148
A21: LOCK-00020 | B21: TKK5132 | C21: Gate | F21: Locken | G21: Key Safe | H21: aljcbqwdjsb | I21: G9L-1056 0000Z_149
A22: LOCK-00021 | B22: TKK5132 | C22: Anti-Climb | D22: TKK5132-T01 | F22: Locken | G22: Euro Cylinder | H22: aljcbqwdjsb | I22: G9L-1056 0000Z_150
A23: LOCK-00022 | B23: TLS2029 | C23: Gate | F23: Locken | G23: Long Padlock | H23: aljcbqwdjsb | I23: G9L-1056 0000Z_151
A24: LOCK-00023 | B24: TWX4003 | C24: Gate | F24: Locken | G24: Short Padlock | H24: aljcbqwdjsb | I24: G9L-1056 0000Z_152
A25: LOCK-00024 | B25: TTP1021 | C25: Gate | F25: Locken | G25: Key Safe | H25: aljcbqwdjsb | I25: G9L-1056 0000Z_153
A26: LOCK-00025 | B26: TTP1021 | C26: Anti-Climb | D26: TTP1021-T01 | F26: Locken | G26: Euro Cylinder | H26: aljcbqwdjsb | I26: G9L-1056 0000Z_154
A27: LOCK-00026 | B27: TTP1021 | C27: Anti-Climb | D27: TTP1021-T01 | F27: Locken | G27: Long Padlock | H27: aljcbqwdjsb | I27: G9L-1056 0000Z_155
A28: LOCK-00028 | B28: TWX2018 | C28: Gate | F28: Locken | G28: Short Padlock | H28: aljcbqwdjsb | I28: G9L-1056 0000Z_158
A29: LOCK-00029 | B29: TWX2018 | C29: Gate | F29: Locken | G29: Key Safe | H29: aljcbqwdjsb | I29: G9L-1056 0000Z_159
A30: LOCK-00030 | B30: TWX2018 | C30: Gate | F30: Locken | G30: Euro Cylinder | H30: aljcbqwdjsb | I30: G9L-1056 0000Z_160
A31: LOCK-00031 | B31: TWD8204 | C31: Anti-Climb | D31: TWD8204-T01 | F31: Locken | G31: Long Padlock | H31: aljcbqwdjsb | I31: G9L-1056 0000Z_161
A32: LOCK-00032 | B32: TWD8204 | C32: Gate | F32: Locken | G32: Short Padlock | H32: aljcbqwdjsb | I32: G9L-1056 0000Z_162
A33: LOCK-00033 | B33: TLS1010 | C33: Accomodation | D33: TLS1010-A01 | F33: Locken | G33: Key Safe | H33: aljcbqwdjsb | I33: G9L-1056 0000Z_163
A34: LOCK-00034 | B34: TLS1010 | C34: Gate | F34: Locken | G34: Euro Cylinder | H34: aljcbqwdjsb | I34: G9L-1056 0000Z_164
A35: LOCK-00035 | B35: TLS1010 | C35: Accomodation | D35: TLS1010-A01 | F35: Locken | G35: Long Padlock | H35: aljcbqwdjsb | I35: G9L-1056 0000Z_165
A36: LOCK-00036 | B36: TWX2037 | C36: Gate | F36: Locken | G36: Short Padlock | H36: aljcbqwdjsb | I36: G9L-1056 0000Z_166
A37: LOCK-00037 | B37: TWX2037 | C37: Gate | F37: Locken | G37: Key Safe | H37: aljcbqwdjsb | I37: G9L-1056 0000Z_167
A38: LOCK-00038 | B38: TRN6462 | C38: Gate | F38: Locken | G38: Euro Cylinder | H38: aljcbqwdjsb | I38: G9L-1056 0000Z_168
A39: LOCK-00039 | B39: TOY6059 | C39: Gate | F39: Locken | G39: Long Padlock | H39: aljcbqwdjsb | I39: G9L-1056 0000Z_169
A40: LOCK-00041 | B40: TDU2013 | C40: Accomodation | D40: TDU2013-A01 | F40: Locken | G40: Short Padlock | H40: aljcbqwdjsb | I40: G9L-1056 0000Z_399
A41: LOCK-00042 | B41: TGY1012 | C41: Accomodation | D41: TGY1012-A01 | F41: Locken | G41: Key Safe | H41: aljcbqwdjsb | I41: G9L-1056 0000Z_400
A42: LOCK-00043 | B42: TKY1031 | C42: Accomodation | D42: TKY1031-A01 | F42: Locken | G42: Euro Cylinder | H42: aljcbqwdjsb | I42: G9L-1056 0000Z_401
A43: LOCK-00044 | B43: TGY1030 | C43: Accomodation | D43: TGY1030-A01 | F43: Locken | G43: Long Padlock | H43: aljcbqwdjsb | I43: G9L-1056 0000Z_402
A44: LOCK-00045 | B44: TKE1009 | C44: Accomodation | D44: TKE1009-A01 | F44: Locken | G44: Short Padlock | H44: aljcbqwdjsb | I44: G9L-1056 0000Z_403
A45: LOCK-00046 | B45: TCK3002 | C45: Accomodation | D45: TCK3002-A01 | F45: Locken | G45: Key Safe | H45: aljcbqwdjsb | I45: G9L-1056 0000Z_404
A46: LOCK-00047 | B46: TKY1025 | C46: Accomodation | D46: TKY1025-A01 | F46: Locken | G46: Euro Cylinder | H46: aljcbqwdjsb | I46: G9L-1056 0000Z_405
A47: LOCK-00049 | B47: TMO1023 | C47: Accomodation | D47: TMO1023-A01 | F47: Locken | G47: Long Padlock | H47: aljcbqwdjsb | I47: G9L-1056 0000Z_407
A48: LOCK-00050 | B48: TDU3004 | C48: Accomodation | D48: TDU3004-A01 | F48: Locken | G48: Short Padlock | H48: aljcbqwdjsb | I48: G9L-1056 0000Z_408
A49: LOCK-00051 | B49: TCE1006 | C49: Accomodation | D49: TCE1006-A01 | F49: Locken | G49: Key Safe | H49: aljcbqwdjsb | I49: G9L-1056 0000Z_409
A50: LOCK-00052 | B50: TKE1009 | C50: Accomodation | D50: TKE1009-A01 | F50: Locken | G50: Euro Cylinder | H50: aljcbqwdjsb | I50: G9L-1056 0000Z_410
A51: LOCK-00053 | B51: TGY1014 | C51: Accomodation | D51: TGY1014-A01 | F51: Locken | G51: Long Padlock | H51: aljcbqwdjsb | I51: G9L-1056 0000Z_411
... A72: LOCK-00074 | B72: TTP1032 | C72: Accomodation | D72: TTP1032-A01 | F72: Locken | G72: Short Padlock | H72: aljcbqwdjsb | I72: G9L-1056 0000Z_445
A73: LOCK-00075 | B73: TDU8100 | C73: Gate | F73: Locken | G73: Key Safe | H73: aljcbqwdjsb | I73: G9L-1056 0000Z_446
A74: LOCK-00076 | B74: TDL1038 | C74: Accomodation | D74: TDL1038-A01 | F74: Locken | G74: Euro Cylinder | H74: aljcbqwdjsb | I74: G9L-1056 0000Z_447
A75: LOCK-00077 | B75: TKY1022 | C75: Accomodation | D75: TKY1022-A01 | F75: Locken | G75: Long Padlock | H75: aljcbqwdjsb | I75: G9L-1056 0000Z_450
A76: LOCK-00078 | B76: TCK2019 | C76: Accomodation | D76: TCK2019-A01 | F76: Locken | G76: Short Padlock | H76: aljcbqwdjsb | I76: G9L-1056 0000Z_452
A77: LOCK-00079 | B77: TSO1007 | C77: Accomodation | D77: TSO1007-A01 | F77: Locken | G77: Key Safe | H77: aljcbqwdjsb | I77: G9L-1056 0000Z_453
A78: LOCK-00080 | B78: TDL1034 | C78: Accomodation | D78: TDL1034-A01 | F78: Locken | G78: Euro Cylinder | H78: aljcbqwdjsb | I78: G9L-1056 0000Z_454
A79: LOCK-00081 | B79: TWD2020 | C79: Accomodation | D79: TWD2020-A01 | F79: Locken | G79: Long Padlock | H79: aljcbqwdjsb | I79: G9L-1056 0000Z_455
A80: LOCK-00082 | B80: TKY1011 | C80: Accomodation | D80: TKY1011-A01 | F80: Locken | G80: Short Padlock | H80: aljcbqwdjsb | I80: G9L-1056 0000Z_456
A81: LOCK-00083 | B81: TKK1004 | C81: Accomodation | D81: TKK1004-A01 | F81: Locken | G81: Key Safe | H81: aljcbqwdjsb | I81: G9L-1056 0000Z_457
A82: LOCK-00084 | B82: TLK1027 | C82: Accomodation | D82: TLK1027-A01 | F82: Locken | G82: Euro Cylinder | H82: aljcbqwdjsb | I82: G9L-1056 0000Z_458
A83: LOCK-00085 | B83: TKK1004 | C83: Accomodation | D83: TKK1004-A01 | F83: Locken | G83: Long Padlock | H83: aljcbqwdjsb | I83: G9L-1056 0000Z_459
A84: LOCK-00086 | B84: TWW1002 | C84: Accomodation | D84: TWW1002-A01 | F84: Locken | G84: Short Padlock | H84: aljcbqwdjsb | I84: G9L-1056 0000Z_460
A85: LOCK-00087 | B85: TMO1001 | C85: Accomodation | D85: TMO1001-A01 | F85: Locken | G85: Key Safe | H85: aljcbqwdjsb | I85: G9L-1056 0000Z_462
... A87: LOCK-00089 | B87: TWX1040 | C87: Accomodation | D87: TWX1040-A01 | F87: Locken | G87: Long Padlock | H87: aljcbqwdjsb | I87: G9L-1056 0000Z_466
A88: LOCK-00090 | B88: TLS6037 | C88: Gate | F88: Locken | G88: Short Padlock | H88: aljcbqwdjsb | I88: G9L-1056 0000Z_172
A89: LOCK-00091 | B89: TLS6037 | C89: Anti-Climb | D89: TLS6037-T01 | F89: Locken | G89: Key Safe | H89: aljcbqwdjsb | I89: G9L-1056 0000Z_173
A90: LOCK-00092 | B90: TLS6039 | C90: Gate | F90: Locken | G90: Euro Cylinder | H90: aljcbqwdjsb | I90: G9L-1056 0000Z_174
A91: LOCK-00093 | B91: TKY6032 | C91: Gate | F91: Locken | G91: Long Padlock | H91: aljcbqwdjsb | I91: G9L-1056 0000Z_175
A92: LOCK-00094 | B92: TCW6301 | C92: Gate | F92: Locken | G92: Short Padlock | H92: aljcbqwdjsb | I92: G9L-1056 0000Z_177
A93: LOCK-00095 | B93: TCK6011 | C93: Anti-Climb | D93: TCK6011-T01 | F93: Locken | G93: Key Safe | H93: aljcbqwdjsb | I93: G9L-1056 0000Z_178
A94: LOCK-00096 | B94: TKY6030 | C94: Gate | F94: Locken | G94: Euro Cylinder | H94: aljcbqwdjsb | I94: G9L-1056 0000Z_179
A95: LOCK-00097 | B95: TLM6040 | C95: Gate | F95: Locken | G95: Long Padlock | H95: aljcbqwdjsb | I95: G9L-1056 0000Z_180
A96: LOCK-00098 | B96: TLM6041 | C96: Gate | F96: Locken | G96: Short Padlock | H96: aljcbqwdjsb | I96: G9L-1056 0000Z_181
A97: LOCK-00099 | B97: TKY6028 | C97: Gate | F97: Locken | G97: Key Safe | H97: aljcbqwdjsb | I97: G9L-1056 0000Z_184
A98: LOCK-00100 | B98: TTP5167 | C98: Gate | F98: Locken | G98: Euro Cylinder | H98: aljcbqwdjsb | I98: G9L-1056 0000Z_185
A99: LOCK-00101 | B99: TWH6468 | C99: Gate | F99: Locken | G99: Long Padlock | H99: aljcbqwdjsb | I99: G9L-1056 0000Z_186
A100: LOCK-00102 | B100: TMO6353 | C100: Gate | F100: Locken | G100: Short Padlock | H100: aljcbqwdjsb | I100: G9L-1056 0000Z_189
A101: LOCK-00103 | B101: TCK6006 | C101: Gate | F101: Locken | G101: Key Safe | H101: aljcbqwdjsb | I101: G9L-1056 0000Z_190
A102: LOCK-00104 | B102: TCK6006 | C102: Anti-Climb | D102: TCK6006-T01 | F102: Locken | G102: Euro Cylinder | H102: aljcbqwdjsb | I102: G9L-1056 0000Z_191
A103: LOCK-00105 | B103: TCE7038 | C103: Anti-Climb | D103: TCE7038-T01 | F103: Locken | G103: Long Padlock | H103: aljcbqwdjsb | I103: G9L-1056 0000Z_193
A104: LOCK-00106 | B104: TCK6005 | C104: Anti-Climb | D104: TCK6005-T01 | F104: Locken | G104: Short Padlock | H104: aljcbqwdjsb | I104: G9L-1056 0000Z_195
A105: LOCK-00107 | B105: TDU5113 | C105: Gate | F105: Locken | G105: Key Safe | H105: aljcbqwdjsb | I105: G9L-1056 0000Z_196
A106: LOCK-00108 | B106: TDU5221 | C106: Gate | F106: Locken | G106: Euro Cylinder | H106: aljcbqwdjsb | I106: G9L-1056 0000Z_197 - gone
A107: LOCK-00109 | B107: TWX5074 | C107: Anti-Climb | D107: TWX5074-T01 | F107: Locken | G107: Long Padlock | H107: aljcbqwdjsb | I107: G9L-1056 0000Z_198
A108: LOCK-00110 | B108: TDU6416 | C108: Gate | F108: Locken | G108: Short Padlock | H108: aljcbqwdjsb | I108: G9L-1056 0000Z_200
A109: LOCK-00111 | B109: TWX7020 | C109: Gate | F109: Locken | G109: Key Safe | H109: aljcbqwdjsb | I109: G9L-1056 0000Z_202
A110: LOCK-00112 | B110: TWX7020 | C110: Anti-Climb | D110: TWX7020-T01 | F110: Locken | G110: Euro Cylinder | H110: aljcbqwdjsb | I110: G9L-1056 0000Z_203
A111: LOCK-00113 | B111: TLH5098 | C111: Anti-Climb | D111: TLH5098-T01 | F111: Locken | G111: Long Padlock | H111: aljcbqwdjsb | I111: G9L-1056 0000Z_204
A112: LOCK-00114 | B112: TCE6003 | C112: Gate | F112: Locken | G112: Short Padlock | H112: aljcbqwdjsb | I112: G9L-1056 0000Z_205
A113: LOCK-00115 | B113: TGY6325 | C113: Anti-Climb | D113: TGY6325-T01 | F113: Locken | G113: Key Safe | H113: aljcbqwdjsb | I113: G9L-1056 0000Z_208
A114: LOCK-00116 | B114: TGY6020 | C114: Gate | F114: Locken | G114: Euro Cylinder | H114: aljcbqwdjsb | I114: G9L-1056 0000Z_209
A115: LOCK-00117 | B115: TMH1020 | C115: Gate | F115: Locken | G115: Long Padlock | H115: aljcbqwdjsb | I115: G9L-1056 0000Z_210
A116: LOCK-00118 | B116: TMH1020 | C116: Anti-Climb | D116: TMH1020-T01 | F116: Locken | G116: Short Padlock | H116: aljcbqwdjsb | I116: G9L-1056 0000Z_211
A117: LOCK-00119 | B117: TMH1020 | C117: Gate | F117: Locken | G117: Key Safe | H117: aljcbqwdjsb | I117: G9L-1056 0000Z_212
A118: LOCK-00120 | B118: TDU5211 | C118: Gate | F118: Locken | G118: Euro Cylinder | H118: aljcbqwdjsb | I118: G9L-1056 0000Z_213
A119: LOCK-00121 | B119: TMH5050 | C119: Anti-Climb | D119: TMH5050-T01 | F119: Locken | G119: Long Padlock | H119: aljcbqwdjsb | I119: G9L-1056 0000Z_216
A120: LOCK-00122 | B120: TMH5166 | C120: Anti-Climb | D120: TMH5166-R01 | F120: Locken | G120: Short Padlock | H120: aljcbqwdjsb | I120: G9L-1056 0000Z_217
A121: LOCK-00123 | B121: TGY6325 | C121: Gate | F121: Locken | G121: Key Safe | H121: aljcbqwdjsb | I121: G9L-1056 0000Z_218
...

Sheet INSPECTIONS
E1: RADIX COMPANY ROW ID | F1: RADIX PROFILE ROW ID | G1: RADIX PROFILE ROW ID
A2: Site | B2: Structure | C2: Inspection Type | D2: Inspection Date | E2: Inspected by Company | F2: Inspected by Profile | G2: Detailed entered by | H2: Comments
A3: TGY6020 | B3: TGY6020-T01 | C3: Fall Arrest Certification | D3: 44167 | E3: 67 | F3: 931 | G3: 931 | H3: all good
A4: TGY6020 | B4: TGY6020-T01 | C4: Fall Arrest Certification | D4: 41199 | E4: 67 | F4: 852 | G4: 852 | H4: Metreel is in good working condition, Tag required to be place on tower with date of inspection
A5: TOY6059 | B5: TOY6059-T01 | C5: Fall Arrest Certification | D5: 41212 | E5: 67 | F5: 852 | G5: 852 | H5: Metreel is in good working condition
A6: TWH6065 | B6: TWH6065-T01 | C6: Fall Arrest Certification | D6: 41212 | E6: 67 | F6: 852 | G6: 852 | H6: Metreel is in good working order, tag is required to be placed on anti-climb.
A7: TDL6014 | B7: TDL6014-T01 | C7: Fall Arrest Certification | D7: 41215 | E7: 67 | F7: 852 | G7: 852 | H7: Metreel is in good working order.
A8: TWH6468 | B8: TWH6468-T01 | C8: Fall Arrest Certification | D8: 41219 | E8: 67 | F8: 1533 | G8: 1533 | H8: metreel in good working order
A9: TTP6064 | B9: TTP6064-T01 | C9: Fall Arrest Certification | D9: 41219 | E9: 67 | F9: 1533 | G9: 1533 | H9: metrail working @ in good order
A10: TMO5143 | B10: TMO5143-T01 | C10: Fall Arrest Certification | D10: 41240 | E10: 67 | F10: 852 | G10: 852 | H10: inspected on climbdown.
A11: TRN5062 | B11: TRN5062-T01 | C11: Fall Arrest Certification | D11: 41246 | E11: 67 | F11: 1533 | G11: 1533 | H11: Fall arrest is in good conditon
A12: TOY6060 | B12: TOY6060-T01 | C12: Fall Arrest Certification | D12: 41219 | E12: 67 | F12: 1533 | G12: 1533 | H12: Metreel in good working order.
A13: TMO6047 | B13: TMO6047-T01 | C13: Fall Arrest Certification | D13: 41284 | E13: 67 | F13: 1533 | G13: 1533 | H13: Metreel is in good working order.
A14: TMO6452 | B14: TMO6452-T01 | C14: Fall Arrest Certification | D14: 41284 | E14: 67 | F14: 1533 | G14: 1533 | H14: Metreel is in good working condition.
... A28: TMO6456 | B28: TMO6456-T01 | C28: Fall Arrest Certification | D28: 41326 | E28: 67 | F28: 1533 | G28: 1533 | H28: Annual climbdown 2013
A29: TMO6452 | B29: TMO6452-T01 | C29: Fall Arrest Certification | D29: 42310 | E29: 67 | F29: 931 | G29: 931
A30: TMO6047 | B30: TMO6047-T01 | C30: Fall Arrest Certification | D30: 42310 | E30: 67 | F30: 931 | G30: 931
A31: TMO6456 | B31: TMO6456-T01 | C31: Fall Arrest Certification | D31: 42310 | E31: 67 | F31: 931 | G31: 931
A32: TLK6044 | B32: TLK6044-T01 | C32: Fall Arrest Certification | D32: 42311 | E32: 67 | F32: 931 | G32: 931
A33: TKY6030 | B33: TKY6030-T01 | C33: Fall Arrest Certification | D33: 42311 | E33: 67 | F33: 931 | G33: 931
A34: TLK6043 | B34: TLK6043-T01 | C34: Fall Arrest Certification | D34: 42311 | E34: 67 | F34: 931 | G34: 931
A35: TKY6028 | B35: TKY6028-T01 | C35: Fall Arrest Certification | D35: 42312 | E35: 67 | F35: 931 | G35: 931
A36: TKY6033 | B36: TKY6033-T01 | C36: Fall Arrest Certification | D36: 42312 | E36: 67 | F36: 931 | G36: 931
A37: TKY6032 | B37: TKY6032-T01 | C37: Fall Arrest Certification | D37: 42312 | E37: 67 | F37: 931 | G37: 931
A38: TCK6011 | B38: TCK6011-T01 | C38: Fall Arrest Certification | D38: 42313 | E38: 67 | F38: 931 | G38: 931
A39: TCK6010 | B39: TCK6010-T01 | C39: Fall Arrest Certification | D39: 42313 | E39: 67 | F39: 931 | G39: 931
A40: TCK6005 | B40: TCK6005-T01 | C40: Fall Arrest Certification | D40: 42313 | E40: 67 | F40: 931 | G40: 931
... A42: TCE6003 | B42: TCE6003-T01 | C42: Fall Arrest Certification | D42: 42317 | E42: 67 | F42: 931 | G42: 931
A43: TDL6014 | B43: TDL6014-T01 | C43: Fall Arrest Certification | D43: 42389 | E43: 67 | F43: 931 | G43: 931 | H43: fall arrest ok
A44: TLM6042 | B44: TLM6042-T01 | C44: Fall Arrest Certification | D44: 42396 | E44: 67 | F44: 931 | G44: 931 | H44: all in good working order
A45: TLM6041 | B45: TLM6041-T01 | C45: Fall Arrest Certification | D45: 42396 | E45: 67 | F45: 931 | G45: 931 | H45: in good working order
A46: TLM6040 | B46: TLM6040-T01 | C46: Fall Arrest Certification | D46: 42397 | E46: 67 | F46: 931 | G46: 931 | H46: all good
A47: TDU6017 | B47: TDU6017-T01 | C47: Fall Arrest Certification | D47: 42404 | E47: 67 | F47: 931 | G47: 931 | H47: all good
A48: TDU6416 | B48: TDU6416-T01 | C48: Fall Arrest Certification | D48: 42498 | E48: 67 | F48: 931 | G48: 931 | H48: all good
A49: TWH6065 | B49: TWH6065-T01 | C49: Fall Arrest Certification | D49: 42498 | E49: 67 | F49: 931 | G49: 931 | H49: metreel in good order new tagcard instlled
A50: TMO6353 | B50: TMO6353-T01 | C50: Fall Arrest Certification | D50: 42499 | E50: 67 | F50: 931 | G50: 931 | H50: metreel ok
A51: TMO6055 | B51: TMO6055-T01 | C51: Fall Arrest Certification | D51: 42499 | E51: 67 | F51: 931 | G51: 931 | H51: metreel in good working order
A52: TKY6028 | B52: TKY6028-T01 | C52: Fall Arrest Certification | D52: 42653 | E52: 67 | F52: 931 | G52: 931 | H52: safe to climb
A53: TKY6033 | B53: TKY6033-T01 | C53: Fall Arrest Certification | D53: 42653 | E53: 67 | F53: 931 | G53: 931 | H53: ladder fit for use
A54: TKY6033 | B54: TKY6033-T01 | C54: Fall Arrest Certification | D54: 42653 | E54: 67 | F54: 931 | G54: 931 | H54: ladder fit for use
... A60: TGY6325 | B60: TGY6325-T01 | C60: Fall Arrest Certification | D60: 42746 | E60: 67 | F60: 931 | G60: 931 | H60: metreel in good order
A61: TOY6059 | B61: TOY6059-T01 | C61: Fall Arrest Certification | D61: 42647 | E61: 67 | F61: 931 | G61: 931
A62: TOY6059 | B62: TOY6059-T01 | C62: Fall Arrest Certification | D62: 25569 | E62: 67 | F62: 931 | G62: 931
A63: TOY6059 | B63: TOY6059-T01 | C63: Fall Arrest Certification | D63: 42755 | E63: 67 | F63: 931 | G63: 931 | H63: metreel in good order
A64: TKE6336 | B64: TKE6336-T01 | C64: Fall Arrest Certification | D64: 42781 | E64: 67 | F64: 931 | G64: 931 | H64: all in good order
A65: TDL6312 | B65: TDL6312-T01 | C65: Fall Arrest Certification | D65: 41311 | E65: 67 | F65: 1547 | G65: 1547
A66: TWH6065 | B66: TWH6065-T01 | C66: Fall Arrest Certification | D66: 42863 | E66: 67 | F66: 1547 | G66: 1547 | H66: Metreel in good order tag-card updated
A67: TMO6055 | B67: TMO6055-T01 | C67: Fall Arrest Certification | D67: 42869 | E67: 67 | F67: 931 | G67: 931 | H67: all good
A68: TMO6353 | B68: TMO6353-T01 | C68: Fall Arrest Certification | D68: 42869 | E68: 67 | F68: 931 | G68: 931 | H68: all in good order
A69: TGY6325 | B69: TGY6325-T01 | C69: Fall Arrest Certification | D69: 42870 | E69: 67 | F69: 931 | G69: 931 | H69: all in good order
A70: TGY6020 | B70: TGY6020-T01 | C70: Fall Arrest Certification | D70: 42870 | E70: 67 | F70: 931 | G70: 931 | H70: all good
A71: TGY6021 | B71: TGY6021-T01 | C71: Fall Arrest Certification | D71: 42871 | E71: 67 | F71: 931 | G71: 931 | H71: all good
A72: TGY6419 | B72: TGY6419-T01 | C72: Fall Arrest Certification | D72: 42871 | E72: 67 | F72: 931 | G72: 931 | H72: all good
A73: TRN6361 | B73: TRN6361-T01 | C73: Fall Arrest Certification | D73: 42871 | E73: 67 | F73: 931 | G73: 931 | H73: all good
A74: TRN6462 | B74: TRN6462-T01 | C74: Fall Arrest Certification | D74: 42871 | E74: 67 | F74: 931 | G74: 931 | H74: all good
A75: TLM6041 | B75: TLM6041-T01 | C75: Fall Arrest Certification | D75: 42871 | E75: 67 | F75: 931 | G75: 931 | H75: all good
A76: TLM6040 | B76: TLM6040-T01 | C76: Fall Arrest Certification | D76: 42871 | E76: 67 | F76: 931 | G76: 931 | H76: all good
A77: TLM6042 | B77: TLM6042-T01 | C77: Fall Arrest Certification | D77: 42871 | E77: 67 | F77: 931 | G77: 931 | H77: all good
... A87: TDU6416 | B87: TDU6416-T01 | C87: Fall Arrest Certification | D87: 42878 | E87: 67 | F87: 931 | G87: 931 | H87: all in good order
A88: TKY6029 | B88: TKY6029-T01 | C88: Fall Arrest Certification | D88: 41305 | E88: 67 | F88: 1547 | G88: 1547
A89: TDL6015 | B89: TDL6015-T01 | C89: Fall Arrest Certification | D89: 41311 | E89: 67 | F89: 1547 | G89: 1547
A90: TDL6013 | B90: TDL6013-T01 | C90: Fall Arrest Certification | D90: 42389 | E90: 67 | F90: 1547 | G90: 1547
A91: TWH6468 | B91: TWH6468-T01 | C91: Fall Arrest Certification | D91: 42299 | E91: 67 | F91: 1547 | G91: 1547
A92: TDU6017 | B92: TDU6017-T01 | C92: Fall Arrest Certification | D92: 42878 | E92: 67 | F92: 931 | G92: 931 | H92: all in good working order
A93: TKE6336 | B93: TKE6336-T01 | C93: Fall Arrest Certification | D93: 42878 | E93: 67 | F93: 931 | G93: 931 | H93: all in good order
A94: TTP6063 | B94: TTP6063-T01 | C94: Fall Arrest Certification | D94: 42879 | E94: 67 | F94: 931 | G94: 931 | H94: all in good order
A95: TLS6038 | B95: TLS6038-T01 | C95: Fall Arrest Certification | D95: 42879 | E95: 67 | F95: 931 | G95: 931 | H95: in good working order
A96: TLS6037 | B96: TLS6037-T01 | C96: Fall Arrest Certification | D96: 42885 | E96: 67 | F96: 931 | G96: 931 | H96: in good working order
A97: TDL6013 | B97: TDL6013-T01 | C97: Fall Arrest Certification | D97: 42892 | E97: 67 | F97: 931 | G97: 931 | H97: all in good order
A98: TDL6312 | B98: TDL6312-T01 | C98: Fall Arrest Certification | D98: 42892 | E98: 67 | F98: 931 | G98: 931 | H98: all in good working order
A99: TDL6015 | B99: TDL6015-T01 | C99: Fall Arrest Certification | D99: 42893 | E99: 67 | F99: 931 | G99: 931 | H99: all in good order
A100: TDL6014 | B100: TDL6014-T01 | C100: Fall Arrest Certification | D100: 42893 | E100: 67 | F100: 931 | G100: 931 | H100: one step/run has a crack about 3m down from top
A101: TCE6003 | B101: TCE6003-T01 | C101: Fall Arrest Certification | D101: 42897 | E101: 67 | F101: 931 | G101: 931 | H101: all in good order
A102: TKY6033 | B102: TKY6033-T01 | C102: Fall Arrest Certification | D102: 42899 | E102: 67 | F102: 931 | G102: 931 | H102: ladder has a cracked rung 4 m from base
A103: TKY6030 | B103: TKY6030-T01 | C103: Fall Arrest Certification | D103: 42899 | E103: 67 | F103: 931 | G103: 931 | H103: all in good order
... A107: TCK6010 | B107: TCK6010-T01 | C107: Fall Arrest Certification | D107: 42907 | E107: 67 | F107: 931 | G107: 931 | H107: in good order
A108: TCK6010 | B108: TCK6010-T01 | C108: Fall Arrest Certification | D108: 25569 | E108: 67 | F108: 931 | G108: 931
A109: TCK6011 | B109: TCK6011-T01 | C109: Fall Arrest Certification | D109: 42907 | E109: 67 | F109: 931 | G109: 931 | H109: in good order
A110: TCK6011 | B110: TCK6011-T01 | C110: Fall Arrest Certification | D110: 42907 | E110: 67 | F110: 931 | G110: 931 | H110: all in good order
A111: TCK6006 | B111: TCK6006-T01 | C111: Fall Arrest Certification | D111: 42907 | E111: 67 | F111: 931 | G111: 931 | H111: all in good order
A112: TCK6005 | B112: TCK6005-T01 | C112: Fall Arrest Certification | D112: 42907 | E112: 67 | F112: 931 | G112: 931 | H112: in good order
A113: TLK6043 | B113: TLK6043-T01 | C113: Fall Arrest Certification | D113: 42907 | E113: 67 | F113: 931 | G113: 931 | H113: all in good order
A114: TLK6044 | B114: TLK6044-T01 | C114: Fall Arrest Certification | D114: 42907 | E114: 67 | F114: 931 | G114: 931 | H114: good order
A115: TDL6014 | B115: TDL6014-T01 | C115: Fall Arrest Certification | D115: 43052 | E115: 67 | F115: 931 | G115: 931 | H115: all in good order
A116: TLM6042 | B116: TLM6042-T01 | C116: Fall Arrest Certification | D116: 43074 | E116: 67 | F116: 931 | G116: 931 | H116: all in good order
A117: TKY6033 | B117: TKY6033-T01 | C117: Fall Arrest Certification | D117: 43075 | E117: 67 | F117: 931 | G117: 931 | H117: all in good order
A118: TWH6468 | B118: TWH6468-T01 | C118: Fall Arrest Certification | D118: 43076 | E118: 67 | F118: 931 | G118: 931 | H118: in good order
A119: TCK6011 | B119: TCK6011-T01 | C119: Fall Arrest Certification | D119: 43126 | E119: 67 | F119: 931 | G119: 931 | H119: all in good order
A120: TCK6010 | B120: TCK6010-T01 | C120: Fall Arrest Certification | D120: 43126 | E120: 67 | F120: 931 | G120: 931 | H120: fall arrest in good order
... A230: TKK5132 | B230: TKK5132-T01 | C230: Fall Arrest Certification | D230: 43948 | E230: 67 | F230: 3102 | G230: 3102 | H230: all ok
A231: TCK5181 | B231: TCK5181-T01 | C231: Fall Arrest Certification | D231: 43949 | E231: 67 | F231: 3102 | G231: 3102
A232: TOY5177 | B232: TOY5177-T01 | C232: Fall Arrest Certification | D232: 43947 | E232: 67 | F232: 3102 | G232: 3102
A233: TLK5137 | B233: TLK5137-T01 | C233: Fall Arrest Certification | D233: 43949 | E233: 67 | F233: 3102 | G233: 3102
A234: TKY6028 | B234: TKY6028-T01 | C234: Fall Arrest Certification | D234: 43964 | E234: 67 | F234: 931 | G234: 931 | H234: all good
A235: TKY6032 | B235: TKY6032-T01 | C235: Fall Arrest Certification | D235: 43964 | E235: 67 | F235: 931 | G235: 931 | H235: all good
A236: TDL6014 | B236: TDL6014-T01 | C236: Fall Arrest Certification | D236: 43970 | E236: 67 | F236: 931 | G236: 931 | H236: all good and in working order
A237: TKY6030 | B237: TKY6030-T01 | C237: Fall Arrest Certification | D237: 44329 | E237: 67 | F237: 931 | G237: 931 | H237: all good
A238: TOY6059 | B238: TOY6059-T01 | C238: Fall Arrest Certification | D238: 43979 | E238: 67 | F238: 931 | G238: 931 | H238: all good
A239: TLS6038 | B239: TLS6038-T01 | C239: Fall Arrest Certification | D239: 43979 | E239: 67 | F239: 931 | G239: 931 | H239: all good
A240: TLS6037 | B240: TLS6037-T01 | C240: Fall Arrest Certification | D240: 43979 | E240: 67 | F240: 931 | G240: 931 | H240: all good
...

Sheet FACILITIES SERVICE
E1: RADIX COMPANY ROW ID | K1: RADIX PROFILE ROW ID
A2: Site | B2: Accommodation | C2: Service Type | D2: Service Date | E2: Serviced By | F2: Temperature (deg C) | G2: units | H2: co2_refilled | I2: co2_tested | J2: abc_refilled | K2: Detailed entered by | L2: Comments
A3: TMO1001 | B3: TMO1001-A01 | C3: AirCon Service | D3: 40781 | E3: 67 | F3: 21 | K3: 856 | L3: Unit stat wired incorrectly. Rewired to suit application.
A4: TWW1002 | B4: TWW1002-A01 | C4: AirCon Service | D4: 40801 | E4: 67 | F4: 20-21 | K4: 856 | L4: Unit 1 compressor faulty Unit 2 running well but amps are high Recommend floor stand 125 and remove old equipment.
A5: TLK1003 | B5: TLK1003-A01 | C5: AirCon Service | D5: 40785 | E5: 67 | F5: 20-21 | K5: 856 | L5: Unit 2 requires gas leak repairs Recommend replacing both with 1 new unit.
A6: TKK1004 | B6: TKK1004-A01 | C6: AirCon Service | D6: 40786 | E6: 67 | F6: 19-20 | K6: 856 | L6: Toshiba system requires pressure test and leak repair. System is 9 years old, needs replacing. Recommend replace Toshiba with floor standing.
A7: TDL1005 | B7: TDL1005-A01 | C7: AirCon Service | D7: 40780 | E7: 67 | F7: 20 | K7: 856 | L7: Both systems are beyond repair and require replacing.
A8: TCE1006 | B8: TCE1006-A01 | C8: AirCon Service | D8: 40785 | E8: 67 | F8: 20 | K8: 856 | L8: System 1 is beyond repair and requires replacing.
A9: TSO1007 | B9: TSO1007-A01 | C9: AirCon Service | D9: 40780 | E9: 67 | F9: 22 | K9: 856 | L9: Unit 1 low in refrigerant and will need leak test.
A10: TCK3002 | B10: TCK3002-A01 | C10: AirCon Service | D10: 40785 | E10: 67 | F10: 19 | K10: 856 | L10: Fan in good working order.
A11: TLS1010 | B11: TLS1010-A01 | C11: AirCon Service | D11: 40786 | E11: 67 | F11: 18 | K11: 856 | L11: Unit 1 very low on refrigerant and will require pressure test. Recommend replacing Panasonic units.
A12: TKE1009 | B12: TKE1009-A01 | C12: AirCon Service | D12: 40795 | E12: 67 | F12: 20-21 | K12: 856 | L12: Both units are beyond repair. Recommend replacing with floor standing 125 units.
A13: TGY1012 | B13: TGY1012-A01 | C13: AirCon Service | D13: 40792 | E13: 67 | F13: 21 | K13: 856 | L13: All three units are running well.
A14: TCK2012 | B14: TCK2012-A01 | C14: AirCon Service | D14: 40785 | E14: 67 | F14: 19 | K14: 856 | L14: Fan in good working order. Cabin temp very high, requires AC but no room.
A15: TDU2013 | B15: TDU2013-A01 | C15: AirCon Service | D15: 40792 | E15: 67 | F15: 22 | K15: 856 | L15: Recommend removal of 2 Toshiba units and fit floor standing or under ceiling unit in Radio Room.
A16: TWX1018 | B16: TWX1018-A01 | C16: AirCon Service | D16: 40787 | E16: 67 | F16: 22 | K16: 856 | L16: York indoor fan motor siezed and needs to be replaced. Recommend replacing with Mitsubishi.
A17: TLH2015 | B17: TLH2015-A01 | C17: AirCon Service | D17: 40795 | E17: 67 | K17: 856 | L17: Had to force both units to work mechanically. Requires proper servicing.
A18: TKE1019 | B18: TKE1019-A01 | C18: AirCon Service | D18: 40786 | E18: 67 | F18: 19-22 | K18: 856 | L18: Toshiba system has faulty compressor. Recommend replace Toshiba and use new unit as Master. Keep Daikin unit and use if load requires.
A19: TCK2019 | B19: TCK2019-A01 | C19: AirCon Service | D19: 40785 | E19: 67 | F19: 20 | K19: 856 | L19: Fan in good working order.
A20: TMH1020 | B20: TMH1020-A01 | C20: AirCon Service | D20: 40795 | E20: 67 | F20: 20-21 | K20: 856 | L20: Unit 1 indoor fan bearings beginning to fail. Unit 2 in good working order but has no water detection protection. Not really suitable for application.
A21: TTP1021 | B21: TTP1021-A01 | C21: AirCon Service | D21: 40787 | E21: 67 | F21: 22 | K21: 856 | L21: Unit 1 York system faulty and needs replacing. Unit 2 York is low in refrigerant. Recommend removing York system and fitting 125 floor standing. Keep Daikin in position and use only if load requires.
A22: TMO1023 | B22: TMO1023-A01 | C22: AirCon Service | D22: 40780 | E22: 67 | F22: 20 | K22: 856 | L22: Unit in poor position for optimal efficiency. Unit indoor fan motor bearings beginning to fail.
A23: TCK1026 | B23: TCK1026-A01 | C23: AirCon Service | D23: 40785 | E23: 67 | K23: 856 | L23: Both York units beyond repair and require urgent replacement.
A24: TLK1027 | B24: TLK1027-A01 | C24: AirCon Service | D24: 40784 | E24: 67 | F24: 22 | K24: 856 | L24: Both units in good order.
A25: TKY1031 | B25: TKY1031-A01 | C25: AirCon Service | D25: 40134 | E25: 67 | F25: 22 | K25: 856 | L25: No air conditioning system at this site. A 7kw power inverter air conditioning unit is required.
A26: TTP1032 | B26: TTP1032-A01 | C26: AirCon Service | D26: 40786 | E26: 67 | F26: 22 | K26: 856 | L26: IMI and York systems faulty. Recommend removing IMI system and fitting 140 floor or under ceiling unit.
A27: TGY2033 | B27: TGY2033-A01 | C27: AirCon Service | D27: 40800 | E27: 67 | K27: 856 | L27: Had to force both units to work mechanically. Requires proper servicing.
A28: TDL1034 | B28: TDL1034-A01 | C28: AirCon Service | D28: 40780 | E28: 67 | F28: 20 | K28: 856 | L28: Both IMI systems are beyond repair. Recommend replacing with 1 floor standing or 2 wall mounted systems.
A29: TKY1035 | B29: TKY1035-A01 | C29: AirCon Service | D29: 40784 | E29: 67 | F29: 19 | K29: 856 | L29: Both units in good order. Unit 1 indoor fan motor bearings are beginning to fail, will need to be changed in the near future.
A30: TLH1036 | B30: TLH1036-A01 | C30: AirCon Service | D30: 40795 | E30: 67 | F30: 21-22 | K30: 856 | L30: Both units working well. Panasonic unit requires new compressor contractor.
A31: TWX1040 | B31: TWX1040-A01 | C31: AirCon Service | D31: 40787 | E31: 67 | F31: 20-22 | K31: 856 | L31: Unit 1 compressor beginning to fail. Recommend 2 floor standing systems.
A32: TDU3018 | B32: TDU3018-A01 | C32: AirCon Service | D32: 40792 | E32: 67 | K32: 856 | L32: Had to force both units to work mechanically. Proper servicing required.
A33: TMO1001 | B33: TMO1001-A01 | C33: AirCon Service | D33: 41144 | E33: 67 | F33: 22 | K33: 852 | L33: Unit is working well.
A34: TWW1002 | B34: TWW1002-A01 | C34: AirCon Service | D34: 41149 | E34: 67 | F34: 22 | K34: 852 | L34: unit in good working order
A35: TLK1003 | B35: TLK1003-A01 | C35: AirCon Service | D35: 41170 | E35: 67 | F35: 21 | K35: 852 | L35: unit in good working order
A36: TKK1004 | B36: TKK1004-A01 | C36: AirCon Service | D36: 41150 | E36: 67 | F36: 22 | K36: 852 | L36: Both units in good working order
A37: TDL1005 | B37: TDL1005-A01 | C37: AirCon Service | D37: 41136 | E37: 67 | F37: 22 | K37: 852 | L37: Unit in good working order.
A38: TCE1006 | B38: TCE1006-A01 | C38: AirCon Service | D38: 41155 | E38: 67 | F38: 22 | K38: 852 | L38: Unit in good working order.
A39: TSO1007 | B39: TSO1007-A01 | C39: AirCon Service | D39: 41144 | E39: 67 | F39: 21 | K39: 852 | L39: Unit in good working order.
A40: TCK3002 | B40: TCK3002-A01 | C40: AirCon Service | D40: 41171 | E40: 67 | F40: 20 | K40: 852 | L40: Unit in good working condition.
A41: TLS1010 | B41: TLS1010-A01 | C41: AirCon Service | D41: 41150 | E41: 67 | F41: 22 | K41: 852 | L41: Units in good working order.
A42: TKE1009 | B42: TKE1009-A01 | C42: AirCon Service | D42: 41149 | E42: 67 | F42: 22 | K42: 852 | L42: Unit in good working order.
A43: TGY1012 | B43: TGY1012-A01 | C43: AirCon Service | D43: 41179 | E43: 67 | F43: 22 | K43: 852 | L43: Units in good working order.
A44: TCK2012 | B44: TCK2012-A01 | C44: AirCon Service | D44: 41171 | E44: 67 | F44: 21 | K44: 852 | L44: Unit in good working order.
... A65: TKY1031 | B65: TKY1031-A01 | C65: AirCon Service | D65: 41185 | E65: 67 | F65: 22 | K65: 856 | L65: Unit in good working order.
A66: TWH2035 | B66: TWH2035-A01 | C66: AirCon Service | D66: 40792 | E66: 67 | K66: 856 | L66: Had to force both units to work mechanically. Requires proper servicing.
A67: TTP1021 | B67: TTP1021-A01 | C67: AirCon Service | D67: 41528.958 | E67: 67 | K67: 1449 | L67: All equipment on site passed and tested
A68: TTP1032 | B68: TTP1032-A01 | C68: AirCon Service | D68: 41528.958 | E68: 67 | K68: 1449 | L68: A/C Unit on site passed tests
A69: TKY1035 | B69: TKY1035-A01 | C69: AirCon Service | D69: 41548.958 | E69: 67 | K69: 1449 | L69: System passed Leak Test Both systems to be replaced
A70: TKY1031 | B70: TKY1031-A01 | C70: AirCon Service | D70: 41548.958 | E70: 67 | K70: 1449 | L70: System passed successfully leak test
A71: TKY1028 | B71: TKY1028-A01 | C71: AirCon Service | D71: 41547.958 | E71: 67 | K71: 1449 | L71: AC System passed successful Leak test Unit to be replaced on decommission
A72: TCK3002 | B72: TCK3002-A01 | C72: AirCon Service | D72: 41589 | E72: 67 | K72: 1449 | L72: Fan requires contactor or relay
A73: TCK2012 | B73: TCK2012-A01 | C73: AirCon Service | D73: 41589 | E73: 67 | K73: 1449 | L73: Fan requires contactor and relay
A74: TCK2012 | B74: TCK2012-A01 | C74: AirCon Service | D74: 44489.958 | E74: 67 | K74: 1547 | L74: System in good order
A75: TCK1026 | B75: TCK1026-A01 | C75: AirCon Service | D75: 41591 | E75: 67 | K75: 1449 | L75: AC Unit passed leak test
A76: TLH1036 | B76: TLH1036-A01 | C76: AirCon Service | D76: 41572.958 | E76: 67 | K76: 1449 | L76: Both systems passed leak inspection
A77: TMH1020 | B77: TMH1020-A01 | C77: AirCon Service | D77: 41572.958 | E77: 67 | K77: 1449 | L77: AC Unit passed successful leak test
... A127: TCE1006 | B127: TCE1006-A01 | C127: AirCon Service | D127: 42243.958 | E127: 67 | K127: 1449 | L127: AC in good order
A128: TLK1027 | B128: TLK1027-A01 | C128: AirCon Service | D128: 42243.958 | E128: 67 | K128: 1449
A129: TKY1035 | B129: TKY1035-A01 | C129: AirCon Service | D129: 42243.958 | E129: 67 | K129: 1449 | L129: AC in good order
A130: TDU3018 | B130: TDU3018-A01 | C130: AirCon Service | D130: 43338.958 | E130: 67 | K130: 1449 | L130: AC in good order
A131: TDU2013 | B131: TDU2013-A01 | C131: AirCon Service | D131: 42241.958 | E131: 67 | K131: 1449 | L131: AC in good order
A132: TMH1020 | B132: TMH1020-A01 | C132: AirCon Service | D132: 42241.958 | E132: 67 | K132: 1449 | L132: AC in good order
A133: TLH1036 | B133: TLH1036-A01 | C133: AirCon Service | D133: 42241.958 | E133: 67 | K133: 1449 | L133: AC in good order
A134: TMO1023 | B134: TMO1023-A01 | C134: AirCon Service | D134: 42239.958 | E134: 67 | K134: 1449 | L134: AC in good order
A135: TWH2035 | B135: TWH2035-A01 | C135: AirCon Service | D135: 42240.958 | E135: 67 | K135: 1449 | L135: AC in good order
A136: TKE1009 | B136: TKE1009-A01 | C136: AirCon Service | D136: 42240.958 | E136: 67 | K136: 1449 | L136: AC in good order
A137: TKE1019 | B137: TKE1019-A01 | C137: AirCon Service | D137: 42240.958 | E137: 67 | K137: 1449 | L137: Both AC units in good order
A138: TLS1010 | B138: TLS1010-A01 | C138: AirCon Service | D138: 42240.958 | E138: 67 | K138: 1449 | L138: Both AC units in good order
A139: TLH2015 | B139: TLH2015-A01 | C139: AirCon Service | D139: 42241.958 | E139: 67 | K139: 1449 | L139: AC in good order
A140: TMO1001 | B140: TMO1001-A01 | C140: AirCon Service | D140: 42239.958 | E140: 67 | K140: 1449 | L140: Carried out ppm, no other issues
... A219: TLK1003 | B219: TLK1003-A01 | C219: AirCon Service | D219: 43340.958 | E219: 67 | K219: 3102 | L219: Unit in good working order
A220: TMO1023 | B220: TMO1023-A01 | C220: AirCon Service | D220: 43341.958 | E220: 67 | K220: 3102
A221: TDL1034 | B221: TDL1034-A01 | C221: AirCon Service | D221: 43375.958 | E221: 67 | K221: 3102 | L221: System in good order
A222: TCE1006 | B222: TCE1006-A01 | C222: AirCon Service | D222: 43335.958 | E222: 67 | K222: 3102 | L222: System in good order
A223: TTP1032 | B223: TTP1032-A01 | C223: AirCon Service | D223: 43335.958 | E223: 67 | K223: 3102 | L223: System in good order
A224: TKY1028 | B224: TKY1028-A01 | C224: AirCon Service | D224: 43338.958 | E224: 67 | K224: 3102 | L224: System in good order
A225: TLK1027 | B225: TLK1027-A01 | C225: AirCon Service | D225: 43338.958 | E225: 67 | K225: 3102 | L225: System in good order
A226: TKY1031 | B226: TKY1031-A01 | C226: AirCon Service | D226: 43338.958 | E226: 67 | K226: 3102 | L226: System in good order
A227: TWX1040 | B227: TWX1040-A01 | C227: AirCon Service | D227: 43398.958 | E227: 67 | K227: 3102 | L227: System in good order
A228: TWX1018 | B228: TWX1018-A01 | C228: AirCon Service | D228: 43398.958 | E228: 67 | K228: 3102 | L228: Both systems in good order, as previously highlighted the outdoor isolator on off switch is broken on the outdoor unit of Ac1, otherwise all is in good order.
A229: TWW1002 | B229: TWW1002-A01 | C229: AirCon Service | D229: 43398.958 | E229: 67 | K229: 3102 | L229: System in good order
A230: TLS1010 | B230: TLS1010-A01 | C230: AirCon Service | D230: 43334.958 | E230: 67 | K230: 3102 | L230: System in good order
A231: TSO1007 | B231: TSO1007-A01 | C231: AirCon Service | D231: 43341.958 | E231: 67 | K231: 3102 | L231: Unit in good working order
A232: TLS1010 | B232: TLS1010-A01 | C232: AirCon Service | D232: 43380.958 | E232: 67 | K232: 3102 | L232: System in good order
... A302: TCK2019 | B302: TCK2019-A01 | C302: AirCon Service | D302: 44607 | E302: 67 | K302: 1547 | L302: Extract fan in good order. Filter sheet has been replaced
A303: TDU3004 | B303: TDU3004-A01 | C303: AirCon Service | D303: 44607 | E303: 67 | F303: 20 | K303: 1547 | L303: System in good order. Tested cut out and in on stat.
A304: TWW1002 | B304: TWW1002-A01 | C304: AirCon Service | D304: 44544 | E304: 67 | K304: 1659 | L304: System pressures and temperatures are lower than required. Leak tested all joints but no leaks found. System will require full decant and pressure test to repair leak. Room temperature okay for time of year
A305: TKK1004 | B305: TKK1004-A01 | C305: AirCon Service | D305: 44521 | E305: 67 | K305: 1659 | L305: System in good order System passed successful leak test
A306: TDL1005 | B306: TDL1005-A01 | C306: AirCon Service | D306: 44539 | E306: 67 | K306: 1659 | L306: Found system powered down at MCB. Powered up unit and found unit to compressor cutting holes and outdoor fan motor is not running. Phoned outdoor PCBs and outdoor fan motor is faulty which possible inverter fault in compressor. Would recommend full system replacement as cost of repairs to high. System passed F Gas tests
A307: TCE1006 | B307: TCE1006-A01 | C307: AirCon Service | D307: 44509 | E307: 67 | K307: 1659 | L307: System in good order.
A308: TSO1007 | B308: TSO1007-A01 | C308: AirCon Service | D308: 44539 | E308: 67 | K308: 1659 | L308: System in good working order. System passed successful leak test for F Gas
A309: TLS1010 | B309: TLS1010-A01 | C309: AirCon Service | D309: 44543 | E309: 67 | K309: 1659 | L309: System in good order System passed successful leak test
A310: TKE1009 | B310: TKE1009-A01 | C310: AirCon Service | D310: 44499.958 | E310: 67 | K310: 1659 | L310: System cooling g but fab bearings in poor condition System 20 yrs old and should be scheduled for replacement
A311: TGY1012 | B311: TGY1012-A01 | C311: AirCon Service | D311: 44546 | E311: 67 | K311: 1659 | L311: System in good order System passed successful leak test Engineer:
A312: TDU2013 | B312: TDU2013-A01 | C312: AirCon Service | D312: 44510 | E312: 67 | K312: 1659 | L312: System in good order System passed successful leak test
A313: TWX1018 | B313: TWX1018-A01 | C313: AirCon Service | D313: 44544 | E313: 67 | K313: 1659 | L313: System in good order System passed successful leak test New outdoor isolator required
A314: TKE1019 | B314: TKE1019-A01 | C314: AirCon Service | D314: 44543 | E314: 67 | K314: 1659 | L314: System working in good order 2nd No external access System passed successful leak test
A315: TMH1020 | B315: TMH1020-A01 | C315: AirCon Service | D315: 44511 | E315: 67 | K315: 1659 | L315: System in Good order. Pressure and leak test passed.
... A360: TMO1001 | B360: TMO1001-A01 | C360: AirCon Service | D360: 44858.958 | E360: 67 | K360: 1659 | L360: Fan in good mechanical order, controlling correctly via fan thermostat. Cabin panel with filter requires replacement
...

Sheet GENERATOR SERVICE
G1: RADIX COMPANY ROW ID | H1: RADIX PROFILE ROW ID
A2: Site | B2: Generator | C2: Service Type | D2: Fuel Delivered | E2: Tank State after Refuel | F2: Comments | G2: Serviced By | H2: Detailed entered by
A3: TTP1041 | B3: TTP1041-G01 | C3: On-Load Run | F3: None | G3: 67 | H3: 3616
A4: TDU3018 | B4: TDU3018-G01 | C4: Off-Load Run | F4: None | G4: 67 | H4: 3616
A5: TCK1042 | B5: TCK1042-G01 | C5: Oil Service | F5: None | G5: 67 | H5: 3616
A6: TTP1041 | B6: TTP1041-G01 | C6: Full Service | F6: None | G6: 67 | H6: 3616
A7: TDU3018 | B7: TDU3018-G01 | C7: Refuel | D7: 200 | E7: Full | F7: None | G7: 67 | H7: 3616
A8: TCK1042 | B8: TCK1042-G01 | C8: Refuel | D8: 120 | E8: 3/4 | F8: None | G8: 67 | H8: 3616

Sheet E&LP SERVICE
C1: RADIX COMPANY ROW ID
A2: Site | B2: Test Date | C2: Tested By | D2: Detailed entered by | E2: Comments
A3: TMO1001 | B3: 45689 | C3: 67 | D3: 3616 | E3: No comment
A4: TWW1002 | B4: 45690 | C4: 67 | D4: 3616 | E4: No comment
A5: TLK1003 | B5: 45691 | C5: 67 | D5: 3616 | E5: No comment
A6: TKK1004 | B6: 45692 | C6: 67 | D6: 3616 | E6: No comment
A7: TDU3018 | B7: 45693 | C7: 67 | D7: 3616 | E7: No comment
A8: TCK1042 | B8: 45694 | C8: 67 | D8: 3616 | E8: No comment

Sheet AWL
A2: Site | B2: Structure | C2: AWL Type | D2: Intensity | E2: Height
A3: TMO1001 | B3: TMO1001-T01 | C3: AWL T1 | D3: High | E3: 106
A4: TMO1001 | B4: TMO1001-T01 | C4: AWL T2 | D4: Medium | E4: 80
A5: TMO1001 | B5: TMO1001-T01 | C5: AWL T1 | D5: High | E5: 60
A6: TMO1001 | B6: TMO1001-T01 | C6: AWL T2 | D6: Medium | E6: 40
A7: TMO1001 | B7: TMO1001-T01 | C7: AWL T1 | D7: Low | E7: 25
A8: TMO2002 | B8: TMO2002-T01 | C8: AWL T1 | D8: High | E8: 83
A9: TMO2002 | B9: TMO2002-T01 | C9: AWL T2 | D9: Medium | E9: 60
A10: TMO2002 | B10: TMO2002-T01 | C10: AWL T1 | D10: High | E10: 40
A11: TSO1007 | B11: TSO1007-T01 | C11: AWL T1 | D11: High | E11: 63
A12: TSO1007 | B12: TSO1007-T01 | C12: AWL T2 | D12: Medium | E12: 40
A13: TKE1009 | B13: TKE1009-T01 | C13: AWL T1 | D13: High | E13: 71
A14: TKE1009 | B14: TKE1009-T01 | C14: AWL T2 | D14: Medium | E14: 55
... A30: TWX2037 | B30: TWX2037-T01 | C30: AWL T7 | D30: High | E30: 66

Sheet PLANNING
L1: RADIX COMPANY ROW ID | M1: RADIX PROFILE ROW ID
A2: Planning Record ID | B2: Site | C2: Infrastructure | D2: Current Planning Record for Structure | E2: In Progress Planning Record for Structure | F2: Planning Type | G2: Planning Status | H2: Planning Expiry Date | I2: Comments | J2: Local Authority | K2: Local Authority Reference | L2: Planning Company | M2: Planner | N2: Forecast Submission Date | O2: Submitted Date | P2: FI Requested | Q2: FI Submitted | R2: Notification of Decision Date | S2: Local Authority Decision | T2: Local Authority Final Decision Date | U2: Restricted | V2: Conditions | W2: Conditions Discharged | X2: Conditions Outstanding | Y2: Financial Condition Status | Z2: Financial Condition Amount | AA2: 1st Party Appeal | AB2: 3rd Party Appeal | AC2: Financial Appeal | AD2: ACP Reference | AE2: Appeal Submission Date | AF2: ACP Decision | AG2: ACP Forecast Decision Date | AH2: ACP Decision Date | AI2: Section 5 Submitted | AJ2: Section 5 Decided | AK2: Section 5 Reference | AL2: Section 5 Decision | AM2: Section 5 Comment | AN2: Risk Level | AO2: C.R. Sensitivity | AP2: C.R. Comments | AQ2: P.R. Sensitivity | AR2: P.R. Comments | AS2: Judicial Review Status | AT2: JR Application Made | AU2: Hearing Commencement | AV2: JR Comments | AW2: JR Result | AX2: Planning Designer
A3: PLN-00001 | B3: TKY6028 | C3: TKY6028-T01 | D3: YES | E3: YES | F3: Full Planning | G3: Lifetime Grant | J3: Kerry County | K3: 19/1237 | O3: 39402 | U3: 1 | AN3: High | AO3: High | AP3: Beside house - Sensitive PR | AQ3: High
A4: PLN-00002 | B4: TWW3001 | C4: TWW3001-T01 | D4: YES | E4: YES | F4: State Planning Exemption | G4: Exempt | I4: 28/03/1974 - planning for extension to existing telephone exchange at Arklow planing ref P24/74 decision 10/04/1974 with no conditions P130/2004 new entrance to eircom site conditions do not impact mast | J4: Wicklow County | K4: P24/74 | O4: 27116 | S4: Lifetime Grant | T4: 27116 | U4: 0 | V4: nil
A5: PLN-00003 | B5: TWW5005 | C5: TWW5005-R01 | D5: YES | E5: YES | F5: Licence Notification | G5: Exempt | J5: Wicklow County | S5: n/a | U5: 0
A6: PLN-00004 | B6: TWW5004 | C6: TWW5004-T01 | D6: YES | E6: YES | F6: Full Planning | G6: Expired | H6: 42954.958 | J6: Wicklow County | K6: 03610043 | N6: 42891.958 | T6: 37850.958 | U6: 1
A7: PLN-00005 | B7: TDL2001 | C7: TDL2001-T01 | D7: YES | E7: YES | F7: State Planning Exemption | G7: Exempt | J7: Donegal County | S7: n/a | U7: 0
A8: PLN-00006 | B8: TCN5006 | C8: TCN5006-T01 | D8: YES | E8: YES | F8: Full Planning | G8: Lifetime Grant | J8: Cavan County | K8: 1510 | L8: 117 | O8: 42025 | T8: 42072 | U8: 1 | V8: Ant type &amp; config. in accordance with drawings and cannot be altered without PP | AX8: 117
A9: PLN-00007 | B9: TMH6457 | C9: TMH6457-T01 | D9: YES | E9: YES | F9: Licence Notification | G9: Exempt | I9: LN submitted | J9: Meath County | O9: 40004 | S9: n/a | U9: 1 | W9: N/A | AN9: High | AO9: High | AP9: Beside house - Sensitive Site
A10: PLN-00008 | B10: TWH4001 | C10: TWH4001-T01 | D10: YES | E10: YES | F10: State Planning Exemption | G10: Exempt | J10: Westmeath County | S10: n/a | U10: 0
A11: PLN-00009 | B11: TLK5009 | C11: TLK5009-T01 | D11: YES | E11: YES | F11: Full Planning | G11: Lifetime Grant | J11: Limerick City & County | K11: 309257 | O11: 44119.958 | T11: 44320.958 | U11: 0
A12: PLN-00010 | B12: TGY6318 | C12: TGY6318-T01 | D12: YES | E12: YES | F12: Exempt | G12: Exempt | I12: Planning Complete | J12: Galway City | O12: 39855 | S12: n/a | U12: 1 | W12: N/A | AO12: Low | AP12: -
A13: PLN-00011 | B13: TGY5010 | C13: TGY5010-T01 | D13: YES | E13: YES | F13: Exempt | G13: Exempt | J13: Galway County | S13: n/a | U13: 0
A14: PLN-00012 | B14: TMO6047 | C14: TMO6047-T01 | D14: YES | E14: YES | F14: Full Planning | G14: Lifetime Grant | J14: Mayo County | K14: P13/135 | L14: 64 | O14: 41355 | T14: 41572.958 | U14: 1 | V14: Restrictive condition (Type, Mounting, Config Landscaping scheme Additional equipment requires notification/ planning as necessary. - Planning Grant P13/135 - Ã¢?Â¬5,000 development contributions and restrictions on new equipment | W14: No | X14: Yes | AO14: Low | AP14: -
A15: PLN-00013 | B15: TMO1001 | C15: TMO1001-T01 | D15: YES | E15: YES | F15: State Planning Exemption | G15: Exempt | J15: Mayo County | S15: n/a | U15: 0
A16: PLN-00014 | B16: TCK6005 | C16: TCK6005-T01 | D16: YES | E16: YES | F16: Full Planning | G16: Lifetime Grant | I16: Planning completed | J16: Cork County | K16: 13/06323 | O16: 41616 | T16: 41709 | U16: 0 | V16: eircom planning ref 07/11921 | W16: Yes | X16: No | AO16: Low | AP16: -
A17: PLN-00015 | B17: TGY5016 | C17: TGY5016-R01 | D17: YES | E17: YES | F17: Licence Notification | G17: Licence Notification | J17: Galway County | S17: n/a | U17: 0
A18: PLN-00016 | B18: TMO2002 | C18: TMO2002-T01 | D18: YES | E18: YES | F18: State Planning Exemption | G18: Exempt | J18: Mayo County | S18: n/a | U18: 0
A19: PLN-00017 | B19: TDU5020 | C19: TDU5020-T01 | D19: YES | E19: YES | F19: Full Planning | G19: Lifetime Grant | J19: Dublin - South Dublin | K19: 307377 | O19: 43875 | T19: 44104.958 | U19: 0
A20: PLN-00018 | B20: TKY6029 | C20: TKY6029-T01 | D20: YES | E20: YES | F20: Full Planning | G20: Lifetime Grant | J20: Kerry County | K20: 18/1066 | L20: 67 | O20: 43406 | T20: 43752.958 | U20: 0 | V20: Landscaping to be completed within 6 months cert of compliance and photos to be submitted to the council, co-location allowed, site to be reinstated as agreed with the council prior to removal. | W20: TBC | X20: TBC | AN20: Medium | AO20: High | AP20: Beside house - Sensitive PR | AX20: 67
